Workbook

Sheet KM RODADO
A1: CORREÇÃO TMA LUCRO DESTINO
A2: Trecho | B2: Pallets: 28 | C2: Pallets: 30 | D2: Correção FT | E2: Trecho FT | F2: ID FT
A3: BR04xBR04x29021610.0 | B3: =_xlfn.XLOOKUP(A3&$B$2,Trecho!B:B,Trecho!BR:BR) -> 64 | C3: =_xlfn.XLOOKUP(A3&$C$2,Trecho!B:B,Trecho!BR:BR) -> 79.24 | D3: =IF(C3>B3,"30 MAIOR",IF(B3=C3,"OK","Corrigir")) -> 30 MAIOR | E3: =_xlfn.XLOOKUP(A3&$C$2,Trecho!B:B,Trecho!AD:AD) -> CERVEJARIA CAMAÇARI_10261249-SENDAS DISTRIBUIDORA SA(S4)_30_false | F3: =_xlfn.XLOOKUP(A3&$C$2,Trecho!B:B,Trecho!DH:DH) -> 70528b4a-84b1-478c-b1e4-6b36a04408e9
A4: BR04xBR04x29021490.0 | B4: =_xlfn.XLOOKUP(A4&$B$2,Trecho!B:B,Trecho!BR:BR) -> 1012 | C4: =_xlfn.XLOOKUP(A4&$C$2,Trecho!B:B,Trecho!BR:BR) -> 1012.78 | D4: =IF(C4>B4,"30 MAIOR",IF(B4=C4,"OK","Corrigir")) -> 30 MAIOR | E4: =_xlfn.XLOOKUP(A4&$C$2,Trecho!B:B,Trecho!AD:AD) -> CERVEJARIA CAMAÇARI_10261166-SENDAS DISTRIBUIDORA SA(S4)_30_false | F4: =_xlfn.XLOOKUP(A4&$C$2,Trecho!B:B,Trecho!DH:DH) -> f9696d56-1cc1-4625-ae94-5a2a140653a5
A5: BR04xBR04x29021355.0 | B5: =_xlfn.XLOOKUP(A5&$B$2,Trecho!B:B,Trecho!BR:BR) -> 1173.41 | C5: =_xlfn.XLOOKUP(A5&$C$2,Trecho!B:B,Trecho!BR:BR) -> 1149.92 | D5: =IF(C5>B5,"30 MAIOR",IF(B5=C5,"OK","Corrigir")) -> Corrigir | E5: =_xlfn.XLOOKUP(A5&$C$2,Trecho!B:B,Trecho!AD:AD) -> CERVEJARIA CAMAÇARI_10261066- SENDAS DISTRIBUIDORA SA (S4)_30_false | F5: =_xlfn.XLOOKUP(A5&$C$2,Trecho!B:B,Trecho!DH:DH) -> 3fdbe4f1-0311-487a-b1f3-105b01c5b1ef
A6: BR04xBR04x29021307.0 | B6: =_xlfn.XLOOKUP(A6&$B$2,Trecho!B:B,Trecho!BR:BR) -> 1078 | C6: =_xlfn.XLOOKUP(A6&$C$2,Trecho!B:B,Trecho!BR:BR) -> 989.24 | D6: =IF(C6>B6,"30 MAIOR",IF(B6=C6,"OK","Corrigir")) -> Corrigir | E6: =_xlfn.XLOOKUP(A6&$C$2,Trecho!B:B,Trecho!AD:AD) -> CERVEJARIA CAMAÇARI_10261027-SENDAS DISTRIBUIDORA SA(S4)_30_false | F6: =_xlfn.XLOOKUP(A6&$C$2,Trecho!B:B,Trecho!DH:DH) -> 2d191341-41c1-4e6a-9702-a37db2d97278
A7: BR04xBR04x29021312.0 | B7: =_xlfn.XLOOKUP(A7&$B$2,Trecho!B:B,Trecho!BR:BR) -> 1562.25 | C7: =_xlfn.XLOOKUP(A7&$C$2,Trecho!B:B,Trecho!BR:BR) -> 1560 | D7: =IF(C7>B7,"30 MAIOR",IF(B7=C7,"OK","Corrigir")) -> Corrigir | E7: =_xlfn.XLOOKUP(A7&$C$2,Trecho!B:B,Trecho!AD:AD) -> CERVEJARIA CAMAÇARI_10261032- SENDAS DISTRIBUIDORA S/A LJ119 (S4)_30_false | F7: =_xlfn.XLOOKUP(A7&$C$2,Trecho!B:B,Trecho!DH:DH) -> 524e16ac-a1f4-4333-ab10-277e12c83822
A8: BR04xBR04x29022096.0 | B8: =_xlfn.XLOOKUP(A8&$B$2,Trecho!B:B,Trecho!BR:BR) -> 199.17 | C8: =_xlfn.XLOOKUP(A8&$C$2,Trecho!B:B,Trecho!BR:BR) -> 210.7 | D8: =IF(C8>B8,"30 MAIOR",IF(B8=C8,"OK","Corrigir")) -> 30 MAIOR | E8: =_xlfn.XLOOKUP(A8&$C$2,Trecho!B:B,Trecho!AD:AD) -> CERVEJARIA CAMAÇARI_10261587- ATACADAO S A (S4)_30_false | F8: =_xlfn.XLOOKUP(A8&$C$2,Trecho!B:B,Trecho!DH:DH) -> 02b00b6d-201d-44cd-924e-1b7acc63a6a2
A9: BR04xBR04x29021848.0 | B9: =_xlfn.XLOOKUP(A9&$B$2,Trecho!B:B,Trecho!BR:BR) -> 2342.78 | C9: =_xlfn.XLOOKUP(A9&$C$2,Trecho!B:B,Trecho!BR:BR) -> 2341.84 | D9: =IF(C9>B9,"30 MAIOR",IF(B9=C9,"OK","Corrigir")) -> Corrigir | E9: =_xlfn.XLOOKUP(A9&$C$2,Trecho!B:B,Trecho!AD:AD) -> CERVEJARIA CAMAÇARI_10261402-SUPERMERCADO COMETA LTDA(S4)_30_false | F9: =_xlfn.XLOOKUP(A9&$C$2,Trecho!B:B,Trecho!DH:DH) -> ea8a6297-8102-4be2-90b7-c824eaae8cc3
A10: BR04xBR04x29021611.0 | B10: =_xlfn.XLOOKUP(A10&$B$2,Trecho!B:B,Trecho!BR:BR) -> 109 | C10: =_xlfn.XLOOKUP(A10&$C$2,Trecho!B:B,Trecho!BR:BR) -> 107.96 | D10: =IF(C10>B10,"30 MAIOR",IF(B10=C10,"OK","Corrigir")) -> Corrigir | E10: =_xlfn.XLOOKUP(A10&$C$2,Trecho!B:B,Trecho!AD:AD) -> CERVEJARIA CAMAÇARI_10261250- SENDAS DISTRIBUIDORA SA (S4)_30_false | F10: =_xlfn.XLOOKUP(A10&$C$2,Trecho!B:B,Trecho!DH:DH) -> 8ae9cfbe-1ea5-4262-9e94-8903e3b0e235
A11: BR04xBR04x29023180.0 | B11: =_xlfn.XLOOKUP(A11&$B$2,Trecho!B:B,Trecho!BR:BR) -> 1558.89 | C11: =_xlfn.XLOOKUP(A11&$C$2,Trecho!B:B,Trecho!BR:BR) -> 1598.52 | D11: =IF(C11>B11,"30 MAIOR",IF(B11=C11,"OK","Corrigir")) -> 30 MAIOR | E11: =_xlfn.XLOOKUP(A11&$C$2,Trecho!B:B,Trecho!AD:AD) -> CERVEJARIA CAMAÇARI_10262331-ATACADAO S A(S4)_30_false | F11: =_xlfn.XLOOKUP(A11&$C$2,Trecho!B:B,Trecho!DH:DH) -> 67942aa0-52ec-4eef-a049-4601aaab0dc3
A12: BR04xBR04x29022977.0 | B12: =_xlfn.XLOOKUP(A12&$B$2,Trecho!B:B,Trecho!BR:BR) -> 1559.85 | C12: =_xlfn.XLOOKUP(A12&$C$2,Trecho!B:B,Trecho!BR:BR) -> 1548.12 | D12: =IF(C12>B12,"30 MAIOR",IF(B12=C12,"OK","Corrigir")) -> Corrigir | E12: =_xlfn.XLOOKUP(A12&$C$2,Trecho!B:B,Trecho!AD:AD) -> CERVEJARIA CAMAÇARI_10262178- DISTCARNES DISTRIBUIDORA CARNES (S4)_30_false | F12: =_xlfn.XLOOKUP(A12&$C$2,Trecho!B:B,Trecho!DH:DH) -> 48494a73-80ad-4ac0-9dc7-35f06d15df50
A13: BR04xBR04x29022696.0 | B13: =_xlfn.XLOOKUP(A13&$B$2,Trecho!B:B,Trecho!BR:BR) -> 854 | C13: =_xlfn.XLOOKUP(A13&$C$2,Trecho!B:B,Trecho!BR:BR) -> 857.98 | D13: =IF(C13>B13,"30 MAIOR",IF(B13=C13,"OK","Corrigir")) -> 30 MAIOR | E13: =_xlfn.XLOOKUP(A13&$C$2,Trecho!B:B,Trecho!AD:AD) -> CERVEJARIA CAMAÇARI_10262021- SENDAS DISTRIBUIDORA SA (S4)_30_false | F13: =_xlfn.XLOOKUP(A13&$C$2,Trecho!B:B,Trecho!DH:DH) -> 28687a62-36fa-4ec8-bd49-fbdd0f051bff
A14: BR04xBR04x29022588.0 | B14: =_xlfn.XLOOKUP(A14&$B$2,Trecho!B:B,Trecho!BR:BR) -> 205.37 | C14: =_xlfn.XLOOKUP(A14&$C$2,Trecho!B:B,Trecho!BR:BR) -> 210.7 | D14: =IF(C14>B14,"30 MAIOR",IF(B14=C14,"OK","Corrigir")) -> 30 MAIOR | E14: =_xlfn.XLOOKUP(A14&$C$2,Trecho!B:B,Trecho!AD:AD) -> CERVEJARIA CAMAÇARI_10261944-MERCANTIL RODRIGUES COMERCIAL LTDA(S4)_30_false | F14: =_xlfn.XLOOKUP(A14&$C$2,Trecho!B:B,Trecho!DH:DH) -> 5282d2a6-1c22-4725-a13c-0f34475f3585
... A1110: BR31xBR04xBR8S | B1110: =_xlfn.XLOOKUP(A1110&$B$2,Trecho!B:B,Trecho!BR:BR) -> 2046.12 | C1110: =_xlfn.XLOOKUP(A1110&$C$2,Trecho!B:B,Trecho!BR:BR) -> 2046.12 | D1110: =IF(C1110>B1110,"30 MAIOR",IF(B1110=C1110,"OK","Corrigir")) -> OK | E1110: =_xlfn.XLOOKUP(A1110&$C$2,Trecho!B:B,Trecho!AD:AD) -> CERVEJARIA CAMAÇARI_CD NATAL_30_false | F1110: =_xlfn.XLOOKUP(A1110&$C$2,Trecho!B:B,Trecho!DH:DH) -> 7141d25d-045a-4ac3-8ca0-db134c9555f7

Sheet Trecho
A1: Trecho | C1: Vigencia | D1: Unidade - CNPJ | E1: Unidade - Nome | F1: Unidade SAP | G1: Unidade TMS | H1: Unidade - Promax UNB | I1: Unidade - Regional | J1: Operador - CNPJ | K1: Operador - Nome | L1: Operador - SAP | M1: Operador - TMS | N1: Operador - Promax | O1: Organizacao de Compras | P1: Prazo Pagamento | Q1: Capacidade | R1: Destino | S1: destino SAP | T1: destino TMS | U1: F-MOV | V1: Origem | W1: origem SAP | X1: origem TMS | Y1: cargaHorariaMotoristaPuxadaMensal | Z1: cargaHorariaPorTrajetoMinuto | AA1: cargaHorariaPorTrajetoMinutoLucro | AB1: cargaHorarioTrajetoDia | AC1: cargaHorarioTrajetoMes | AD1: chaveTrecho | AE1: cnpjIda | AF1: cnpjVolta | AG1: consumoDieselAjustado | AH1: custoDaDiaria | AI1: custoDoTr | AJ1: diasMes | AK1: dieselConsumoDieselReaisKM | AL1: dieselConsumoKmL | AM1: fatorMotoristaAjustado | AN1: fatorMotoristaIndicado | AO1: faturamentoDestinoObrigatorio | AP1: freteComCprb | AQ1: freteCtrc | AR1: freteLiquido | AS1: fretePTms | AT1: fretePisCofins | AU1: freteReaisKMDiesel | AV1: freteReaisKMLavagem | AW1: freteReaisKMLucroVariavel | AX1: freteReaisKMManutencaoCarreta | AY1: freteReaisKMManutencaoCavalo | AZ1: freteReaisKMPedagio | BA1: freteReaisKMPneu | BB1: freteReaisKMSalarioVariavel | BC1: freteReaisKMSeguro | BD1: freteReaisViagemDiesel | BE1: freteReaisViagemLavagem | BF1: freteReaisViagemLucroVariavel | BG1: freteReaisViagemManutencaoCarreta | BH1: freteReaisViagemManutencaoCavalo | BI1: freteReaisViagemPedagio | BJ1: freteReaisViagemPneus | BK1: freteReaisViagemSalarioVariavel | BL1: freteReaisViagemSeguro | BM1: frotaNoMunicipio | BN1: gradeCarregamento | BO1: icmsIss | BP1: impostosIcmsIss | BQ1: kmIda | BR1: kmRodado | BS1: kmRodadoMesPorEquipe | BT1: kmRodadoMesPorEquipeLucro | BU1: kmVolta | BV1: lavagemReaisKm | BW1: lucroVariavelReaisKm | BX1: manutencaoCavalo | BY1: manutencaoImplementoReaiskm | BZ1: observacao | CA1: pedagio | CB1: pedagioPorEixoIdaVolta | CC1: pedagioReaisKM | CD1: percentualIcmsIss | CE1: percentualPerdaDescartavel | CF1: percentualPerdaKm | CG1: percentualPerdaRegiao | CH1: pneuCustoPneusCamarasReaisKm | CI1: pneuQuantidadeDePneus | CJ1: pneuValorDeVendaDaCarcaca | CK1: pneuValorMedioDaRecapagem | CL1: pneuValorMedioPneus | CM1: pneuVidautilPneu | CN1: premioProdutividadeFatorMotorista | CO1: premioProdutividadeKmRodado | CP1: premioProdutividadeSalarioVariavel | CQ1: premioProdutividadeSalarioVariavelReaisKm | CR1: previsaoViagens | CS1: regiaoEmpurrada | CT1: seguro | CU1: seguroReaiskm | CV1: tempoInternoDestino | CW1: tempoInternoDestinoLucro | CX1: tempoInternoOrigem | CY1: tempoInternoOrigemLucro | CZ1: tempoRefeicaoMinuto | DA1: tempoTrajetoFabricaCDMinuto | DB1: trechoComDiaria | DC1: trechoComVr | DD1: turnoEmpurrada | DE1: turnosFabrica | DF1: velocidadeMediaKmH | DG1: vidautilAjustadaPneu | DH1: _id
A2: =F2&"x"&W2&"x"&S2 -> BR04xBR04x142200.0 | B2: =F2&"x"&W2&"x"&S2&Q2 -> BR04xBR04x142200.0Pallets: 28 | C2: EMPURRADA_1_9_2026 | D2: 07526557001505_CERV | E2: CAMAÇARI | F2: BR04 | I2: Geo NE | J2: 20618821000799 | K2: OPERALOG | L2: 390268 | N2: 1 | Q2: Pallets: 28 | R2: Unidade: ASA BRANCA | Região: null | S2: 142200.0 | T2: Revenda | U2: FALSE | V2: Unidade: CERVEJARIA CAMAÇARI | Região: NE | W2: BR04 | X2: 421 | Y2: 12500 | Z2: 2806.13 | AA2: 2927.43 | AB2: 1440 | AC2: 36000 | AD2: CERVEJARIA CAMAÇARI_ASA BRANCA_28_false | AE2: 0 | AF2: 0 | AG2: 1.92 | AH2: 115.5 | AI2: 0 | AJ2: 25 | AK2: 3.53 | AL2: 1.92 | AM2: 3 | AN2: 2.88 | AO2: FALSE | AP2: 20209.64 | AQ2: 25306.33 | AR2: 19984.42 | AS2: 20209.64 | AT2: 22269.57 | AU2: 3.53 | AV2: 0.01 | AW2: 0.22 | AX2: 0.1 | AY2: 0.31 | AZ2: 0 | BA2: 0.39 | BB2: 0.46 | BC2: 0 | BD2: 9474.39 | BE2: 19.15 | BF2: 581.07 | BG2: 268.14 | BH2: 819.59 | BI2: 6563.2 | BJ2: 1042.17 | BK2: 1216.7 | BL2: 0 | BM2: FALSE | BN2: 1440 | BO2: 12 | BP2: 3079.56 | BQ2: 1305.63 | BR2: 2686.13 | BS2: 30152.95 | BT2: 28903.54 | BU2: 1380.5 | BV2: 0.01 | BW2: 0.22 | BX2: 0.31 | BY2: 0.1 | CA2: 0 | CB2: 0 | CC2: 0 | CD2: 12 | CE2: 0 | CF2: 0 | CG2: 0 | CH2: 0.39 | CI2: 28.22 | CJ2: 0 | CK2: 437.68 | CL2: 1907.11 | CM2: 202400 | CN2: 3 | CO2: 30152.95 | CP2: 4611.33 | CQ2: 0.46 | CR2: 0.45 | CS2: Região: NE | CT2: 0 | CU2: 0 | CV2: 60 | CW2: 60 | CX2: 60 | CY2: 181.3 | CZ2: 60 | DA2: 2686.13 | DB2: TRUE | DC2: FALSE | DD2: Cargo: MODELO EQUIPE ATIVA ATUAL | DE2: 3 | DF2: 60 | DG2: 202400 | DH2: c1f9a7c0-81c9-43a6-bf14-77e59275d93d
A3: =F3&"x"&W3&"x"&S3 -> BR04xBR04x29021610.0 | B3: =F3&"x"&W3&"x"&S3&Q3 -> BR04xBR04x29021610.0Pallets: 28 | C3: EMPURRADA_1_9_2026 | D3: 07526557001505_CERV | E3: CAMAÇARI | F3: BR04 | I3: Geo NE | J3: 20618821000799 | K3: OPERALOG | L3: 390268 | N3: 1 | Q3: Pallets: 28 | R3: Unidade: 10261249-SENDAS DISTRIBUIDORA SA(S4) | Região: 0 | S3: 29021610.0 | T3: 792071.0 | U3: FALSE | V3: Unidade: CERVEJARIA CAMAÇARI | Região: NE | W3: BR04 | X3: 421 | Y3: 12500 | Z3: 184 | AA3: 305.3 | AB3: 1440 | AC3: 36000 | AD3: CERVEJARIA CAMAÇARI_10261249-SENDAS DISTRIBUIDORA SA(S4)_28_false | AE3: null | AF3: null | AG3: 1.92 | AH3: 0 | AI3: 31 | AJ3: 25 | AK3: 3.53 | AL3: 1.92 | AM3: 3 | AN3: 2.88 | AO3: FALSE | AP3: 1746.9 | AQ3: 2347.51 | AR3: 1726.03 | AS3: 1746.9 | AT3: 1924.96 | AU3: 3.53 | AV3: 0.02 | AW3: 0.95 | AX3: 0.1 | AY3: 0.31 | AZ3: 0 | BA3: 0.39 | BB3: 1.26 | BC3: 0 | BD3: 225.74 | BE3: 1.26 | BF3: 60.6 | BG3: 6.39 | BH3: 19.53 | BI3: 1307.91 | BJ3: 24.83 | BK3: 79.78 | BL3: 0 | BM3: FALSE | BN3: 1440 | BO3: 18 | BP3: 432.22 | BQ3: 32 | BR3: 64 | BS3: 10956.52 | BT3: 6603.34 | BU3: 32 | BV3: 0.02 | BW3: 0.95 | BX3: 0.31 | BY3: 0.1 | BZ3: null | CA3: 0 | CB3: 0 | CC3: 0 | CD3: 18 | CE3: 0 | CF3: 0 | CG3: 0 | CH3: 0.39 | CI3: 28.22 | CJ3: 0 | CK3: 437.68 | CL3: 1907.11 | CM3: 202400 | CN3: 3 | CO3: 10956.52 | CP3: 4611.33 | CQ3: 1.26 | CR3: 6.85 | CS3: Região: NE | CT3: 0 | CU3: 0 | CV3: 60 | CW3: 60 | CX3: 60 | CY3: 181.3 | CZ3: 60 | DA3: 64 | DB3: FALSE | DC3: TRUE | DD3: Cargo: MODELO EQUIPE ATIVA ATUAL | DE3: 3 | DF3: 60 | DG3: 202400 | DH3: 2caf369f-3b1e-4b24-9ff7-79f6c03b0447
A4: =F4&"x"&W4&"x"&S4 -> BR04xBR04x29021490.0 | B4: =F4&"x"&W4&"x"&S4&Q4 -> BR04xBR04x29021490.0Pallets: 28 | C4: EMPURRADA_1_9_2026 | D4: 07526557001505_CERV | E4: CAMAÇARI | F4: BR04 | I4: Geo NE | J4: 20618821000799 | K4: OPERALOG | L4: 390268 | N4: 1 | Q4: Pallets: 28 | R4: Unidade: 10261166-SENDAS DISTRIBUIDORA SA(S4) | Região: 0 | S4: 29021490.0 | T4: 790443.0 | U4: FALSE | V4: Unidade: CERVEJARIA CAMAÇARI | Região: NE | W4: BR04 | X4: 421 | Y4: 12500 | Z4: 1132 | AA4: 1253.3 | AB4: 1440 | AC4: 36000 | AD4: CERVEJARIA CAMAÇARI_10261166-SENDAS DISTRIBUIDORA SA(S4)_28_false | AE4: null | AF4: null | AG4: 1.92 | AH4: 115.5 | AI4: 0 | AJ4: 25 | AK4: 3.53 | AL4: 1.92 | AM4: 3 | AN4: 2.88 | AO4: FALSE | AP4: 7608.29 | AQ4: 10224.13 | AR4: 7517.37 | AS4: 7608.29 | AT4: 8383.79 | AU4: 3.53 | AV4: 0.01 | AW4: 0.25 | AX4: 0.1 | AY4: 0.31 | AZ4: 0 | BA4: 0.39 | BB4: 0.49 | BC4: 0 | BD4: 3569.48 | BE4: 7.73 | BF4: 248.77 | BG4: 101.02 | BH4: 308.78 | BI4: 2398.14 | BJ4: 392.64 | BK4: 490.82 | BL4: 0 | BM4: FALSE | BN4: 1440 | BO4: 18 | BP4: 1882.46 | BQ4: 506 | BR4: 1012 | BS4: 28160.78 | BT4: 25435.25 | BU4: 506 | BV4: 0.01 | BW4: 0.25 | BX4: 0.31 | BY4: 0.1 | BZ4: null | CA4: 0 | CB4: 0 | CC4: 0 | CD4: 18 | CE4: 0 | CF4: 0 | CG4: 0 | CH4: 0.39 | CI4: 28.22 | CJ4: 0 | CK4: 437.68 | CL4: 1907.11 | CM4: 202400 | CN4: 3 | CO4: 28160.78 | CP4: 4611.33 | CQ4: 0.49 | CR4: 1.11 | CS4: Região: NE | CT4: 0 | CU4: 0 | CV4: 60 | CW4: 60 | CX4: 60 | CY4: 181.3 | CZ4: 60 | DA4: 1012 | DB4: TRUE | DC4: FALSE | DD4: Cargo: MODELO EQUIPE ATIVA ATUAL | DE4: 3 | DF4: 60 | DG4: 202400 | DH4: 221c6bb6-1d3f-4866-93a2-1c47598d50d7
A5: =F5&"x"&W5&"x"&S5 -> BR04xBR04x29021355.0 | B5: =F5&"x"&W5&"x"&S5&Q5 -> BR04xBR04x29021355.0Pallets: 28 | C5: EMPURRADA_1_9_2026 | D5: 07526557001505_CERV | E5: CAMAÇARI | F5: BR04 | I5: Geo NE | J5: 20618821000799 | K5: OPERALOG | L5: 390268 | N5: 1 | Q5: Pallets: 28 | R5: Unidade: 10261066-SENDAS DISTRIBUIDORA SA(S4) | Região: 0 | S5: 29021355.0 | T5: 789127.0 | U5: FALSE | V5: Unidade: CERVEJARIA CAMAÇARI | Região: NE | W5: BR04 | X5: 421 | Y5: 12500 | Z5: 1293.41 | AA5: 1414.71 | AB5: 1440 | AC5: 36000 | AD5: CERVEJARIA CAMAÇARI_10261066-SENDAS DISTRIBUIDORA SA(S4)_28_false | AE5: null | AF5: null | AG5: 1.92 | AH5: 115.5 | AI5: 0 | AJ5: 25 | AK5: 3.53 | AL5: 1.92 | AM5: 3 | AN5: 2.88 | AO5: FALSE | AP5: 9504.84 | AQ5: 11901.87 | AR5: 9398.91 | AS5: 9504.84 | AT5: 10473.65 | AU5: 3.53 | AV5: 0.01 | AW5: 0.24 | AX5: 0.1 | AY5: 0.31 | AZ5: 0 | BA5: 0.39 | BB5: 0.48 | BC5: 0 | BD5: 4138.8 | BE5: 8.83 | BF5: 280.81 | BG5: 117.14 | BH5: 358.03 | BI5: 3479.25 | BJ5: 455.26 | BK5: 560.8 | BL5: 0 | BM5: FALSE | BN5: 1440 | BO5: 12 | BP5: 1448.36 | BQ5: 595.06 | BR5: 1173.41 | BS5: 28577.49 | BT5: 26127.2 | BU5: 578.35 | BV5: 0.01 | BW5: 0.24 | BX5: 0.31 | BY5: 0.1 | BZ5: null | CA5: 0 | CB5: 0 | CC5: 0 | CD5: 12 | CE5: 0 | CF5: 0 | CG5: 0 | CH5: 0.39 | CI5: 28.22 | CJ5: 0 | CK5: 437.68 | CL5: 1907.11 | CM5: 202400 | CN5: 3 | CO5: 28577.49 | CP5: 4611.33 | CQ5: 0.48 | CR5: 0.97 | CS5: Região: NE | CT5: 0 | CU5: 0 | CV5: 60 | CW5: 60 | CX5: 60 | CY5: 181.3 | CZ5: 60 | DA5: 1173.41 | DB5: TRUE | DC5: FALSE | DD5: Cargo: MODELO EQUIPE ATIVA ATUAL | DE5: 3 | DF5: 60 | DG5: 202400 | DH5: a43e452c-0095-4512-86bd-f48529a503bc
A6: =F6&"x"&W6&"x"&S6 -> BR04xBR04x29021307.0 | B6: =F6&"x"&W6&"x"&S6&Q6 -> BR04xBR04x29021307.0Pallets: 28 | C6: EMPURRADA_1_9_2026 | D6: 07526557001505_CERV | E6: CAMAÇARI | F6: BR04 | I6: Geo NE | J6: 20618821000799 | K6: OPERALOG | L6: 390268 | N6: 1 | Q6: Pallets: 28 | R6: Unidade: 10261027-SENDAS DISTRIBUIDORA SA(S4) | Região: 0 | S6: 29021307.0 | T6: 788759.0 | U6: FALSE | V6: Unidade: CERVEJARIA CAMAÇARI | Região: NE | W6: BR04 | X6: 421 | Y6: 12500 | Z6: 1198 | AA6: 1319.3 | AB6: 1440 | AC6: 36000 | AD6: CERVEJARIA CAMAÇARI_10261027-SENDAS DISTRIBUIDORA SA(S4)_28_false | AE6: null | AF6: null | AG6: 1.92 | AH6: 115.5 | AI6: 0 | AJ6: 25 | AK6: 3.53 | AL6: 1.92 | AM6: 3 | AN6: 2.88 | AO6: FALSE | AP6: 7899.97 | AQ6: 10616.09 | AR6: 7805.56 | AS6: 7899.97 | AT6: 8705.2 | AU6: 3.53 | AV6: 0.01 | AW6: 0.24 | AX6: 0.1 | AY6: 0.31 | AZ6: 0 | BA6: 0.39 | BB6: 0.49 | BC6: 0 | BD6: 3802.27 | BE6: 8.18 | BF6: 261.87 | BG6: 107.61 | BH6: 328.92 | BI6: 2359.04 | BJ6: 418.24 | BK6: 519.43 | BL6: 0 | BM6: FALSE | BN6: 1440 | BO6: 18 | BP6: 1954.63 | BQ6: 539 | BR6: 1078 | BS6: 28344.74 | BT6: 25738.65 | BU6: 539 | BV6: 0.01 | BW6: 0.24 | BX6: 0.31 | BY6: 0.1 | BZ6: null | CA6: 0 | CB6: 0 | CC6: 0 | CD6: 18 | CE6: 0 | CF6: 0 | CG6: 0 | CH6: 0.39 | CI6: 28.22 | CJ6: 0 | CK6: 437.68 | CL6: 1907.11 | CM6: 202400 | CN6: 3 | CO6: 28344.74 | CP6: 4611.33 | CQ6: 0.49 | CR6: 1.05 | CS6: Região: NE | CT6: 0 | CU6: 0 | CV6: 60 | CW6: 60 | CX6: 60 | CY6: 181.3 | CZ6: 60 | DA6: 1078 | DB6: TRUE | DC6: FALSE | DD6: Cargo: MODELO EQUIPE ATIVA ATUAL | DE6: 3 | DF6: 60 | DG6: 202400 | DH6: 70b668fb-771c-4cae-82f0-3a25d580d775
A7: =F7&"x"&W7&"x"&S7 -> BR04xBR04x29021312.0 | B7: =F7&"x"&W7&"x"&S7&Q7 -> BR04xBR04x29021312.0Pallets: 28 | C7: EMPURRADA_1_9_2026 | D7: 07526557001505_CERV | E7: CAMAÇARI | F7: BR04 | I7: Geo NE | J7: 20618821000799 | K7: OPERALOG | L7: 390268 | N7: 1 | Q7: Pallets: 28 | R7: Unidade: 10261032-SENDAS DISTRIBUIDORA SA(S4) | Região: 0 | S7: 29021312.0 | T7: 788732.0 | U7: FALSE | V7: Unidade: CERVEJARIA CAMAÇARI | Região: NE | W7: BR04 | X7: 421 | Y7: 12500 | Z7: 1682.25 | AA7: 1803.55 | AB7: 1440 | AC7: 36000 | AD7: CERVEJARIA CAMAÇARI_10261032-SENDAS DISTRIBUIDORA SA(S4)_28_false | AE7: null | AF7: null | AG7: 1.92 | AH7: 115.5 | AI7: 0 | AJ7: 25 | AK7: 3.53 | AL7: 1.92 | AM7: 3 | AN7: 2.88 | AO7: FALSE | AP7: 12086.48 | AQ7: 15134.59 | AR7: 11951.79 | AS7: 12086.48 | AT7: 13318.44 | AU7: 3.53 | AV7: 0.01 | AW7: 0.23 | AX7: 0.1 | AY7: 0.31 | AZ7: 0 | BA7: 0.39 | BB7: 0.47 | BC7: 0 | BD7: 5510.3 | BE7: 11.48 | BF7: 357.99 | BG7: 155.95 | BH7: 476.67 | BI7: 4103.87 | BJ7: 606.12 | BK7: 729.4 | BL7: 0 | BM7: FALSE | BN7: 1440 | BO7: 12 | BP7: 1841.75 | BQ7: 784.43 | BR7: 1562.25 | BS7: 29253.01 | BT7: 27285.56 | BU7: 777.82 | BV7: 0.01 | BW7: 0.23 | BX7: 0.31 | BY7: 0.1 | BZ7: null | CA7: 0 | CB7: 0 | CC7: 0 | CD7: 12 | CE7: 0 | CF7: 0 | CG7: 0 | CH7: 0.39 | CI7: 28.22 | CJ7: 0 | CK7: 437.68 | CL7: 1907.11 | CM7: 202400 | CN7: 3 | CO7: 29253.01 | CP7: 4611.33 | CQ7: 0.47 | CR7: 0.75 | CS7: Região: NE | CT7: 0 | CU7: 0 | CV7: 60 | CW7: 60 | CX7: 60 | CY7: 181.3 | CZ7: 60 | DA7: 1562.25 | DB7: TRUE | DC7: FALSE | DD7: Cargo: MODELO EQUIPE ATIVA ATUAL | DE7: 3 | DF7: 60 | DG7: 202400 | DH7: 3f605636-6d2e-4eb9-af1d-1c0636749866
A8: =F8&"x"&W8&"x"&S8 -> BR04xBR04x29022096.0 | B8: =F8&"x"&W8&"x"&S8&Q8 -> BR04xBR04x29022096.0Pallets: 28 | C8: EMPURRADA_1_9_2026 | D8: 07526557001505_CERV | E8: CAMAÇARI | F8: BR04 | I8: Geo NE | J8: 20618821000799 | K8: OPERALOG | L8: 390268 | N8: 1 | Q8: Pallets: 28 | R8: Unidade: 10261587-ATACADAO S A(S4) | Região: 0 | S8: 29022096.0 | T8: 796239.0 | U8: FALSE | V8: Unidade: CERVEJARIA CAMAÇARI | Região: NE | W8: BR04 | X8: 421 | Y8: 12500 | Z8: 319.17 | AA8: 440.47 | AB8: 1440 | AC8: 36000 | AD8: CERVEJARIA CAMAÇARI_10261587-ATACADAO S A(S4)_28_false | AE8: null | AF8: null | AG8: 1.92 | AH8: 0 | AI8: 31 | AJ8: 25 | AK8: 3.53 | AL8: 1.92 | AM8: 3 | AN8: 2.88 | AO8: FALSE | AP8: 2556.83 | AQ8: 3435.91 | AR8: 2526.28 | AS8: 2556.83 | AT8: 2817.45 | AU8: 3.53 | AV8: 0.01 | AW8: 0.44 | AX8: 0.1 | AY8: 0.31 | AZ8: 0 | BA8: 0.39 | BB8: 0.7 | BC8: 0 | BD8: 702.5 | BE8: 2.18 | BF8: 87.43 | BG8: 19.88 | BH8: 60.77 | BI8: 1437.85 | BJ8: 77.27 | BK8: 138.39 | BL8: 0 | BM8: FALSE | BN8: 1440 | BO8: 18 | BP8: 632.62 | BQ8: 100.55 | BR8: 199.17 | BS8: 19656.78 | BT8: 14243.55 | BU8: 98.62 | BV8: 0.01 | BW8: 0.44 | BX8: 0.31 | BY8: 0.1 | BZ8: null | CA8: 0 | CB8: 0 | CC8: 0 | CD8: 18 | CE8: 0 | CF8: 0 | CG8: 0 | CH8: 0.39 | CI8: 28.22 | CJ8: 0 | CK8: 437.68 | CL8: 1907.11 | CM8: 202400 | CN8: 3 | CO8: 19656.78 | CP8: 4611.33 | CQ8: 0.7 | CR8: 3.95 | CS8: Região: NE | CT8: 0 | CU8: 0 | CV8: 60 | CW8: 60 | CX8: 60 | CY8: 181.3 | CZ8: 60 | DA8: 199.17 | DB8: FALSE | DC8: TRUE | DD8: Cargo: MODELO EQUIPE ATIVA ATUAL | DE8: 3 | DF8: 60 | DG8: 202400 | DH8: 3475189a-5709-40ca-bcb8-39cecc1b8c4d
A9: =F9&"x"&W9&"x"&S9 -> BR04xBR04x29021848.0 | B9: =F9&"x"&W9&"x"&S9&Q9 -> BR04xBR04x29021848.0Pallets: 28 | C9: EMPURRADA_1_9_2026 | D9: 07526557001505_CERV | E9: CAMAÇARI | F9: BR04 | I9: Geo NE | J9: 20618821000799 | K9: OPERALOG | L9: 390268 | N9: 1 | Q9: Pallets: 28 | R9: Unidade: 10261402-SUPERMERCADO COMETA LTDA(S4) | Região: 0.0 | S9: 29021848.0 | T9: 794333.0 | U9: FALSE | V9: Unidade: CERVEJARIA CAMAÇARI | Região: NE | W9: BR04 | X9: 421 | Y9: 12500 | Z9: 2462.78 | AA9: 2584.08 | AB9: 1440 | AC9: 36000 | AD9: CERVEJARIA CAMAÇARI_10261402-SUPERMERCADO COMETA LTDA(S4)_28_false | AE9: null | AF9: null | AG9: 1.92 | AH9: 115.5 | AI9: 0 | AJ9: 25 | AK9: 3.53 | AL9: 1.92 | AM9: 3 | AN9: 2.88 | AO9: FALSE | AP9: 17362.78 | AQ9: 21741.53 | AR9: 17169.29 | AS9: 17362.78 | AT9: 19132.54 | AU9: 3.53 | AV9: 0.01 | AW9: 0.22 | AX9: 0.1 | AY9: 0.31 | AZ9: 0 | BA9: 0.39 | BB9: 0.46 | BC9: 0 | BD9: 8263.35 | BE9: 16.81 | BF9: 512.92 | BG9: 233.87 | BH9: 714.82 | BI9: 5450.75 | BJ9: 908.96 | BK9: 1067.82 | BL9: 0 | BM9: FALSE | BN9: 1440 | BO9: 12 | BP9: 2645.76 | BQ9: 1171.49 | BR9: 2342.78 | BS9: 29965.15 | BT9: 28558.55 | BU9: 1171.29 | BV9: 0.01 | BW9: 0.22 | BX9: 0.31 | BY9: 0.1 | BZ9: null | CA9: 0 | CB9: 0 | CC9: 0 | CD9: 12 | CE9: 0 | CF9: 0 | CG9: 0 | CH9: 0.39 | CI9: 28.22 | CJ9: 0 | CK9: 437.68 | CL9: 1907.11 | CM9: 202400 | CN9: 3 | CO9: 29965.15 | CP9: 4611.33 | CQ9: 0.46 | CR9: 0.51 | CS9: Região: NE | CT9: 0 | CU9: 0 | CV9: 60 | CW9: 60 | CX9: 60 | CY9: 181.3 | CZ9: 60 | DA9: 2342.78 | DB9: TRUE | DC9: FALSE | DD9: Cargo: MODELO EQUIPE ATIVA ATUAL | DE9: 3 | DF9: 60 | DG9: 202400 | DH9: 584132c3-e1a3-4ad7-a454-77363c5b29ee
A10: =F10&"x"&W10&"x"&S10 -> BR04xBR04x29021611.0 | B10: =F10&"x"&W10&"x"&S10&Q10 -> BR04xBR04x29021611.0Pallets: 28 | C10: EMPURRADA_1_9_2026 | D10: 07526557001505_CERV | E10: CAMAÇARI | F10: BR04 | I10: Geo NE | J10: 20618821000799 | K10: OPERALOG | L10: 390268 | N10: 1 | Q10: Pallets: 28 | R10: Unidade: 10261250-SENDAS DISTRIBUIDORA SA(S4) | Região: 0 | S10: 29021611.0 | T10: 792080.0 | U10: FALSE | V10: Unidade: CERVEJARIA CAMAÇARI | Região: NE | W10: BR04 | X10: 421 | Y10: 12500 | Z10: 229 | AA10: 350.3 | AB10: 1440 | AC10: 36000 | AD10: CERVEJARIA CAMAÇARI_10261250-SENDAS DISTRIBUIDORA SA(S4)_28_false | AE10: null | AF10: null | AG10: 1.92 | AH10: 0 | AI10: 31 | AJ10: 25 | AK10: 3.53 | AL10: 1.92 | AM10: 3 | AN10: 2.88 | AO10: FALSE | AP10: 1936.81 | AQ10: 2602.71 | AR10: 1913.66 | AS10: 1936.81 | AT10: 2134.22 | AU10: 3.53 | AV10: 0.01 | AW10: 0.64 | AX10: 0.1 | AY10: 0.31 | AZ10: 0 | BA10: 0.39 | BB10: 0.92 | BC10: 0 | BD10: 384.46 | BE10: 1.56 | BF10: 69.53 | BG10: 10.88 | BH10: 33.26 | BI10: 1272.39 | BJ10: 42.29 | BK10: 99.29 | BL10: 0 | BM10: FALSE | BN10: 1440 | BO10: 18 | BP10: 479.21 | BQ10: 55 | BR10: 109 | BS10: 14993.45 | BT10: 9801.6 | BU10: 54 | BV10: 0.01 | BW10: 0.64 | BX10: 0.31 | BY10: 0.1 | BZ10: null | CA10: 0 | CB10: 0 | CC10: 0 | CD10: 18 | CE10: 0 | CF10: 0 | CG10: 0 | CH10: 0.39 | CI10: 28.22 | CJ10: 0 | CK10: 437.68 | CL10: 1907.11 | CM10: 202400 | CN10: 3 | CO10: 14993.45 | CP10: 4611.33 | CQ10: 0.92 | CR10: 5.5 | CS10: Região: NE | CT10: 0 | CU10: 0 | CV10: 60 | CW10: 60 | CX10: 60 | CY10: 181.3 | CZ10: 60 | DA10: 109 | DB10: FALSE | DC10: TRUE | DD10: Cargo: MODELO EQUIPE ATIVA ATUAL | DE10: 3 | DF10: 60 | DG10: 202400 | DH10: 3ced02f2-aa19-4e25-8eb2-2f3828510e9f
A11: =F11&"x"&W11&"x"&S11 -> BR04xBR04x29023180.0 | B11: =F11&"x"&W11&"x"&S11&Q11 -> BR04xBR04x29023180.0Pallets: 28 | C11: EMPURRADA_1_9_2026 | D11: 07526557001505_CERV | E11: CAMAÇARI | F11: BR04 | I11: Geo NE | J11: 20618821000799 | K11: OPERALOG | L11: 390268 | N11: 1 | Q11: Pallets: 28 | R11: Unidade: 10262331-ATACADAO S A(S4) | Região: 0 | S11: 29023180.0 | T11: 816523.0 | U11: FALSE | V11: Unidade: CERVEJARIA CAMAÇARI | Região: NE | W11: BR04 | X11: 421 | Y11: 12500 | Z11: 1678.89 | AA11: 1800.19 | AB11: 1440 | AC11: 36000 | AD11: CERVEJARIA CAMAÇARI_10262331-ATACADAO S A(S4)_28_false | AE11: null | AF11: null | AG11: 1.92 | AH11: 115.5 | AI11: 0 | AJ11: 25 | AK11: 3.53 | AL11: 1.92 | AM11: 3 | AN11: 2.88 | AO11: FALSE | AP11: 12289.96 | AQ11: 15389.38 | AR11: 12153 | AS11: 12289.96 | AT11: 13542.66 | AU11: 3.53 | AV11: 0.01 | AW11: 0.23 | AX11: 0.1 | AY11: 0.31 | AZ11: 0 | BA11: 0.39 | BB11: 0.47 | BC11: 0 | BD11: 5498.45 | BE11: 11.46 | BF11: 357.32 | BG11: 155.62 | BH11: 475.65 | BI11: 4321.75 | BJ11: 604.82 | BK11: 727.94 | BL11: 0 | BM11: FALSE | BN11: 1440 | BO11: 12 | BP11: 1872.76 | BQ11: 782.05 | BR11: 1558.89 | BS11: 29248.51 | BT11: 27277.7 | BU11: 776.84 | BV11: 0.01 | BW11: 0.23 | BX11: 0.31 | BY11: 0.1 | BZ11: null | CA11: 0 | CB11: 0 | CC11: 0 | CD11: 12 | CE11: 0 | CF11: 0 | CG11: 0 | CH11: 0.39 | CI11: 28.22 | CJ11: 0 | CK11: 437.68 | CL11: 1907.11 | CM11: 202400 | CN11: 3 | CO11: 29248.51 | CP11: 4611.33 | CQ11: 0.47 | CR11: 0.75 | CS11: Região: NE | CT11: 0 | CU11: 0 | CV11: 60 | CW11: 60 | CX11: 60 | CY11: 181.3 | CZ11: 60 | DA11: 1558.89 | DB11: TRUE | DC11: FALSE | DD11: Cargo: MODELO EQUIPE ATIVA ATUAL | DE11: 3 | DF11: 60 | DG11: 202400 | DH11: bb3b7946-a6ed-4607-8ba5-b223db54abe3
A12: =F12&"x"&W12&"x"&S12 -> BR04xBR04x29022977.0 | B12: =F12&"x"&W12&"x"&S12&Q12 -> BR04xBR04x29022977.0Pallets: 28 | C12: EMPURRADA_1_9_2026 | D12: 07526557001505_CERV | E12: CAMAÇARI | F12: BR04 | I12: Geo NE | J12: 20618821000799 | K12: OPERALOG | L12: 390268 | N12: 1 | Q12: Pallets: 28 | R12: Unidade: 10262178-DISTCARNES DISTRIBUIDORA CARNES(S4) | Região: 0 | S12: 29022977.0 | T12: 814237.0 | U12: FALSE | V12: Unidade: CERVEJARIA CAMAÇARI | Região: NE | W12: BR04 | X12: 421 | Y12: 12500 | Z12: 1679.85 | AA12: 1801.15 | AB12: 1440 | AC12: 36000 | AD12: CERVEJARIA CAMAÇARI_10262178-DISTCARNES DISTRIBUIDORA CARNES(S4)_28_false | AE12: null | AF12: null | AG12: 1.92 | AH12: 115.5 | AI12: 0 | AJ12: 25 | AK12: 3.53 | AL12: 1.92 | AM12: 3 | AN12: 2.88 | AO12: FALSE | AP12: 12406.3 | AQ12: 15535.07 | AR12: 12268.05 | AS12: 12406.3 | AT12: 13670.86 | AU12: 3.53 | AV12: 0.01 | AW12: 0.23 | AX12: 0.1 | AY12: 0.31 | AZ12: 0 | BA12: 0.39 | BB12: 0.47 | BC12: 0 | BD12: 5501.83 | BE12: 11.47 | BF12: 357.51 | BG12: 155.71 | BH12: 475.94 | BI12: 4432.03 | BJ12: 605.19 | BK12: 728.36 | BL12: 0 | BM12: FALSE | BN12: 1440 | BO12: 12 | BP12: 1890.48 | BQ12: 782.03 | BR12: 1559.85 | BS12: 29249.8 | BT12: 27279.95 | BU12: 777.82 | BV12: 0.01 | BW12: 0.23 | BX12: 0.31 | BY12: 0.1 | BZ12: null | CA12: 0 | CB12: 0 | CC12: 0 | CD12: 12 | CE12: 0 | CF12: 0 | CG12: 0 | CH12: 0.39 | CI12: 28.22 | CJ12: 0 | CK12: 437.68 | CL12: 1907.11 | CM12: 202400 | CN12: 3 | CO12: 29249.8 | CP12: 4611.33 | CQ12: 0.47 | CR12: 0.75 | CS12: Região: NE | CT12: 0 | CU12: 0 | CV12: 60 | CW12: 60 | CX12: 60 | CY12: 181.3 | CZ12: 60 | DA12: 1559.85 | DB12: TRUE | DC12: FALSE | DD12: Cargo: MODELO EQUIPE ATIVA ATUAL | DE12: 3 | DF12: 60 | DG12: 202400 | DH12: b2a27fe1-660c-4869-9b30-f4f00d952ce6
A13: =F13&"x"&W13&"x"&S13 -> BR04xBR04x29022696.0 | B13: =F13&"x"&W13&"x"&S13&Q13 -> BR04xBR04x29022696.0Pallets: 28 | C13: EMPURRADA_1_9_2026 | D13: 07526557001505_CERV | E13: CAMAÇARI | F13: BR04 | I13: Geo NE | J13: 20618821000799 | K13: OPERALOG | L13: 390268 | N13: 1 | Q13: Pallets: 28 | R13: Unidade: 10262021-SENDAS DISTRIBUIDORA SA(S4) | Região: 0 | S13: 29022696.0 | T13: 811653.0 | U13: FALSE | V13: Unidade: CERVEJARIA CAMAÇARI | Região: NE | W13: BR04 | X13: 421 | Y13: 12500 | Z13: 974 | AA13: 1095.3 | AB13: 1440 | AC13: 36000 | AD13: CERVEJARIA CAMAÇARI_10262021-SENDAS DISTRIBUIDORA SA(S4)_28_false | AE13: null | AF13: null | AG13: 1.92 | AH13: 115.5 | AI13: 0 | AJ13: 25 | AK13: 3.53 | AL13: 1.92 | AM13: 3 | AN13: 2.88 | AO13: FALSE | AP13: 6544.48 | AQ13: 8794.57 | AR13: 6466.27 | AS13: 6544.48 | AT13: 7211.54 | AU13: 3.53 | AV13: 0.01 | AW13: 0.25 | AX13: 0.1 | AY13: 0.31 | AZ13: 0 | BA13: 0.39 | BB13: 0.5 | BC13: 0 | BD13: 3012.19 | BE13: 6.65 | BF13: 217.41 | BG13: 85.25 | BH13: 260.57 | BI13: 2130.56 | BJ13: 331.34 | BK13: 422.31 | BL13: 0 | BM13: FALSE | BN13: 1440 | BO13: 18 | BP13: 1619.25 | BQ13: 427 | BR13: 854 | BS13: 27619.1 | BT13: 24560.39 | BU13: 427 | BV13: 0.01 | BW13: 0.25 | BX13: 0.31 | BY13: 0.1 | BZ13: null | CA13: 0 | CB13: 0 | CC13: 0 | CD13: 18 | CE13: 0 | CF13: 0 | CG13: 0 | CH13: 0.39 | CI13: 28.22 | CJ13: 0 | CK13: 437.68 | CL13: 1907.11 | CM13: 202400 | CN13: 3 | CO13: 27619.1 | CP13: 4611.33 | CQ13: 0.5 | CR13: 1.29 | CS13: Região: NE | CT13: 0 | CU13: 0 | CV13: 60 | CW13: 60 | CX13: 60 | CY13: 181.3 | CZ13: 60 | DA13: 854 | DB13: TRUE | DC13: FALSE | DD13: Cargo: MODELO EQUIPE ATIVA ATUAL | DE13: 3 | DF13: 60 | DG13: 202400 | DH13: f4852988-b6a1-44f8-ad2b-f7db429b1b67
A14: =F14&"x"&W14&"x"&S14 -> BR04xBR04x29022588.0 | B14: =F14&"x"&W14&"x"&S14&Q14 -> BR04xBR04x29022588.0Pallets: 28 | C14: EMPURRADA_1_9_2026 | D14: 07526557001505_CERV | E14: CAMAÇARI | F14: BR04 | I14: Geo NE | J14: 20618821000799 | K14: OPERALOG | L14: 390268 | N14: 1 | Q14: Pallets: 28 | R14: Unidade: 10261944-MERCANTIL RODRIGUES COMERCIAL LTDA(S4) | Região: 0 | S14: 29022588.0 | T14: 810614.0 | U14: FALSE | V14: Unidade: CERVEJARIA CAMAÇARI | Região: NE | W14: BR04 | X14: 421 | Y14: 12500 | Z14: 325.37 | AA14: 446.67 | AB14: 1440 | AC14: 36000 | AD14: CERVEJARIA CAMAÇARI_10261944-MERCANTIL RODRIGUES COMERCIAL LTDA(S4)_28_false | AE14: null | AF14: null | AG14: 1.92 | AH14: 0 | AI14: 31 | AJ14: 25 | AK14: 3.53 | AL14: 1.92 | AM14: 3 | AN14: 2.88 | AO14: FALSE | AP14: 2579.82 | AQ14: 3466.8 | AR14: 2548.99 | AS14: 2579.82 | AT14: 2842.78 | AU14: 3.53 | AV14: 0.01 | AW14: 0.43 | AX14: 0.1 | AY14: 0.31 | AZ14: 0 | BA14: 0.39 | BB14: 0.7 | BC14: 0 | BD14: 724.37 | BE14: 2.22 | BF14: 88.66 | BG14: 20.5 | BH14: 62.66 | BI14: 1429.82 | BJ14: 79.68 | BK14: 141.08 | BL14: 0 | BM14: FALSE | BN14: 1440 | BO14: 18 | BP14: 638.31 | BQ14: 104.13 | BR14: 205.37 | BS14: 19882.46 | BT14: 14483.07 | BU14: 101.24 | BV14: 0.01 | BW14: 0.43 | BX14: 0.31 | BY14: 0.1 | BZ14: null | CA14: 0 | CB14: 0 | CC14: 0 | CD14: 18 | CE14: 0 | CF14: 0 | CG14: 0 | CH14: 0.39 | CI14: 28.22 | CJ14: 0 | CK14: 437.68 | CL14: 1907.11 | CM14: 202400 | CN14: 3 | CO14: 19882.46 | CP14: 4611.33 | CQ14: 0.7 | CR14: 3.87 | CS14: Região: NE | CT14: 0 | CU14: 0 | CV14: 60 | CW14: 60 | CX14: 60 | CY14: 181.3 | CZ14: 60 | DA14: 205.37 | DB14: FALSE | DC14: TRUE | DD14: Cargo: MODELO EQUIPE ATIVA ATUAL | DE14: 3 | DF14: 60 | DG14: 202400 | DH14: 0a75e8ab-21df-458f-97f2-f63e1fb1b05d
... A177: =F177&"x"&W177&"x"&S177 -> BR04xBR04x487570.0 | B177: =F177&"x"&W177&"x"&S177&Q177 -> BR04xBR04x487570.0Pallets: 28 | C177: EMPURRADA_1_9_2026 | D177: 07526557001505_CERV | E177: CAMAÇARI | F177: BR04 | I177: Geo NE | J177: 20618821000799 | K177: OPERALOG | L177: 390268 | N177: 1 | Q177: Pallets: 28 | R177: Unidade: 487570-PAU BRASIL/SOUSA(PB) | S177: 487570.0 | T177: Revenda | U177: FALSE | V177: Unidade: CERVEJARIA CAMAÇARI | Região: NE | W177: BR04 | X177: 421 | Y177: 12500 | Z177: 1738 | AA177: 1859.3 | AB177: 1440 | AC177: 36000 | AD177: CERVEJARIA CAMAÇARI_487570-PAU BRASIL/SOUSA(PB)_28_false | AE177: null | AF177: null | AG177: 1.92 | AH177: 115.5 | AI177: 0 | AJ177: 25 | AK177: 3.53 | AL177: 1.92 | AM177: 3 | AN177: 2.88 | AO177: FALSE | AP177: 12421.61 | AQ177: 15554.23 | AR177: 12283.18 | AS177: 12421.61 | AT177: 13687.72 | AU177: 3.53 | AV177: 0.01 | AW177: 0.23 | AX177: 0.1 | AY177: 0.31 | AZ177: 0 | BA177: 0.39 | BB177: 0.47 | BC177: 0 | BD177: 5706.94 | BE177: 11.86 | BF177: 369.05 | BG177: 161.52 | BH177: 493.68 | BI177: 4158.81 | BJ177: 627.75 | BK177: 753.57 | BL177: 0 | BM177: FALSE | BN177: 1440 | BO177: 12 | BP177: 1892.82 | BQ177: 809 | BR177: 1618 | BS177: 29325.09 | BT177: 27411.93 | BU177: 809 | BV177: 0.01 | BW177: 0.23 | BX177: 0.31 | BY177: 0.1 | BZ177: null | CA177: 0 | CB177: 0 | CC177: 0 | CD177: 12 | CE177: 0 | CF177: 0 | CG177: 0 | CH177: 0.39 | CI177: 28.22 | CJ177: 0 | CK177: 437.68 | CL177: 1907.11 | CM177: 202400 | CN177: 3 | CO177: 29325.09 | CP177: 4611.33 | CQ177: 0.47 | CR177: 0.72 | CS177: Região: NE | CT177: 0 | CU177: 0 | CV177: 60 | CW177: 60 | CX177: 60 | CY177: 181.3 | CZ177: 60 | DA177: 1618 | DB177: TRUE | DC177: FALSE | DD177: Cargo: MODELO EQUIPE ATIVA ATUAL | DE177: 3 | DF177: 60 | DG177: 202400 | DH177: be4e99ec-96e9-4473-a136-8c65fff875de
A178: =F178&"x"&W178&"x"&S178 -> BR04xBR04xBR28 | B178: =F178&"x"&W178&"x"&S178&Q178 -> BR04xBR04xBR28Pallets: 28 | C178: EMPURRADA_1_9_2026 | D178: 07526557001505_CERV | E178: CAMAÇARI | F178: BR04 | I178: Geo NE | J178: 20618821000799 | K178: OPERALOG | L178: 390268 | N178: 1 | Q178: Pallets: 28 | R178: Unidade: CDR BELEM | S178: BR28 | T178: 433.0 | U178: FALSE | V178: Unidade: CERVEJARIA CAMAÇARI | Região: NE | W178: BR04 | X178: 421 | Y178: 12500 | Z178: 4316 | AA178: 4423.53 | AB178: 1440 | AC178: 36000 | AD178: CERVEJARIA CAMAÇARI_CDR BELEM_28_false | AG178: 1.92 | AH178: 115.5 | AI178: 0 | AJ178: 25 | AK178: 3.53 | AL178: 1.92 | AM178: 3 | AN178: 2.88 | AO178: FALSE | AP178: 28902.54 | AQ178: 36191.51 | AR178: 28580.45 | AS178: 28902.54 | AT178: 31848.53 | AU178: 3.53 | AV178: 0.01 | AW178: 0.21 | AX178: 0.1 | AY178: 0.31 | AZ178: 0 | BA178: 0.39 | BB178: 0.45 | BC178: 0 | BD178: 14799.94 | BE178: 29.46 | BF178: 878.03 | BG178: 418.87 | BH178: 1280.27 | BI178: 7791.84 | BJ178: 1627.97 | BK178: 1754.07 | BL178: 0 | BM178: FALSE | BN178: 1440 | BO178: 12 | BP178: 4404.2 | BQ178: 2099 | BR178: 4196 | BS178: 30624.19 | BT178: 29879.76 | BU178: 2097 | BV178: 0.01 | BW178: 0.21 | BX178: 0.31 | BY178: 0.1 | CA178: 0 | CB178: 0 | CC178: 0 | CD178: 12 | CE178: 0 | CF178: 0 | CG178: 0 | CH178: 0.39 | CI178: 28.22 | CJ178: 0 | CK178: 437.68 | CL178: 1907.11 | CM178: 202400 | CN178: 3 | CO178: 30624.19 | CP178: 4611.33 | CQ178: 0.45 | CR178: 0.29 | CS178: Região: NE | CT178: 0 | CU178: 0 | CV178: 60 | CW178: 56.28 | CX178: 60 | CY178: 171.25 | CZ178: 60 | DA178: 4196 | DB178: TRUE | DC178: FALSE | DD178: Cargo: MODELO EQUIPE ATIVA ATUAL | DE178: 3 | DF178: 60 | DG178: 202400 | DH178: 5405cc4a-9799-4b55-8b20-a42d11ec347b
A179: =F179&"x"&W179&"x"&S179 -> BR04xBR17xBR5D | B179: =F179&"x"&W179&"x"&S179&Q179 -> BR04xBR17xBR5DPallets: 28 | C179: EMPURRADA_1_9_2026 | D179: 07526557001505_CERV | E179: CAMAÇARI | F179: BR04 | I179: Geo NE | J179: 20618821000799 | K179: OPERALOG | L179: 390268 | N179: 1 | Q179: Pallets: 28 | R179: Unidade: CDR BAHIA | Região: NE | S179: BR5D | T179: 505 | U179: FALSE | V179: Unidade: CERVEJARIA JUATUBA | Região: MG | W179: BR17 | X179: 140 | Y179: 12500 | Z179: 2973.8 | AA179: 3142.03 | AB179: 1440 | AC179: 36000 | AD179: CERVEJARIA JUATUBA_CDR BAHIA_28_false | AG179: 1.92 | AH179: 115.5 | AI179: 0 | AJ179: 25 | AK179: 3.53 | AL179: 1.92 | AM179: 3 | AN179: 2.88 | AO179: FALSE | AP179: 17815.43 | AQ179: 22308.32 | AR179: 17616.89 | AS179: 17815.43 | AT179: 19631.32 | AU179: 3.53 | AV179: 0.01 | AW179: 0.22 | AX179: 0.1 | AY179: 0.31 | AZ179: 0 | BA179: 0.39 | BB179: 0.46 | BC179: 0 | BD179: 10065.79 | BE179: 20.3 | BF179: 623.67 | BG179: 284.88 | BH179: 870.75 | BI179: 3435.71 | BJ179: 1107.22 | BK179: 1208.58 | BL179: 0 | BM179: FALSE | BN179: 1440 | BO179: 12 | BP179: 2714.73 | BQ179: 1428.8 | BR179: 2853.8 | BS179: 30228.9 | BT179: 28610.39 | BU179: 1425 | BV179: 0.01 | BW179: 0.22 | BX179: 0.31 | BY179: 0.1 | CA179: 0 | CB179: 0 | CC179: 0 | CD179: 12 | CE179: 0 | CF179: 0 | CG179: 0 | CH179: 0.39 | CI179: 28.22 | CJ179: 0 | CK179: 437.68 | CL179: 1907.11 | CM179: 202400 | CN179: 3 | CO179: 30228.9 | CP179: 4611.33 | CQ179: 0.46 | CR179: 0.42 | CS179: Região: NE | CT179: 0 | CU179: 0 | CV179: 60 | CW179: 183.71 | CX179: 60 | CY179: 104.52 | CZ179: 60 | DA179: 2853.8 | DB179: TRUE | DC179: FALSE | DD179: Cargo: MODELO EQUIPE ATIVA ATUAL | DE179: 3 | DF179: 60 | DG179: 202400 | DH179: 158d5304-2abf-4e3f-aa73-37cadb26fb46
A180: =F180&"x"&W180&"x"&S180 -> BR04xBR02xBR31 | B180: =F180&"x"&W180&"x"&S180&Q180 -> BR04xBR02xBR31Pallets: 28 | C180: EMPURRADA_1_9_2026 | D180: 07526557001505_CERV | E180: CAMAÇARI | F180: BR04 | I180: Geo NE | J180: 20618821000799 | K180: OPERALOG | L180: 390268 | N180: 1 | Q180: Pallets: 28 | R180: Unidade: CERVEJARIA PERNAMBUCO | Região: NE | S180: BR31 | T180: 950 | U180: FALSE | V180: Unidade: CERVEJARIA ESTÂNCIA | Região: NE | W180: BR02 | X180: 205 | Y180: 12500 | Z180: 1135.4 | AA180: 1507.48 | AB180: 1440 | AC180: 36000 | AD180: CERVEJARIA ESTÂNCIA_CERVEJARIA PERNAMBUCO_28_false | AG180: 1.92 | AH180: 115.5 | AI180: 0 | AJ180: 25 | AK180: 3.53 | AL180: 1.92 | AM180: 3 | AN180: 2.88 | AO180: FALSE | AP180: 8656.04 | AQ180: 10839.02 | AR180: 8559.58 | AS180: 8656.04 | AT180: 9538.34 | AU180: 3.53 | AV180: 0.01 | AW180: 0.29 | AX180: 0.1 | AY180: 0.31 | AZ180: 0 | BA180: 0.39 | BB180: 0.49 | BC180: 0 | BD180: 3581.47 | BE180: 7.75 | BF180: 299.22 | BG180: 101.36 | BH180: 309.82 | BI180: 3404.56 | BJ180: 393.96 | BK180: 461.44 | BL180: 0 | BM180: FALSE | BN180: 1440 | BO180: 12 | BP180: 1319.02 | BQ180: 507.7 | BR180: 1015.4 | BS180: 28170.78 | BT180: 21217.59 | BU180: 507.7 | BV180: 0.01 | BW180: 0.29 | BX180: 0.31 | BY180: 0.1 | CA180: 0 | CB180: 0 | CC180: 0 | CD180: 12 | CE180: 0 | CF180: 0 | CG180: 0 | CH180: 0.39 | CI180: 28.22 | CJ180: 0 | CK180: 437.68 | CL180: 1907.11 | CM180: 202400 | CN180: 3 | CO180: 28170.78 | CP180: 4611.33 | CQ180: 0.49 | CR180: 1.11 | CS180: Região: NE | CT180: 0 | CU180: 0 | CV180: 60 | CW180: 339.28 | CX180: 60 | CY180: 152.8 | CZ180: 60 | DA180: 1015.4 | DB180: TRUE | DC180: FALSE | DD180: Cargo: MODELO EQUIPE ATIVA ATUAL | DE180: 3 | DF180: 60 | DG180: 202400 | DH180: db540a9d-a77e-4710-9ebb-a080e187589f
A181: =F181&"x"&W181&"x"&S181 -> BR04xBR29xBR5D | B181: =F181&"x"&W181&"x"&S181&Q181 -> BR04xBR29xBR5DPallets: 28 | C181: EMPURRADA_1_9_2026 | D181: 07526557001505_CERV | E181: CAMAÇARI | F181: BR04 | I181: Geo NE | J181: 20618821000799 | K181: OPERALOG | L181: 390268 | N181: 1 | Q181: Pallets: 28 | R181: Unidade: CDR BAHIA | Região: NE | S181: BR5D | T181: 505 | U181: FALSE | V181: Unidade: CERVEJARIA NOVA MINAS | Região: MG | W181: BR29 | X181: 803 | Y181: 12500 | Z181: 2840.9 | AA181: 3016.03 | AB181: 1440 | AC181: 36000 | AD181: CERVEJARIA NOVA MINAS_CDR BAHIA_28_false | AG181: 1.92 | AH181: 115.5 | AI181: 0 | AJ181: 25 | AK181: 3.53 | AL181: 1.92 | AM181: 3 | AN181: 2.88 | AO181: FALSE | AP181: 16787.98 | AQ181: 21021.77 | AR181: 16600.9 | AS181: 16787.98 | AT181: 18499.16 | AU181: 3.53 | AV181: 0.01 | AW181: 0.22 | AX181: 0.1 | AY181: 0.31 | AZ181: 0 | BA181: 0.39 | BB181: 0.46 | BC181: 0 | BD181: 9597.03 | BE181: 19.39 | BF181: 598.66 | BG181: 271.61 | BH181: 830.2 | BI181: 3073.78 | BJ181: 1055.66 | BK181: 1154.57 | BL181: 0 | BM181: FALSE | BN181: 1440 | BO181: 12 | BP181: 2558.17 | BQ181: 1361.9 | BR181: 2720.9 | BS181: 30169.44 | BT181: 28417.61 | BU181: 1359 | BV181: 0.01 | BW181: 0.22 | BX181: 0.31 | BY181: 0.1 | CA181: 0 | CB181: 0 | CC181: 0 | CD181: 12 | CE181: 0 | CF181: 0 | CG181: 0 | CH181: 0.39 | CI181: 28.22 | CJ181: 0 | CK181: 437.68 | CL181: 1907.11 | CM181: 202400 | CN181: 3 | CO181: 30169.44 | CP181: 4611.33 | CQ181: 0.46 | CR181: 0.44 | CS181: Região: NE | CT181: 0 | CU181: 0 | CV181: 60 | CW181: 183.71 | CX181: 60 | CY181: 111.42 | CZ181: 60 | DA181: 2720.9 | DB181: TRUE | DC181: FALSE | DD181: Cargo: MODELO EQUIPE ATIVA ATUAL | DE181: 3 | DF181: 60 | DG181: 202400 | DH181: bcf1c62e-dfc8-4ed4-8a89-11e6013f7d60
A182: =F182&"x"&W182&"x"&S182 -> BR04xBR23xBR5D | B182: =F182&"x"&W182&"x"&S182&Q182 -> BR04xBR23xBR5DPallets: 28 | C182: EMPURRADA_1_9_2026 | D182: 07526557001505_CERV | E182: CAMAÇARI | F182: BR04 | I182: Geo NE | J182: 20618821000799 | K182: OPERALOG | L182: 390268 | N182: 1 | Q182: Pallets: 28 | R182: Unidade: CDR BAHIA | Região: NE | S182: BR5D | T182: 505 | U182: FALSE | V182: Unidade: CERVEJARIA JAGUARIÚNA | Região: SP INTERIOR | W182: BR23 | X182: 952 | Y182: 12500 | Z182: 4012.3 | AA182: 4281.21 | AB182: 1440 | AC182: 36000 | AD182: CERVEJARIA JAGUARIÚNA_CDR BAHIA_28_false | AG182: 1.92 | AH182: 115.5 | AI182: 0 | AJ182: 25 | AK182: 3.53 | AL182: 1.92 | AM182: 3 | AN182: 2.88 | AO182: FALSE | AP182: 24007.35 | AQ182: 30061.8 | AR182: 23739.81 | AS182: 24007.35 | AT182: 26454.38 | AU182: 3.53 | AV182: 0.01 | AW182: 0.22 | AX182: 0.1 | AY182: 0.31 | AZ182: 0 | BA182: 0.39 | BB182: 0.45 | BC182: 0 | BD182: 13728.74 | BE182: 27.39 | BF182: 849.78 | BG182: 388.55 | BH182: 1187.61 | BI182: 4416.96 | BJ182: 1510.14 | BK182: 1630.64 | BL182: 0 | BM182: FALSE | BN182: 1440 | BO182: 12 | BP182: 3658.26 | BQ182: 1927.4 | BR182: 3892.3 | BS182: 30557.9 | BT182: 28638.5 | BU182: 1964.9 | BV182: 0.01 | BW182: 0.22 | BX182: 0.31 | BY182: 0.1 | CA182: 0 | CB182: 0 | CC182: 0 | CD182: 12 | CE182: 0 | CF182: 0 | CG182: 0 | CH182: 0.39 | CI182: 28.22 | CJ182: 0 | CK182: 437.68 | CL182: 1907.11 | CM182: 202400 | CN182: 3 | CO182: 30557.9 | CP182: 4611.33 | CQ182: 0.45 | CR182: 0.31 | CS182: Região: NE | CT182: 0 | CU182: 0 | CV182: 60 | CW182: 183.71 | CX182: 60 | CY182: 205.2 | CZ182: 60 | DA182: 3892.3 | DB182: TRUE | DC182: FALSE | DD182: Cargo: MODELO EQUIPE ATIVA ATUAL | DE182: 3 | DF182: 60 | DG182: 202400 | DH182: d4efb2e6-425e-4926-ade6-65c694927da9
A183: =F183&"x"&W183&"x"&S183 -> BR04xBR40xBR51 | B183: =F183&"x"&W183&"x"&S183&Q183 -> BR04xBR40xBR51Pallets: 28 | C183: EMPURRADA_1_9_2026 | D183: 07526557001505_CERV | E183: CAMAÇARI | F183: BR04 | I183: Geo NE | J183: 20618821000799 | K183: OPERALOG | L183: 390268 | N183: 1 | Q183: Pallets: 28 | R183: Unidade: C. Macacu | Região: RJ INTERIOR | S183: BR51 | T183: 320 | U183: FALSE | V183: Unidade: CERVEJARIA PIRAÍ | Região: RJ CAPITAL | W183: BR40 | X183: 781 | Y183: 12500 | Z183: 427.8 | AA183: 612.22 | AB183: 1440 | AC183: 36000 | AD183: CERVEJARIA PIRAÍ_C. Macacu_28_false | AG183: 1.92 | AH183: 115.5 | AI183: 0 | AJ183: 25 | AK183: 3.53 | AL183: 1.92 | AM183: 3 | AN183: 2.88 | AO183: FALSE | AP183: 2072.74 | AQ183: 2404.22 | AR183: 2051.32 | AS183: 2072.74 | AT183: 2284.01 | AU183: 3.53 | AV183: 0.01 | AW183: 0.39 | AX183: 0.1 | AY183: 0.31 | AZ183: 0 | BA183: 0.39 | BB183: 0.61 | BC183: 0 | BD183: 1085.66 | BE183: 2.92 | BF183: 121.52 | BG183: 30.73 | BH183: 93.92 | BI183: 423.3 | BJ183: 119.42 | BK183: 173.86 | BL183: 0 | BM183: TRUE | BN183: 1440 | BO183: 5 | BP183: 120.86 | BQ183: 153.9 | BR183: 307.8 | BS183: 22664.1 | BT183: 15836.95 | BU183: 153.9 | BV183: 0.01 | BW183: 0.39 | BX183: 0.31 | BY183: 0.1 | CA183: 0 | CB183: 0 | CC183: 0 | CD183: 5 | CE183: 0 | CF183: 0 | CG183: 0 | CH183: 0.39 | CI183: 28.22 | CJ183: 0 | CK183: 437.68 | CL183: 1907.11 | CM183: 202400 | CN183: 3 | CO183: 22664.1 | CP183: 4611.33 | CQ183: 0.61 | CR183: 2.95 | CS183: Região: NE | CT183: 0 | CU183: 0 | CV183: 60 | CW183: 188.99 | CX183: 60 | CY183: 115.43 | CZ183: 60 | DA183: 307.8 | DB183: TRUE | DC183: FALSE | DD183: Cargo: MODELO EQUIPE ATIVA ATUAL | DE183: 3 | DF183: 60 | DG183: 202400 | DH183: b31699ee-6bac-45ea-b0ff-746554ebc414
A184: =F184&"x"&W184&"x"&S184 -> BR04xBR04x966673.0 | B184: =F184&"x"&W184&"x"&S184&Q184 -> BR04xBR04x966673.0Pallets: 28 | C184: EMPURRADA_1_9_2026 | D184: 07526557001505_CERV | E184: CAMAÇARI | F184: BR04 | I184: Geo NE | J184: 20618821000799 | K184: OPERALOG | L184: 390268 | N184: 1 | Q184: Pallets: 28 | R184: Unidade: 966673-ASA BRANCA/TERESINA | Região: null | S184: 966673.0 | T184: Revenda | U184: FALSE | V184: Unidade: CERVEJARIA CAMAÇARI | Região: NE | W184: BR04 | X184: 421 | Y184: 12500 | Z184: 3299.59 | AA184: 3420.89 | AB184: 1440 | AC184: 36000 | AD184: CERVEJARIA CAMAÇARI_966673-ASA BRANCA/TERESINA _28_false | AE184: 0 | AF184: 0 | AG184: 1.92 | AH184: 115.5 | AI184: 0 | AJ184: 25 | AK184: 3.53 | AL184: 1.92 | AM184: 3 | AN184: 2.88 | AO184: FALSE | AP184: 16916.77 | AQ184: 21183.03 | AR184: 16728.24 | AS184: 16916.77 | AT184: 18641.07 | AU184: 3.53 | AV184: 0.01 | AW184: 0.3 | AX184: 0.1 | AY184: 0.31 | AZ184: 0 | BA184: 0.39 | BB184: 0.64 | BC184: 0 | BD184: 8024.28 | BE184: 22.52 | BF184: 679.02 | BG184: 227.1 | BH184: 694.14 | BI184: 4767.87 | BJ184: 882.66 | BK184: 1430.66 | BL184: 0 | BM184: FALSE | BN184: 1440 | BO184: 12 | BP184: 2577.79 | BQ184: 1136 | BR184: 2275 | BS184: 21718.58 | BT184: 20948.47 | BU184: 1139 | BV184: 0.01 | BW184: 0.3 | BX184: 0.31 | BY184: 0.1 | CA184: 0 | CB184: 0 | CC184: 0 | CD184: 12 | CE184: 0 | CF184: 0 | CG184: 0 | CH184: 0.39 | CI184: 28.22 | CJ184: 0 | CK184: 437.68 | CL184: 1907.11 | CM184: 202400 | CN184: 3 | CO184: 21718.58 | CP184: 4611.33 | CQ184: 0.64 | CR184: 0.38 | CS184: Região: NE | CT184: 0 | CU184: 0 | CV184: 60 | CW184: 60 | CX184: 60 | CY184: 181.3 | CZ184: 60 | DA184: 3179.59 | DB184: TRUE | DC184: FALSE | DD184: Cargo: MODELO EQUIPE ATIVA ATUAL | DE184: 3 | DF184: 42.93 | DG184: 202400 | DH184: 1bc14d41-20c7-413a-a089-4edac99ad4a8
A185: =F185&"x"&W185&"x"&S185 -> BR04xBR5WxBR20 | B185: =F185&"x"&W185&"x"&S185&Q185 -> BR04xBR5WxBR20Pallets: 28 | C185: EMPURRADA_1_9_2026 | D185: 07526557001505_CERV | E185: CAMAÇARI | F185: BR04 | I185: Geo NE | J185: 20618821000799 | K185: OPERALOG | L185: 390268 | N185: 1 | Q185: Pallets: 28 | R185: Unidade: CERVEJARIA SAPUCAIA | Região: RS | S185: BR20 | T185: 47 | U185: FALSE | V185: Unidade: CDR EXTREMA | Região: MG | W185: BR5W | X185: 324 | Y185: 12500 | Z185: 2633.15 | AA185: 2730.67 | AB185: 1440 | AC185: 36000 | AD185: CDR EXTREMA_CERVEJARIA SAPUCAIA_28_false | AG185: 1.92 | AH185: 115.5 | AI185: 0 | AJ185: 25 | AK185: 3.53 | AL185: 1.92 | AM185: 3 | AN185: 2.88 | AO185: FALSE | AP185: 14736.78 | AQ185: 18453.27 | AR185: 14572.55 | AS185: 14736.78 | AT185: 16238.87 | AU185: 3.53 | AV185: 0.01 | AW185: 0.22 | AX185: 0.1 | AY185: 0.31 | AZ185: 0 | BA185: 0.39 | BB185: 0.46 | BC185: 0 | BD185: 8864.27 | BE185: 17.97 | BF185: 542.01 | BG185: 250.88 | BH185: 766.81 | BI185: 2085.42 | BJ185: 975.06 | BK185: 1070.14 | BL185: 0 | BM185: FALSE | BN185: 1440 | BO185: 12 | BP185: 2245.6 | BQ185: 1260.15 | BR185: 2513.15 | BS185: 30064.46 | BT185: 28990.77 | BU185: 1253 | BV185: 0.01 | BW185: 0.22 | BX185: 0.31 | BY185: 0.1 | CA185: 0 | CB185: 0 | CC185: 0 | CD185: 12 | CE185: 0 | CF185: 0 | CG185: 0 | CH185: 0.39 | CI185: 28.22 | CJ185: 0 | CK185: 437.68 | CL185: 1907.11 | CM185: 202400 | CN185: 3 | CO185: 30064.46 | CP185: 4611.33 | CQ185: 0.46 | CR185: 0.48 | CS185: Região: NE | CT185: 0 | CU185: 0 | CV185: 60 | CW185: 97.42 | CX185: 60 | CY185: 120.1 | CZ185: 60 | DA185: 2513.15 | DB185: TRUE | DC185: FALSE | DD185: Cargo: MODELO EQUIPE ATIVA ATUAL | DE185: 3 | DF185: 60 | DG185: 202400 | DH185: 342fc83f-2bd2-401a-a6ca-e00d7f46f5fa
A186: =F186&"x"&W186&"x"&S186 -> BR04xBR04x798479.0 | B186: =F186&"x"&W186&"x"&S186&Q186 -> BR04xBR04x798479.0Pallets: 28 | C186: EMPURRADA_1_9_2026 | D186: 07526557001505_CERV | E186: CAMAÇARI | F186: BR04 | I186: Geo NE | J186: 20618821000799 | K186: OPERALOG | L186: 390268 | N186: 1 | Q186: Pallets: 28 | R186: Unidade: 798479-DISCAR DISTRIBUIDORA/PRESI. DUTRA(MA) | S186: 798479.0 | T186: Revenda | U186: FALSE | V186: Unidade: CERVEJARIA CAMAÇARI | Região: NE | W186: BR04 | X186: 421 | Y186: 12500 | Z186: 2806.13 | AA186: 2927.43 | AB186: 1440 | AC186: 36000 | AD186: CERVEJARIA CAMAÇARI_798479-DISCAR DISTRIBUIDORA/PRESI. DUTRA(MA)_28_false | AE186: 0 | AF186: 0 | AG186: 1.92 | AH186: 115.5 | AI186: 0 | AJ186: 25 | AK186: 3.53 | AL186: 1.92 | AM186: 3 | AN186: 2.88 | AO186: FALSE | AP186: 20209.64 | AQ186: 25306.33 | AR186: 19984.42 | AS186: 20209.64 | AT186: 22269.57 | AU186: 3.53 | AV186: 0.01 | AW186: 0.22 | AX186: 0.1 | AY186: 0.31 | AZ186: 0 | BA186: 0.39 | BB186: 0.46 | BC186: 0 | BD186: 9474.39 | BE186: 19.15 | BF186: 581.07 | BG186: 268.14 | BH186: 819.59 | BI186: 6563.2 | BJ186: 1042.17 | BK186: 1216.7 | BL186: 0 | BM186: FALSE | BN186: 1440 | BO186: 12 | BP186: 3079.56 | BQ186: 1305.63 | BR186: 2686.13 | BS186: 30152.95 | BT186: 28903.54 | BU186: 1380.5 | BV186: 0.01 | BW186: 0.22 | BX186: 0.31 | BY186: 0.1 | CA186: 0 | CB186: 0 | CC186: 0 | CD186: 12 | CE186: 0 | CF186: 0 | CG186: 0 | CH186: 0.39 | CI186: 28.22 | CJ186: 0 | CK186: 437.68 | CL186: 1907.11 | CM186: 202400 | CN186: 3 | CO186: 30152.95 | CP186: 4611.33 | CQ186: 0.46 | CR186: 0.45 | CS186: Região: NE | CT186: 0 | CU186: 0 | CV186: 60 | CW186: 60 | CX186: 60 | CY186: 181.3 | CZ186: 60 | DA186: 2686.13 | DB186: TRUE | DC186: FALSE | DD186: Cargo: MODELO EQUIPE ATIVA ATUAL | DE186: 3 | DF186: 60 | DG186: 202400 | DH186: d6b8521e-e33f-4026-9209-b1603af0ed19
A187: =F187&"x"&W187&"x"&S187 -> BR04xBR04x820288.0 | B187: =F187&"x"&W187&"x"&S187&Q187 -> BR04xBR04x820288.0Pallets: 28 | C187: EMPURRADA_1_9_2026 | D187: 07526557001505_CERV | E187: CAMAÇARI | F187: BR04 | I187: Geo NE | J187: 20618821000799 | K187: OPERALOG | L187: 390268 | N187: 1 | Q187: Pallets: 28 | R187: Unidade: 820288-PAU BRASIL/ FILIAL ITAPORANGA | S187: 820288.0 | T187: Revenda | U187: FALSE | V187: Unidade: CERVEJARIA CAMAÇARI | Região: NE | W187: BR04 | X187: 421 | Y187: 12500 | Z187: 1598.61 | AA187: 1719.91 | AB187: 1440 | AC187: 36000 | AD187: CERVEJARIA CAMAÇARI_820288-PAU BRASIL/ FILIAL ITAPORANGA_28_false | AG187: 1.77 | AH187: 115.5 | AI187: 0 | AJ187: 25 | AK187: 3.83 | AL187: 1.77 | AM187: 3 | AN187: 2.88 | AO187: FALSE | AP187: 11494.41 | AQ187: 13619.38 | AR187: 11373.13 | AS187: 11494.41 | AT187: 12666.02 | AU187: 3.83 | AV187: 0.01 | AW187: 0.23 | AX187: 0.1 | AY187: 0.31 | AZ187: 0 | BA187: 0.39 | BB187: 0.47 | BC187: 0 | BD187: 5668.79 | BE187: 10.91 | BF187: 341.39 | BG187: 147.6 | BH187: 451.15 | BI187: 3486.49 | BJ187: 573.67 | BK187: 693.13 | BL187: 0 | BM187: FALSE | BN187: 1440 | BO187: 7 | BP187: 960.73 | BQ187: 738 | BR187: 1478.61 | BS187: 29135.45 | BT187: 27080.61 | BU187: 740.61 | BV187: 0.01 | BW187: 0.23 | BX187: 0.31 | BY187: 0.1 | CA187: 0 | CB187: 0 | CC187: 0 | CD187: 7 | CE187: 0 | CF187: 0 | CG187: -8 | CH187: 0.39 | CI187: 28.22 | CJ187: 0 | CK187: 437.68 | CL187: 1907.11 | CM187: 202400 | CN187: 3 | CO187: 29135.45 | CP187: 4611.33 | CQ187: 0.47 | CR187: 0.79 | CS187: Região: NE | CT187: 0 | CU187: 0 | CV187: 60 | CW187: 60 | CX187: 60 | CY187: 181.3 | CZ187: 60 | DA187: 1478.61 | DB187: TRUE | DC187: FALSE | DD187: Cargo: MODELO EQUIPE ATIVA ATUAL | DE187: 3 | DF187: 60 | DG187: 202400 | DH187: 824caeea-22f7-49fc-b86d-d1382e485ee6
A188: =F188&"x"&W188&"x"&S188 -> BR04xBR04x729817.0 | B188: =F188&"x"&W188&"x"&S188&Q188 -> BR04xBR04x729817.0Pallets: 28 | C188: EMPURRADA_1_9_2026 | D188: 07526557001505_CERV | E188: CAMAÇARI | F188: BR04 | I188: Geo NE | J188: 20618821000799 | K188: OPERALOG | L188: 390268 | N188: 1 | Q188: Pallets: 28 | R188: Unidade: 729817-DISBECOL/PAU DOS FERROS(RN) | S188: 729817.0 | T188: Revenda | U188: FALSE | V188: Unidade: CERVEJARIA CAMAÇARI | Região: NE | W188: BR04 | X188: 421 | Y188: 12500 | Z188: 1860.94 | AA188: 1982.24 | AB188: 1440 | AC188: 36000 | AD188: CERVEJARIA CAMAÇARI_729817-DISBECOL/PAU DOS FERROS(RN)_28_false | AG188: 1.77 | AH188: 115.5 | AI188: 0 | AJ188: 25 | AK188: 3.83 | AL188: 1.77 | AM188: 3 | AN188: 2.88 | AO188: FALSE | AP188: 13285.65 | AQ188: 16636.18 | AR188: 13137.59 | AS188: 13285.65 | AT188: 14639.83 | AU188: 3.83 | AV188: 0.01 | AW188: 0.23 | AX188: 0.1 | AY188: 0.31 | AZ188: 0 | BA188: 0.39 | BB188: 0.47 | BC188: 0 | BD188: 6674.53 | BE188: 12.7 | BF188: 393.46 | BG188: 173.79 | BH188: 531.19 | BI188: 3869.59 | BJ188: 675.45 | BK188: 806.88 | BL188: 0 | BM188: FALSE | BN188: 1440 | BO188: 12 | BP188: 2024.48 | BQ188: 869 | BR188: 1740.94 | BS188: 29468.77 | BT188: 27665.47 | BU188: 871.94 | BV188: 0.01 | BW188: 0.23 | BX188: 0.31 | BY188: 0.1 | CA188: 0 | CB188: 0 | CC188: 0 | CD188: 12 | CE188: 0 | CF188: 0 | CG188: -8 | CH188: 0.39 | CI188: 28.22 | CJ188: 0 | CK188: 437.68 | CL188: 1907.11 | CM188: 202400 | CN188: 3 | CO188: 29468.77 | CP188: 4611.33 | CQ188: 0.47 | CR188: 0.68 | CS188: Região: NE | CT188: 0 | CU188: 0 | CV188: 60 | CW188: 60 | CX188: 60 | CY188: 181.3 | CZ188: 60 | DA188: 1740.94 | DB188: TRUE | DC188: FALSE | DD188: Cargo: MODELO EQUIPE ATIVA ATUAL | DE188: 3 | DF188: 60 | DG188: 202400 | DH188: a3dad4dc-919a-4559-a79e-47fca09bdfde
A189: =F189&"x"&W189&"x"&S189 -> BR04xBR04x983610.0 | B189: =F189&"x"&W189&"x"&S189&Q189 -> BR04xBR04x983610.0Pallets: 28 | C189: EMPURRADA_1_9_2026 | D189: 07526557001505_CERV | E189: CAMAÇARI | F189: BR04 | I189: Geo NE | J189: 20618821000799 | K189: OPERALOG | L189: 390268 | N189: 1 | Q189: Pallets: 28 | R189: Unidade: 983610-REVALLE PAULO AFONSO(BA) | Região: null | S189: 983610.0 | T189: Revenda | U189: FALSE | V189: Unidade: CERVEJARIA CAMAÇARI | Região: NE | W189: BR04 | X189: 421 | Y189: 12500 | Z189: 946 | AA189: 1067.3 | AB189: 1440 | AC189: 36000 | AD189: CERVEJARIA CAMAÇARI_983610-REVALLE PAULO AFONSO(BA)_28_false | AG189: 1.77 | AH189: 115.5 | AI189: 0 | AJ189: 25 | AK189: 3.83 | AL189: 1.77 | AM189: 3 | AN189: 2.88 | AO189: FALSE | AP189: 7027.08 | AQ189: 9443.1 | AR189: 6943.11 | AS189: 7027.08 | AT189: 7743.34 | AU189: 3.83 | AV189: 0.01 | AW189: 0.23 | AX189: 0.1 | AY189: 0.31 | AZ189: 0 | BA189: 0.39 | BB189: 0.5 | BC189: 0 | BD189: 3166.77 | BE189: 6.46 | BF189: 187.77 | BG189: 82.46 | BH189: 252.03 | BI189: 2516.99 | BJ189: 320.47 | BK189: 410.17 | BL189: 0 | BM189: FALSE | BN189: 1440 | BO189: 18 | BP189: 1738.66 | BQ189: 413 | BR189: 826 | BS189: 27504.23 | BT189: 24378.34 | BU189: 413 | BV189: 0.01 | BW189: 0.23 | BX189: 0.31 | BY189: 0.1 | CA189: 0 | CB189: 0 | CC189: 0 | CD189: 18 | CE189: 0 | CF189: 0 | CG189: -8 | CH189: 0.39 | CI189: 28.22 | CJ189: 0 | CK189: 437.68 | CL189: 1907.11 | CM189: 202400 | CN189: 3 | CO189: 27504.23 | CP189: 4611.33 | CQ189: 0.5 | CR189: 1.33 | CS189: Região: NE | CT189: 0 | CU189: 0 | CV189: 60 | CW189: 60 | CX189: 60 | CY189: 181.3 | CZ189: 60 | DA189: 826 | DB189: TRUE | DC189: FALSE | DD189: Cargo: MODELO EQUIPE ATIVA ATUAL | DE189: 3 | DF189: 60 | DG189: 202400 | DH189: 44d0114b-5b6a-4efe-b777-132296d6791d
A190: =F190&"x"&W190&"x"&S190 -> BR04xBR08xBR5D | B190: =F190&"x"&W190&"x"&S190&Q190 -> BR04xBR08xBR5DPallets: 28 | C190: EMPURRADA_1_9_2026 | D190: 07526557001505_CERV | E190: CAMAÇARI | F190: BR04 | I190: Geo NE | J190: 20618821000799 | K190: OPERALOG | L190: 390268 | N190: 1 | Q190: Pallets: 28 | R190: Unidade: CDR BAHIA | Região: NE | S190: BR5D | T190: 505 | U190: FALSE | V190: Unidade: CERVEJARIA TERESINA | Região: NE | W190: BR08 | X190: 428 | Y190: 12500 | Z190: 2531.3 | AA190: 2719.77 | AB190: 1440 | AC190: 36000 | AD190: CERVEJARIA TERESINA_CDR BAHIA_28_false | AG190: 1.77 | AH190: 115.5 | AI190: 0 | AJ190: 25 | AK190: 3.83 | AL190: 1.77 | AM190: 3 | AN190: 2.88 | AO190: FALSE | AP190: 14616.97 | AQ190: 18303.24 | AR190: 14454.08 | AS190: 14616.97 | AT190: 16106.85 | AU190: 3.83 | AV190: 0.01 | AW190: 0.21 | AX190: 0.1 | AY190: 0.31 | AZ190: 0 | BA190: 0.39 | BB190: 0.46 | BC190: 0 | BD190: 9244.59 | BE190: 17.28 | BF190: 502.44 | BG190: 240.71 | BH190: 735.73 | BI190: 1801.5 | BJ190: 935.54 | BK190: 976.29 | BL190: 0 | BM190: FALSE | BN190: 1440 | BO190: 12 | BP190: 2227.35 | BQ190: 1205 | BR190: 2411.3 | BS190: 30006.7 | BT190: 27927.34 | BU190: 1206.3 | BV190: 0.01 | BW190: 0.21 | BX190: 0.31 | BY190: 0.1 | CA190: 0 | CB190: 0 | CC190: 0 | CD190: 12 | CE190: 0 | CF190: 0 | CG190: -8 | CH190: 0.39 | CI190: 28.22 | CJ190: 0 | CK190: 437.68 | CL190: 1907.11 | CM190: 202400 | CN190: 3 | CO190: 30006.7 | CP190: 4611.33 | CQ190: 0.46 | CR190: 0.5 | CS190: Região: NE | CT190: 0 | CU190: 0 | CV190: 60 | CW190: 183.71 | CX190: 60 | CY190: 124.76 | CZ190: 60 | DA190: 2411.3 | DB190: TRUE | DC190: FALSE | DD190: Cargo: MODELO EQUIPE ATIVA ATUAL | DE190: 3 | DF190: 60 | DG190: 202400 | DH190: 10593576-c8cf-4762-98c5-ba46413eb8c7
A191: =F191&"x"&W191&"x"&S191 -> BR04xBR04x101662.0 | B191: =F191&"x"&W191&"x"&S191&Q191 -> BR04xBR04x101662.0Pallets: 28 | C191: EMPURRADA_1_9_2026 | D191: 07526557001505_CERV | E191: CAMAÇARI | F191: BR04 | I191: Geo NE | J191: 20618821000799 | K191: OPERALOG | L191: 390268 | N191: 1 | Q191: Pallets: 28 | R191: Unidade: 101662-JODIBE/GARANHUNS (PE) | S191: 101662.0 | T191: Revenda | U191: FALSE | V191: Unidade: CERVEJARIA CAMAÇARI | Região: NE | W191: BR04 | X191: 421 | Y191: 12500 | Z191: 1293.96 | AA191: 1415.26 | AB191: 1440 | AC191: 36000 | AD191: CERVEJARIA CAMAÇARI_101662-JODIBE/GARANHUNS (PE)_28_false | AG191: 1.77 | AH191: 115.5 | AI191: 0 | AJ191: 25 | AK191: 3.83 | AL191: 1.77 | AM191: 3 | AN191: 2.88 | AO191: FALSE | AP191: 9513.65 | AQ191: 11912.91 | AR191: 9407.63 | AS191: 9513.65 | AT191: 10483.36 | AU191: 3.83 | AV191: 0.01 | AW191: 0.22 | AX191: 0.1 | AY191: 0.31 | AZ191: 0 | BA191: 0.39 | BB191: 0.48 | BC191: 0 | BD191: 4500.8 | BE191: 8.83 | BF191: 256.84 | BG191: 117.19 | BH191: 358.2 | BI191: 3149.25 | BJ191: 455.47 | BK191: 561.04 | BL191: 0 | BM191: FALSE | BN191: 1440 | BO191: 12 | BP191: 1449.7 | BQ191: 595.37 | BR191: 1173.96 | BS191: 28578.74 | BT191: 26129.29 | BU191: 578.59 | BV191: 0.01 | BW191: 0.22 | BX191: 0.31 | BY191: 0.1 | CA191: 0 | CB191: 0 | CC191: 0 | CD191: 12 | CE191: 0 | CF191: 0 | CG191: -8 | CH191: 0.39 | CI191: 28.22 | CJ191: 0 | CK191: 437.68 | CL191: 1907.11 | CM191: 202400 | CN191: 3 | CO191: 28578.74 | CP191: 4611.33 | CQ191: 0.48 | CR191: 0.97 | CS191: Região: NE | CT191: 0 | CU191: 0 | CV191: 60 | CW191: 60 | CX191: 60 | CY191: 181.3 | CZ191: 60 | DA191: 1173.96 | DB191: TRUE | DC191: FALSE | DD191: Cargo: MODELO EQUIPE ATIVA ATUAL | DE191: 3 | DF191: 60 | DG191: 202400 | DH191: 3f1919f0-65ac-4517-ab52-d7e8d75227db
A192: =F192&"x"&W192&"x"&S192 -> BR04xBR04x998540.0 | B192: =F192&"x"&W192&"x"&S192&Q192 -> BR04xBR04x998540.0Pallets: 28 | C192: EMPURRADA_1_9_2026 | D192: 07526557001505_CERV | E192: CAMAÇARI | F192: BR04 | I192: Geo NE | J192: 20618821000799 | K192: OPERALOG | L192: 390268 | N192: 1 | Q192: Pallets: 28 | R192: Unidade: INOVA LOG/BACABAL (MA) | S192: 998540.0 | T192: Revenda | U192: FALSE | V192: Unidade: CERVEJARIA CAMAÇARI | Região: NE | W192: BR04 | X192: 421 | Y192: 12500 | Z192: 2918 | AA192: 3039.3 | AB192: 1440 | AC192: 36000 | AD192: CERVEJARIA CAMAÇARI_INOVA LOG/BACABAL (MA)_28_false | AG192: 1.77 | AH192: 115.5 | AI192: 0 | AJ192: 25 | AK192: 3.83 | AL192: 1.77 | AM192: 3 | AN192: 2.88 | AO192: FALSE | AP192: 20474.39 | AQ192: 25637.85 | AR192: 20246.22 | AS192: 20474.39 | AT192: 22561.31 | AU192: 3.83 | AV192: 0.01 | AW192: 0.21 | AX192: 0.1 | AY192: 0.31 | AZ192: 0 | BA192: 0.39 | BB192: 0.46 | BC192: 0 | BD192: 10727.15 | BE192: 19.92 | BF192: 579.2 | BG192: 279.31 | BH192: 853.72 | BI192: 5436.15 | BJ192: 1085.57 | BK192: 1265.2 | BL192: 0 | BM192: FALSE | BN192: 1440 | BO192: 12 | BP192: 3119.91 | BQ192: 1399 | BR192: 2798 | BS192: 30204.59 | BT192: 28999.11 | BU192: 1399 | BV192: 0.01 | BW192: 0.21 | BX192: 0.31 | BY192: 0.1 | CA192: 0 | CB192: 0 | CC192: 0 | CD192: 12 | CE192: 0 | CF192: 0 | CG192: -8 | CH192: 0.39 | CI192: 28.22 | CJ192: 0 | CK192: 437.68 | CL192: 1907.11 | CM192: 202400 | CN192: 3 | CO192: 30204.59 | CP192: 4611.33 | CQ192: 0.46 | CR192: 0.43 | CS192: Região: NE | CT192: 0 | CU192: 0 | CV192: 60 | CW192: 60 | CX192: 60 | CY192: 181.3 | CZ192: 60 | DA192: 2798 | DB192: TRUE | DC192: FALSE | DD192: Cargo: MODELO EQUIPE ATIVA ATUAL | DE192: 3 | DF192: 60 | DG192: 202400 | DH192: ef2f42b3-2e69-4fac-9098-f867ed10e206
A193: =F193&"x"&W193&"x"&S193 -> BR04xBR04x1018957.0 | B193: =F193&"x"&W193&"x"&S193&Q193 -> BR04xBR04x1018957.0Pallets: 28 | C193: EMPURRADA_1_9_2026 | D193: 07526557001505_CERV | E193: CAMAÇARI | F193: BR04 | I193: Geo NE | J193: 20618821000799 | K193: OPERALOG | L193: 390268 | N193: 1 | Q193: Pallets: 28 | R193: Unidade: 1018957-CBM/CARPINA (PE) | S193: 1018957.0 | T193: Revenda | U193: FALSE | V193: Unidade: CERVEJARIA CAMAÇARI | Região: NE | W193: BR04 | X193: 421 | Y193: 12500 | Z193: 1761 | AA193: 1882.3 | AB193: 1440 | AC193: 36000 | AD193: CERVEJARIA CAMAÇARI_1018957-CBM/CARPINA (PE)_28_false | AG193: 1.77 | AH193: 115.5 | AI193: 0 | AJ193: 25 | AK193: 3.83 | AL193: 1.77 | AM193: 3 | AN193: 2.88 | AO193: FALSE | AP193: 12584.61 | AQ193: 15758.34 | AR193: 12444.36 | AS193: 12584.61 | AT193: 13867.34 | AU193: 3.83 | AV193: 0.01 | AW193: 0.21 | AX193: 0.1 | AY193: 0.31 | AZ193: 0 | BA193: 0.39 | BB193: 0.47 | BC193: 0 | BD193: 6291.37 | BE193: 12.02 | BF193: 349.54 | BG193: 163.81 | BH193: 500.7 | BI193: 3726.7 | BJ193: 636.68 | BK193: 763.54 | BL193: 0 | BM193: FALSE | BN193: 1440 | BO193: 12 | BP193: 1917.65 | BQ193: 820.5 | BR193: 1641 | BS193: 29353.49 | BT193: 27461.88 | BU193: 820.5 | BV193: 0.01 | BW193: 0.21 | BX193: 0.31 | BY193: 0.1 | CA193: 0 | CB193: 0 | CC193: 0 | CD193: 12 | CE193: 0 | CF193: 0 | CG193: -8 | CH193: 0.39 | CI193: 28.22 | CJ193: 0 | CK193: 437.68 | CL193: 1907.11 | CM193: 202400 | CN193: 3 | CO193: 29353.49 | CP193: 4611.33 | CQ193: 0.47 | CR193: 0.72 | CS193: Região: NE | CT193: 0 | CU193: 0 | CV193: 60 | CW193: 60 | CX193: 60 | CY193: 181.3 | CZ193: 60 | DA193: 1641 | DB193: TRUE | DC193: FALSE | DD193: Cargo: MODELO EQUIPE ATIVA ATUAL | DE193: 3 | DF193: 60 | DG193: 202400 | DH193: bf78fa51-8c06-487b-8344-0307470a574f
A194: =F194&"x"&W194&"x"&S194 -> BR04xBR04x1019147.0 | B194: =F194&"x"&W194&"x"&S194&Q194 -> BR04xBR04x1019147.0Pallets: 28 | C194: EMPURRADA_1_9_2026 | D194: 07526557001505_CERV | E194: CAMAÇARI | F194: BR04 | I194: Geo NE | J194: 20618821000799 | K194: OPERALOG | L194: 390268 | N194: 1 | Q194: Pallets: 28 | R194: Unidade: 1019147-CBM/PALMARES (PE) | S194: 1019147.0 | T194: Revenda | U194: FALSE | V194: Unidade: CERVEJARIA CAMAÇARI | Região: NE | W194: BR04 | X194: 421 | Y194: 12500 | Z194: 1427 | AA194: 1548.3 | AB194: 1440 | AC194: 36000 | AD194: CERVEJARIA CAMAÇARI_1019147-CBM/PALMARES (PE)_28_false | AG194: 1.77 | AH194: 115.5 | AI194: 0 | AJ194: 25 | AK194: 3.83 | AL194: 1.77 | AM194: 3 | AN194: 2.88 | AO194: FALSE | AP194: 10307 | AQ194: 12906.34 | AR194: 10192.14 | AS194: 10307 | AT194: 11357.58 | AU194: 3.83 | AV194: 0.01 | AW194: 0.22 | AX194: 0.1 | AY194: 0.31 | AZ194: 0 | BA194: 0.39 | BB194: 0.48 | BC194: 0 | BD194: 5010.86 | BE194: 9.74 | BF194: 283.25 | BG194: 130.47 | BH194: 398.79 | BI194: 3233.21 | BJ194: 507.09 | BK194: 618.73 | BL194: 0 | BM194: FALSE | BN194: 1440 | BO194: 12 | BP194: 1570.59 | BQ194: 653.5 | BR194: 1307 | BS194: 28851.09 | BT194: 26590.78 | BU194: 653.5 | BV194: 0.01 | BW194: 0.22 | BX194: 0.31 | BY194: 0.1 | CA194: 0 | CB194: 0 | CC194: 0 | CD194: 12 | CE194: 0 | CF194: 0 | CG194: -8 | CH194: 0.39 | CI194: 28.22 | CJ194: 0 | CK194: 437.68 | CL194: 1907.11 | CM194: 202400 | CN194: 3 | CO194: 28851.09 | CP194: 4611.33 | CQ194: 0.48 | CR194: 0.88 | CS194: Região: NE | CT194: 0 | CU194: 0 | CV194: 60 | CW194: 60 | CX194: 60 | CY194: 181.3 | CZ194: 60 | DA194: 1307 | DB194: TRUE | DC194: FALSE | DD194: Cargo: MODELO EQUIPE ATIVA ATUAL | DE194: 3 | DF194: 60 | DG194: 202400 | DH194: 82f07bae-8e32-4ec6-87e1-6521f794ed6c
A195: =F195&"x"&W195&"x"&S195 -> BR04xBR5Dx1031295.0 | B195: =F195&"x"&W195&"x"&S195&Q195 -> BR04xBR5Dx1031295.0Pallets: 28 | C195: EMPURRADA_1_9_2026 | D195: 07526557001505_CERV | E195: CAMAÇARI | F195: BR04 | I195: Geo NE | J195: 20618821000799 | K195: OPERALOG | L195: 390268 | N195: 1 | Q195: Pallets: 28 | R195: Unidade: REVALLE AGRESTE/SERRINHA (BA) | Região: NE | S195: 1031295.0 | T195: Revenda | U195: FALSE | V195: Unidade: CDR BAHIA | Região: NE | W195: BR5D | X195: 505 | Y195: 12500 | Z195: 463 | AA195: 532.25 | AB195: 1440 | AC195: 36000 | AD195: CDR BAHIA_REVALLE AGRESTE/SERRINHA (BA)_28_false | AG195: 1.73 | AH195: 115.5 | AI195: 0 | AJ195: 25 | AK195: 3.92 | AL195: 1.73 | AM195: 3 | AN195: 2.88 | AO195: FALSE | AP195: 3733.7 | AQ195: 5017.4 | AR195: 3689.08 | AS195: 3733.7 | AT195: 4114.27 | AU195: 3.92 | AV195: 0.01 | AW195: 0.27 | AX195: 0.1 | AY195: 0.31 | AZ195: 0.17 | BA195: 0.4 | BB195: 0.59 | BC195: 0 | BD195: 1344.24 | BE195: 3.16 | BF195: 91.9 | BG195: 34.24 | BH195: 104.66 | BI195: 1774.34 | BJ195: 135.79 | BK195: 200.75 | BL195: 0 | BM195: FALSE | BN195: 1440 | BO195: 18 | BP195: 923.8 | BQ195: 171.5 | BR195: 343 | BS195: 23335.85 | BT195: 20299.67 | BU195: 171.5 | BV195: 0.01 | BW195: 0.27 | BX195: 0.31 | BY195: 0.1 | CA195: 58.92 | CB195: 9.82 | CC195: 0.17 | CD195: 18 | CE195: 0 | CF195: -2 | CG195: -8 | CH195: 0.4 | CI195: 28.22 | CJ195: 0 | CK195: 437.68 | CL195: 1907.11 | CM195: 198352 | CN195: 3 | CO195: 23335.85 | CP195: 4611.33 | CQ195: 0.59 | CR195: 2.72 | CS195: Região: NE | CT195: 0 | CU195: 0 | CV195: 60 | CW195: 60 | CX195: 60 | CY195: 129.25 | CZ195: 60 | DA195: 343 | DB195: TRUE | DC195: FALSE | DD195: Cargo: MODELO EQUIPE ATIVA ATUAL | DE195: 3 | DF195: 60 | DG195: 198352 | DH195: d1ed3d65-6d40-4923-ba6c-b9546236236b
A196: =F196&"x"&W196&"x"&S196 -> BR04xBR5Dx1028510.0 | B196: =F196&"x"&W196&"x"&S196&Q196 -> BR04xBR5Dx1028510.0Pallets: 28 | C196: EMPURRADA_1_9_2026 | D196: 07526557001505_CERV | E196: CAMAÇARI | F196: BR04 | I196: Geo NE | J196: 20618821000799 | K196: OPERALOG | L196: 390268 | N196: 1 | Q196: Pallets: 28 | R196: Unidade: DBS/SANTALUZ(BA) | Região: NE | S196: 1028510.0 | T196: Revenda | U196: FALSE | V196: Unidade: CDR BAHIA | Região: NE | W196: BR5D | X196: 505 | Y196: 12500 | Z196: 644 | AA196: 713.25 | AB196: 1440 | AC196: 36000 | AD196: CDR BAHIA_DBS/SANTALUZ(BA)_28_false | AG196: 1.77 | AH196: 115.5 | AI196: 0 | AJ196: 25 | AK196: 3.83 | AL196: 1.77 | AM196: 3 | AN196: 2.88 | AO196: FALSE | AP196: 4967.65 | AQ196: 6675.6 | AR196: 4908.28 | AS196: 4967.65 | AT196: 5473.99 | AU196: 3.83 | AV196: 0.01 | AW196: 0.24 | AX196: 0.1 | AY196: 0.31 | AZ196: 0 | BA196: 0.39 | BB196: 0.54 | BC196: 0 | BD196: 2008.94 | BE196: 4.4 | BF196: 127.83 | BG196: 52.31 | BH196: 159.88 | BI196: 2072.39 | BJ196: 203.3 | BK196: 279.23 | BL196: 0 | BM196: FALSE | BN196: 1440 | BO196: 18 | BP196: 1229.11 | BQ196: 262 | BR196: 524 | BS196: 25630.43 | BT196: 23141.96 | BU196: 262 | BV196: 0.01 | BW196: 0.24 | BX196: 0.31 | BY196: 0.1 | CA196: 0 | CB196: 0 | CC196: 0 | CD196: 18 | CE196: 0 | CF196: 0 | CG196: -8 | CH196: 0.39 | CI196: 28.22 | CJ196: 0 | CK196: 437.68 | CL196: 1907.11 | CM196: 202400 | CN196: 3 | CO196: 25630.43 | CP196: 4611.33 | CQ196: 0.54 | CR196: 1.96 | CS196: Região: NE | CT196: 0 | CU196: 0 | CV196: 60 | CW196: 60 | CX196: 60 | CY196: 129.25 | CZ196: 60 | DA196: 524 | DB196: TRUE | DC196: FALSE | DD196: Cargo: MODELO EQUIPE ATIVA ATUAL | DE196: 3 | DF196: 60 | DG196: 202400 | DH196: e217b480-1016-4c0d-a511-9e5796658d6b
A197: =F197&"x"&W197&"x"&S197 -> BR04xBR04x639257.0 | B197: =F197&"x"&W197&"x"&S197&Q197 -> BR04xBR04x639257.0Pallets: 28 | C197: EMPURRADA_1_9_2026 | D197: 07526557001505_CERV | E197: CAMAÇARI | F197: BR04 | I197: Geo NE | J197: 20618821000799 | K197: OPERALOG | L197: 390268 | N197: 1 | Q197: Pallets: 28 | R197: Unidade: 639257-OLIVEIRA/BREVES(PA) | S197: 639257.0 | T197: Revenda | U197: FALSE | V197: Unidade: CERVEJARIA CAMAÇARI | Região: NE | W197: BR04 | X197: 421 | Y197: 12500 | Z197: 4213 | AA197: 4334.3 | AB197: 1440 | AC197: 36000 | AD197: CERVEJARIA CAMAÇARI_639257-OLIVEIRA/BREVES(PA)_28_false | AG197: 1.77 | AH197: 115.5 | AI197: 0 | AJ197: 25 | AK197: 3.83 | AL197: 1.77 | AM197: 3 | AN197: 2.88 | AO197: FALSE | AP197: 29305.24 | AQ197: 36695.77 | AR197: 28978.66 | AS197: 29305.24 | AT197: 32292.27 | AU197: 3.83 | AV197: 0.01 | AW197: 0.2 | AX197: 0.1 | AY197: 0.31 | AZ197: 0 | BA197: 0.39 | BB197: 0.45 | BC197: 0 | BD197: 15692 | BE197: 28.76 | BF197: 836.24 | BG197: 408.58 | BH197: 1248.85 | BI197: 7349.53 | BJ197: 1588.01 | BK197: 1826.69 | BL197: 0 | BM197: FALSE | BN197: 1440 | BO197: 12 | BP197: 4465.56 | BQ197: 2046.5 | BR197: 4093 | BS197: 30602.78 | BT197: 29746.33 | BU197: 2046.5 | BV197: 0.01 | BW197: 0.2 | BX197: 0.31 | BY197: 0.1 | CA197: 0 | CB197: 0 | CC197: 0 | CD197: 12 | CE197: 0 | CF197: 0 | CG197: -8 | CH197: 0.39 | CI197: 28.22 | CJ197: 0 | CK197: 437.68 | CL197: 1907.11 | CM197: 202400 | CN197: 3 | CO197: 30602.78 | CP197: 4611.33 | CQ197: 0.45 | CR197: 0.3 | CS197: Região: NE | CT197: 0 | CU197: 0 | CV197: 60 | CW197: 60 | CX197: 60 | CY197: 181.3 | CZ197: 60 | DA197: 4093 | DB197: TRUE | DC197: FALSE | DD197: Cargo: MODELO EQUIPE ATIVA ATUAL | DE197: 3 | DF197: 60 | DG197: 202400 | DH197: 68b7d9e9-0b04-42ee-9b0f-fa9426662ca9
A198: =F198&"x"&W198&"x"&S198 -> BR04xBR5Dx1025317.0 | B198: =F198&"x"&W198&"x"&S198&Q198 -> BR04xBR5Dx1025317.0Pallets: 28 | C198: EMPURRADA_1_9_2026 | D198: 07526557001505_CERV | E198: CAMAÇARI | F198: BR04 | I198: Geo NE | J198: 20618821000799 | K198: OPERALOG | L198: 390268 | N198: 1 | Q198: Pallets: 28 | R198: Unidade: 1025317-LITORAL/CAMAMU(BA) | S198: 1025317.0 | T198: Revenda | U198: FALSE | V198: Unidade: CDR BAHIA | Região: NE | W198: BR5D | X198: 505 | Y198: 12500 | Z198: 766 | AA198: 835.25 | AB198: 1440 | AC198: 36000 | AD198: CDR BAHIA_1025317-LITORAL/CAMAMU(BA)_28_false | AG198: 1.77 | AH198: 115.5 | AI198: 0 | AJ198: 25 | AK198: 3.83 | AL198: 1.77 | AM198: 3 | AN198: 2.88 | AO198: FALSE | AP198: 5799.6 | AQ198: 7793.59 | AR198: 5730.3 | AS198: 5799.6 | AT198: 6390.75 | AU198: 3.83 | AV198: 0.01 | AW198: 0.24 | AX198: 0.1 | AY198: 0.31 | AZ198: 0 | BA198: 0.39 | BB198: 0.52 | BC198: 0 | BD198: 2476.68 | BE198: 5.23 | BF198: 152.04 | BG198: 64.49 | BH198: 197.11 | BI198: 2251.99 | BJ198: 250.64 | BK198: 332.13 | BL198: 0 | BM198: FALSE | BN198: 1440 | BO198: 18 | BP198: 1434.95 | BQ198: 323 | BR198: 646 | BS198: 26565.27 | BT198: 24362.77 | BU198: 323 | BV198: 0.01 | BW198: 0.24 | BX198: 0.31 | BY198: 0.1 | CA198: 0 | CB198: 0 | CC198: 0 | CD198: 18 | CE198: 0 | CF198: 0 | CG198: -8 | CH198: 0.39 | CI198: 28.22 | CJ198: 0 | CK198: 437.68 | CL198: 1907.11 | CM198: 202400 | CN198: 3 | CO198: 26565.27 | CP198: 4611.33 | CQ198: 0.52 | CR198: 1.64 | CS198: Região: NE | CT198: 0 | CU198: 0 | CV198: 60 | CW198: 60 | CX198: 60 | CY198: 129.25 | CZ198: 60 | DA198: 646 | DB198: TRUE | DC198: FALSE | DD198: Cargo: MODELO EQUIPE ATIVA ATUAL | DE198: 3 | DF198: 60 | DG198: 202400 | DH198: cd0f7856-82e3-44df-bffc-35e762d974ff
... A203: =F203&"x"&W203&"x"&S203 -> BR04xBR5Dx1028758.0 | B203: =F203&"x"&W203&"x"&S203&Q203 -> BR04xBR5Dx1028758.0Pallets: 28 | C203: EMPURRADA_1_9_2026 | D203: 07526557001505_CERV | E203: CAMAÇARI | F203: BR04 | I203: Geo NE | J203: 20618821000799 | K203: OPERALOG | L203: 390268 | N203: 1 | Q203: Pallets: 28 | R203: Unidade: DBS/MONTE SANTO(BA) | Região: NE | S203: 1028758.0 | T203: Revenda | U203: FALSE | V203: Unidade: CDR BAHIA | Região: NE | W203: BR5D | X203: 505 | Y203: 12500 | Z203: 826 | AA203: 895.25 | AB203: 1440 | AC203: 36000 | AD203: CDR BAHIA_DBS/MONTE SANTO(BA)_28_false | AG203: 1.77 | AH203: 115.5 | AI203: 0 | AJ203: 25 | AK203: 3.83 | AL203: 1.77 | AM203: 3 | AN203: 2.88 | AO203: FALSE | AP203: 6208.76 | AQ203: 8343.42 | AR203: 6134.56 | AS203: 6208.76 | AT203: 6841.61 | AU203: 3.83 | AV203: 0.01 | AW203: 0.23 | AX203: 0.1 | AY203: 0.31 | AZ203: 0.08 | BA203: 0.39 | BB203: 0.51 | BC203: 0 | BD203: 2706.71 | BE203: 5.64 | BF203: 163.95 | BG203: 70.48 | BH203: 215.41 | BI203: 2340.32 | BJ203: 273.91 | BK203: 358.14 | BL203: 0 | BM203: FALSE | BN203: 1440 | BO203: 18 | BP203: 1536.19 | BQ203: 353 | BR203: 706 | BS203: 26923.73 | BT203: 24841.11 | BU203: 353 | BV203: 0.01 | BW203: 0.23 | BX203: 0.31 | BY203: 0.1 | CA203: 58.92 | CB203: 9.82 | CC203: 0.08 | CD203: 18 | CE203: 0 | CF203: 0 | CG203: -8 | CH203: 0.39 | CI203: 28.22 | CJ203: 0 | CK203: 437.68 | CL203: 1907.11 | CM203: 202400 | CN203: 3 | CO203: 26923.73 | CP203: 4611.33 | CQ203: 0.51 | CR203: 1.53 | CS203: Região: NE | CT203: 0 | CU203: 0 | CV203: 60 | CW203: 60 | CX203: 60 | CY203: 129.25 | CZ203: 60 | DA203: 706 | DB203: TRUE | DC203: FALSE | DD203: Cargo: MODELO EQUIPE ATIVA ATUAL | DE203: 3 | DF203: 60 | DG203: 202400 | DH203: db16728f-44c1-4a52-8bed-eba65900b4b5
A204: =F204&"x"&W204&"x"&S204 -> BR04xBR04x29033944.0 | B204: =F204&"x"&W204&"x"&S204&Q204 -> BR04xBR04x29033944.0Pallets: 42 | C204: EMPURRADA_1_9_2026 | D204: 07526557001505_CERV | E204: CAMAÇARI | F204: BR04 | I204: Geo NE | J204: 20618821000799 | K204: OPERALOG | L204: 390268 | N204: 1 | Q204: Pallets: 42 | R204: Unidade: 10274122-SENDAS DISTRIBUIDORA SA(S4) | Região: 0 | S204: 29033944.0 | T204: 881392.0 | U204: FALSE | V204: Unidade: CERVEJARIA CAMAÇARI | Região: NE | W204: BR04 | X204: 421 | Y204: 12500 | Z204: 2965.31 | AA204: 3086.61 | AB204: 1440 | AC204: 36000 | AD204: CERVEJARIA CAMAÇARI_10274122-SENDAS DISTRIBUIDORA SA(S4)_42_false | AE204: null | AF204: null | AG204: 1.92 | AH204: 115.5 | AI204: 0 | AJ204: 25 | AK204: 3.53 | AL204: 1.92 | AM204: 3 | AN204: 2.88 | AO204: FALSE | AP204: 24186.29 | AQ204: 30285.86 | AR204: 23916.75 | AS204: 24186.29 | AT204: 26651.56 | AU204: 3.53 | AV204: 0.01 | AW204: 0.22 | AX204: 0.2 | AY204: 0.31 | AZ204: 0 | BA204: 0.57 | BB204: 0.76 | BC204: 0 | BD204: 10035.85 | BE204: 20.24 | BF204: 612.67 | BG204: 568.07 | BH204: 868.15 | BI204: 8806.41 | BJ204: 1625.56 | BK204: 1379.81 | BL204: 0 | BM204: FALSE | BN204: 1440 | BO204: 12 | BP204: 3685.53 | BQ204: 1418.72 | BR204: 2845.31 | BS204: 30225.26 | BT204: 29037.44 | BU204: 1426.59 | BV204: 0.01 | BW204: 0.22 | BX204: 0.31 | BY204: 0.2 | BZ204: null | CA204: 0 | CB204: 0 | CC204: 0 | CD204: 12 | CE204: 0 | CF204: 0 | CG204: 0 | CH204: 0.57 | CI204: 40.22 | CJ204: 0 | CK204: 475.56 | CL204: 1923.76 | CM204: 202400 | CN204: 4 | CO204: 30225.26 | CP204: 5764.17 | CQ204: 0.76 | CR204: 0.42 | CS204: Região: NE | CT204: 0 | CU204: 0 | CV204: 60 | CW204: 60 | CX204: 60 | CY204: 181.3 | CZ204: 60 | DA204: 2845.31 | DB204: TRUE | DC204: FALSE | DD204: Cargo: MODELO EQUIPE ATIVA ATUAL | DE204: 3 | DF204: 60 | DG204: 202400 | DH204: bf82945c-2823-464f-9bc4-98029bb95802
A205: =F205&"x"&W205&"x"&S205 -> BR04xBR04x29001922.0 | B205: =F205&"x"&W205&"x"&S205&Q205 -> BR04xBR04x29001922.0Pallets: 42 | C205: EMPURRADA_1_9_2026 | D205: 07526557001505_CERV | E205: CAMAÇARI | F205: BR04 | I205: Geo NE | J205: 20618821000799 | K205: OPERALOG | L205: 390268 | N205: 1 | Q205: Pallets: 42 | R205: Unidade: 10242604-ATACADAO S A(S4) | Região: COM-CDD Goiânia | S205: 29001922.0 | T205: 651907.0 | U205: FALSE | V205: Unidade: CERVEJARIA CAMAÇARI | Região: NE | W205: BR04 | X205: 421 | Y205: 12500 | Z205: 2986.53 | AA205: 3107.83 | AB205: 1440 | AC205: 36000 | AD205: CERVEJARIA CAMAÇARI_10242604-ATACADAO S A(S4)_42_false | AE205: null | AF205: null | AG205: 1.92 | AH205: 115.5 | AI205: 0 | AJ205: 25 | AK205: 3.53 | AL205: 1.92 | AM205: 3 | AN205: 2.88 | AO205: FALSE | AP205: 24154.97 | AQ205: 30246.64 | AR205: 23885.78 | AS205: 24154.97 | AT205: 26617.05 | AU205: 3.53 | AV205: 0.01 | AW205: 0.22 | AX205: 0.2 | AY205: 0.31 | AZ205: 0 | BA205: 0.57 | BB205: 0.76 | BC205: 0 | BD205: 10110.69 | BE205: 20.38 | BF205: 616.88 | BG205: 572.3 | BH205: 874.63 | BI205: 8663.53 | BJ205: 1637.69 | BK205: 1389.68 | BL205: 0 | BM205: FALSE | BN205: 1440 | BO205: 12 | BP205: 3680.76 | BQ205: 1429.46 | BR205: 2866.53 | BS205: 30234.32 | BT205: 29054.26 | BU205: 1437.07 | BV205: 0.01 | BW205: 0.22 | BX205: 0.31 | BY205: 0.2 | BZ205: null | CA205: 0 | CB205: 0 | CC205: 0 | CD205: 12 | CE205: 0 | CF205: 0 | CG205: 0 | CH205: 0.57 | CI205: 40.22 | CJ205: 0 | CK205: 475.56 | CL205: 1923.76 | CM205: 202400 | CN205: 4 | CO205: 30234.32 | CP205: 5764.17 | CQ205: 0.76 | CR205: 0.42 | CS205: Região: NE | CT205: 0 | CU205: 0 | CV205: 60 | CW205: 60 | CX205: 60 | CY205: 181.3 | CZ205: 60 | DA205: 2866.53 | DB205: TRUE | DC205: FALSE | DD205: Cargo: MODELO EQUIPE ATIVA ATUAL | DE205: 3 | DF205: 60 | DG205: 202400 | DH205: 119d4788-956e-453a-b3b5-e862a8b55281
A206: =F206&"x"&W206&"x"&S206 -> BR04xBR04x1016620.0 | B206: =F206&"x"&W206&"x"&S206&Q206 -> BR04xBR04x1016620.0Pallets: 28 | C206: EMPURRADA_1_9_2026 | D206: 07526557001505_CERV | E206: CAMAÇARI | F206: BR04 | I206: Geo NE | J206: 20618821000799 | K206: OPERALOG | L206: 390268 | N206: 1 | Q206: Pallets: 28 | R206: Unidade: JODIBE/GARANHUNS | Região: PE | S206: 1016620.0 | T206: Revenda | U206: FALSE | V206: Unidade: CERVEJARIA CAMAÇARI | Região: NE | W206: BR04 | X206: 421 | Y206: 12500 | Z206: 1293.96 | AA206: 1415.26 | AB206: 1440 | AC206: 36000 | AD206: CERVEJARIA CAMAÇARI_JODIBE/GARANHUNS _28_false | AG206: 1.77 | AH206: 115.5 | AI206: 0 | AJ206: 25 | AK206: 3.83 | AL206: 1.77 | AM206: 3 | AN206: 2.88 | AO206: FALSE | AP206: 9399.78 | AQ206: 11770.32 | AR206: 9295.03 | AS206: 9399.78 | AT206: 10357.89 | AU206: 3.83 | AV206: 0.01 | AW206: 0.22 | AX206: 0.1 | AY206: 0.31 | AZ206: 0 | BA206: 0.39 | BB206: 0.48 | BC206: 0 | BD206: 4500.8 | BE206: 8.83 | BF206: 256.84 | BG206: 117.19 | BH206: 358.2 | BI206: 3036.65 | BJ206: 455.47 | BK206: 561.04 | BL206: 0 | BM206: FALSE | BN206: 1440 | BO206: 12 | BP206: 1432.35 | BQ206: 586.98 | BR206: 1173.96 | BS206: 28578.74 | BT206: 26129.29 | BU206: 586.98 | BV206: 0.01 | BW206: 0.22 | BX206: 0.31 | BY206: 0.1 | CA206: 0 | CB206: 0 | CC206: 0 | CD206: 12 | CE206: 0 | CF206: 0 | CG206: -8 | CH206: 0.39 | CI206: 28.22 | CJ206: 0 | CK206: 437.68 | CL206: 1907.11 | CM206: 202400 | CN206: 3 | CO206: 28578.74 | CP206: 4611.33 | CQ206: 0.48 | CR206: 0.97 | CS206: Região: NE | CT206: 0 | CU206: 0 | CV206: 60 | CW206: 60 | CX206: 60 | CY206: 181.3 | CZ206: 60 | DA206: 1173.96 | DB206: TRUE | DC206: FALSE | DD206: Cargo: MODELO EQUIPE ATIVA ATUAL | DE206: 3 | DF206: 60 | DG206: 202400 | DH206: 5e2c3e06-48ee-4d61-81b9-abf4d2ecd4bf
A207: =F207&"x"&W207&"x"&S207 -> BR04xBR5Dx1033913.0 | B207: =F207&"x"&W207&"x"&S207&Q207 -> BR04xBR5Dx1033913.0Pallets: 28 | C207: EMPURRADA_1_9_2026 | D207: 07526557001505_CERV | E207: CAMAÇARI | F207: BR04 | I207: Geo NE | J207: 20618821000799 | K207: OPERALOG | L207: 390268 | N207: 1 | Q207: Pallets: 28 | R207: Unidade: DBS/IPIRÁ (BA) | Região: BA | S207: 1033913.0 | T207: Revenda | U207: FALSE | V207: Unidade: CDR BAHIA | Região: NE | W207: BR5D | X207: 505 | Y207: 12500 | Z207: 510 | AA207: 579.25 | AB207: 1440 | AC207: 36000 | AD207: CDR BAHIA_DBS/IPIRÁ (BA)_28_false | AG207: 1.73 | AH207: 115.5 | AI207: 0 | AJ207: 25 | AK207: 3.92 | AL207: 1.73 | AM207: 3 | AN207: 2.88 | AO207: FALSE | AP207: 4054.24 | AQ207: 5448.15 | AR207: 4005.8 | AS207: 4054.24 | AT207: 4467.49 | AU207: 3.92 | AV207: 0.01 | AW207: 0.26 | AX207: 0.1 | AY207: 0.31 | AZ207: 0 | BA207: 0.4 | BB207: 0.57 | BC207: 0 | BD207: 1528.43 | BE207: 3.48 | BF207: 101.23 | BG207: 38.93 | BH207: 119 | BI207: 1839.19 | BJ207: 154.4 | BK207: 221.13 | BL207: 0 | BM207: FALSE | BN207: 1440 | BO207: 18 | BP207: 1003.11 | BQ207: 195 | BR207: 390 | BS207: 24088.24 | BT207: 21208.46 | BU207: 195 | BV207: 0.01 | BW207: 0.26 | BX207: 0.31 | BY207: 0.1 | CA207: 0 | CB207: 0 | CC207: 0 | CD207: 18 | CE207: 0 | CF207: -2 | CG207: -8 | CH207: 0.4 | CI207: 28.22 | CJ207: 0 | CK207: 437.68 | CL207: 1907.11 | CM207: 198352 | CN207: 3 | CO207: 24088.24 | CP207: 4611.33 | CQ207: 0.57 | CR207: 2.47 | CS207: Região: NE | CT207: 0 | CU207: 0 | CV207: 60 | CW207: 60 | CX207: 60 | CY207: 129.25 | CZ207: 60 | DA207: 390 | DB207: TRUE | DC207: FALSE | DD207: Cargo: MODELO EQUIPE ATIVA ATUAL | DE207: 3 | DF207: 60 | DG207: 198352 | DH207: 9cc5d4bd-f332-4b1a-938f-13363e476353
A208: =F208&"x"&W208&"x"&S208 -> BR04xBR04x29005338.0 | B208: =F208&"x"&W208&"x"&S208&Q208 -> BR04xBR04x29005338.0Pallets: 42 | C208: EMPURRADA_1_9_2026 | D208: 07526557001505_CERV | E208: CAMAÇARI | F208: BR04 | I208: Geo NE | J208: 20618821000799 | K208: OPERALOG | L208: 390268 | N208: 1 | Q208: Pallets: 42 | R208: Unidade: 10244349-ATACADAO S A(S4) | Região: COM-CDD Goiânia | S208: 29005338.0 | T208: 659614.0 | U208: FALSE | V208: Unidade: CERVEJARIA CAMAÇARI | Região: NE | W208: BR04 | X208: 421 | Y208: 12500 | Z208: 2993.03 | AA208: 3114.33 | AB208: 1440 | AC208: 36000 | AD208: CERVEJARIA CAMAÇARI_10244349-ATACADAO S A(S4)_42_false | AE208: null | AF208: null | AG208: 1.92 | AH208: 115.5 | AI208: 0 | AJ208: 25 | AK208: 3.53 | AL208: 1.92 | AM208: 3 | AN208: 2.88 | AO208: FALSE | AP208: 24163.96 | AQ208: 30257.9 | AR208: 23894.68 | AS208: 24163.96 | AT208: 26626.96 | AU208: 3.53 | AV208: 0.01 | AW208: 0.22 | AX208: 0.2 | AY208: 0.31 | AZ208: 0 | BA208: 0.57 | BB208: 0.76 | BC208: 0 | BD208: 10133.62 | BE208: 20.43 | BF208: 618.17 | BG208: 573.6 | BH208: 876.61 | BI208: 8638.14 | BJ208: 1641.4 | BK208: 1392.71 | BL208: 0 | BM208: FALSE | BN208: 1440 | BO208: 12 | BP208: 3682.13 | BQ208: 1433.3 | BR208: 2873.03 | BS208: 30237.07 | BT208: 29059.36 | BU208: 1439.73 | BV208: 0.01 | BW208: 0.22 | BX208: 0.31 | BY208: 0.2 | BZ208: null | CA208: 0 | CB208: 0 | CC208: 0 | CD208: 12 | CE208: 0 | CF208: 0 | CG208: 0 | CH208: 0.57 | CI208: 40.22 | CJ208: 0 | CK208: 475.56 | CL208: 1923.76 | CM208: 202400 | CN208: 4 | CO208: 30237.07 | CP208: 5764.17 | CQ208: 0.76 | CR208: 0.42 | CS208: Região: NE | CT208: 0 | CU208: 0 | CV208: 60 | CW208: 60 | CX208: 60 | CY208: 181.3 | CZ208: 60 | DA208: 2873.03 | DB208: TRUE | DC208: FALSE | DD208: Cargo: MODELO EQUIPE ATIVA ATUAL | DE208: 3 | DF208: 60 | DG208: 202400 | DH208: d7e99bcb-e263-4082-b7d2-e8b8977ad015
A209: =F209&"x"&W209&"x"&S209 -> BR04xBR04x29023701.0 | B209: =F209&"x"&W209&"x"&S209&Q209 -> BR04xBR04x29023701.0Pallets: 42 | C209: EMPURRADA_1_9_2026 | D209: 07526557001505_CERV | E209: CAMAÇARI | F209: BR04 | I209: Geo NE | J209: 20618821000799 | K209: OPERALOG | L209: 390268 | N209: 1 | Q209: Pallets: 42 | R209: Unidade: 10262601-DISTRIBUIDORA ALIMENTOS MIGUELENSE(S4) | Região: 0 | S209: 29023701.0 | T209: 821616.0 | U209: FALSE | V209: Unidade: CERVEJARIA CAMAÇARI | Região: NE | W209: BR04 | X209: 421 | Y209: 12500 | Z209: 470.85 | AA209: 592.15 | AB209: 1440 | AC209: 36000 | AD209: CERVEJARIA CAMAÇARI_10262601-DISTRIBUIDORA ALIMENTOS MIGUELENSE(S4)_42_false | AE209: null | AF209: null | AG209: 1.92 | AH209: 115.5 | AI209: 0 | AJ209: 25 | AK209: 3.53 | AL209: 1.92 | AM209: 3 | AN209: 2.88 | AO209: FALSE | AP209: 3912.73 | AQ209: 5257.98 | AR209: 3865.97 | AS209: 3912.73 | AT209: 4311.55 | AU209: 3.53 | AV209: 0.01 | AW209: 0.34 | AX209: 0.2 | AY209: 0.31 | AZ209: 0 | BA209: 0.57 | BB209: 0.98 | BC209: 0 | BD209: 1237.5 | BE209: 3.21 | BF209: 117.54 | BG209: 70.05 | BH209: 107.05 | BI209: 1911.09 | BJ209: 200.45 | BK209: 219.09 | BL209: 0 | BM209: FALSE | BN209: 1440 | BO209: 18 | BP209: 968.1 | BQ209: 175.97 | BR209: 350.85 | BS209: 23471.97 | BT209: 18663.81 | BU209: 174.88 | BV209: 0.01 | BW209: 0.34 | BX209: 0.31 | BY209: 0.2 | BZ209: null | CA209: 0 | CB209: 0 | CC209: 0 | CD209: 18 | CE209: 0 | CF209: 0 | CG209: 0 | CH209: 0.57 | CI209: 40.22 | CJ209: 0 | CK209: 475.56 | CL209: 1923.76 | CM209: 202400 | CN209: 4 | CO209: 23471.97 | CP209: 5764.17 | CQ209: 0.98 | CR209: 2.68 | CS209: Região: NE | CT209: 0 | CU209: 0 | CV209: 60 | CW209: 60 | CX209: 60 | CY209: 181.3 | CZ209: 60 | DA209: 350.85 | DB209: TRUE | DC209: FALSE | DD209: Cargo: MODELO EQUIPE ATIVA ATUAL | DE209: 3 | DF209: 60 | DG209: 202400 | DH209: 3f4cbe41-00d6-49a1-9dd6-40aed8f42d60
A210: =F210&"x"&W210&"x"&S210 -> BR04xBR04xBR1X | B210: =F210&"x"&W210&"x"&S210&Q210 -> BR04xBR04xBR1XPallets: 42 | C210: EMPURRADA_1_9_2026 | D210: 07526557001505_CERV | E210: CAMAÇARI | F210: BR04 | I210: Geo NE | J210: 20618821000799 | K210: OPERALOG | L210: 390268 | N210: 1 | Q210: Pallets: 42 | R210: Unidade: CD SUL MARANHÃO | Região: NO | S210: BR1X | T210: 67 | U210: FALSE | V210: Unidade: CERVEJARIA CAMAÇARI | Região: NE | W210: BR04 | X210: 421 | Y210: 12500 | Z210: 3065.04 | AA210: 3239.8 | AB210: 1440 | AC210: 36000 | AD210: CERVEJARIA CAMAÇARI_CD SUL MARANHÃO_42_false | AE210: null | AF210: null | AG210: 1.92 | AH210: 115.5 | AI210: 0 | AJ210: 25 | AK210: 3.53 | AL210: 1.92 | AM210: 3 | AN210: 2.88 | AO210: FALSE | AP210: 19557.12 | AQ210: 24489.25 | AR210: 19339.17 | AS210: 19557.12 | AT210: 21550.54 | AU210: 3.53 | AV210: 0.01 | AW210: 0.22 | AX210: 0.2 | AY210: 0.31 | AZ210: 0 | BA210: 0.57 | BB210: 0.76 | BC210: 0 | BD210: 10387.61 | BE210: 20.92 | BF210: 643.07 | BG210: 587.98 | BH210: 898.58 | BI210: 3309.58 | BJ210: 1682.54 | BK210: 1808.88 | BL210: 0 | BM210: FALSE | BN210: 1440 | BO210: 12 | BP210: 2980.13 | BQ210: 1473.04 | BR210: 2945.04 | BS210: 30266.74 | BT210: 28634.1 | BU210: 1472 | BV210: 0.01 | BW210: 0.22 | BX210: 0.31 | BY210: 0.2 | BZ210: null | CA210: 0 | CB210: 0 | CC210: 0 | CD210: 12 | CE210: 0 | CF210: 0 | CG210: 0 | CH210: 0.57 | CI210: 40.22 | CJ210: 0 | CK210: 475.56 | CL210: 1923.76 | CM210: 202400 | CN210: 4 | CO210: 30266.74 | CP210: 5764.17 | CQ210: 0.76 | CR210: 0.41 | CS210: Região: NE | CT210: 0 | CU210: 0 | CV210: 60 | CW210: 128.76 | CX210: 60 | CY210: 166 | CZ210: 60 | DA210: 2945.04 | DB210: TRUE | DC210: FALSE | DD210: Cargo: MODELO EQUIPE ATIVA ATUAL | DE210: 3 | DF210: 60 | DG210: 202400 | DH210: 4aff1af1-a1ec-4bb4-aa73-a9f619689d76
A211: =F211&"x"&W211&"x"&S211 -> BR04xBR04x29022387.0 | B211: =F211&"x"&W211&"x"&S211&Q211 -> BR04xBR04x29022387.0Pallets: 42 | C211: EMPURRADA_1_9_2026 | D211: 07526557001505_CERV | E211: CAMAÇARI | F211: BR04 | I211: Geo NE | J211: 20618821000799 | K211: OPERALOG | L211: 390268 | N211: 1 | Q211: Pallets: 42 | R211: Unidade: 10261816-PEFISA ALIMENTOS LTDA(S4) | S211: 29022387.0 | T211: 799203.0 | U211: FALSE | V211: Unidade: CERVEJARIA CAMAÇARI | Região: NE | W211: BR04 | X211: 421 | Y211: 12500 | Z211: 468.84 | AA211: 590.14 | AB211: 1440 | AC211: 36000 | AD211: CERVEJARIA CAMAÇARI_10261816-PEFISA ALIMENTOS LTDA(S4)_42_false | AE211: null | AF211: null | AG211: 1.92 | AH211: 115.5 | AI211: 0 | AJ211: 25 | AK211: 3.53 | AL211: 1.92 | AM211: 3 | AN211: 2.88 | AO211: FALSE | AP211: 3912.67 | AQ211: 5257.91 | AR211: 3865.92 | AS211: 3912.67 | AT211: 4311.49 | AU211: 3.53 | AV211: 0.01 | AW211: 0.34 | AX211: 0.2 | AY211: 0.31 | AZ211: 0 | BA211: 0.57 | BB211: 0.98 | BC211: 0 | BD211: 1230.41 | BE211: 3.2 | BF211: 117.14 | BG211: 69.65 | BH211: 106.44 | BI211: 1921.63 | BJ211: 199.3 | BK211: 218.16 | BL211: 0 | BM211: FALSE | BN211: 1440 | BO211: 18 | BP211: 968.08 | BQ211: 175.62 | BR211: 348.84 | BS211: 23437.55 | BT211: 18620.09 | BU211: 173.22 | BV211: 0.01 | BW211: 0.34 | BX211: 0.31 | BY211: 0.2 | BZ211: null | CA211: 0 | CB211: 0 | CC211: 0 | CD211: 18 | CE211: 0 | CF211: 0 | CG211: 0 | CH211: 0.57 | CI211: 40.22 | CJ211: 0 | CK211: 475.56 | CL211: 1923.76 | CM211: 202400 | CN211: 4 | CO211: 23437.55 | CP211: 5764.17 | CQ211: 0.98 | CR211: 2.69 | CS211: Região: NE | CT211: 0 | CU211: 0 | CV211: 60 | CW211: 60 | CX211: 60 | CY211: 181.3 | CZ211: 60 | DA211: 348.84 | DB211: TRUE | DC211: FALSE | DD211: Cargo: MODELO EQUIPE ATIVA ATUAL | DE211: 3 | DF211: 60 | DG211: 202400 | DH211: 95c6c152-a8e4-4f70-ab3c-3bcafb7fbfc3
A212: =F212&"x"&W212&"x"&S212 -> BR04xBR04xBR1T | B212: =F212&"x"&W212&"x"&S212&Q212 -> BR04xBR04xBR1TPallets: 42 | C212: EMPURRADA_1_9_2026 | D212: 07526557001505_CERV | E212: CAMAÇARI | F212: BR04 | I212: Geo NE | J212: 20618821000799 | K212: OPERALOG | L212: 390268 | N212: 1 | Q212: Pallets: 42 | R212: Unidade: CD GUANAMBI | Região: NE | S212: BR1T | T212: 52 | U212: FALSE | V212: Unidade: CERVEJARIA CAMAÇARI | Região: NE | W212: BR04 | X212: 421 | Y212: 12500 | Z212: 1429.6 | AA212: 1585.42 | AB212: 1440 | AC212: 36000 | AD212: CERVEJARIA CAMAÇARI_CD GUANAMBI_42_false | AE212: null | AF212: null | AG212: 1.92 | AH212: 115.5 | AI212: 0 | AJ212: 25 | AK212: 3.53 | AL212: 1.92 | AM212: 3 | AN212: 2.88 | AO212: FALSE | AP212: 10174.08 | AQ212: 13672.08 | AR212: 10052.5 | AS212: 10174.08 | AT212: 11211.11 | AU212: 3.53 | AV212: 0.01 | AW212: 0.24 | AX212: 0.2 | AY212: 0.31 | AZ212: 0 | BA212: 0.57 | BB212: 0.8 | BC212: 0 | BD212: 4619.16 | BE212: 9.76 | BF212: 314.69 | BG212: 261.46 | BH212: 399.58 | BI212: 2855.96 | BJ212: 748.19 | BK212: 843.7 | BL212: 0 | BM212: FALSE | BN212: 1440 | BO212: 18 | BP212: 2517.3 | BQ212: 654.8 | BR212: 1309.6 | BS212: 28855.9 | BT212: 26019.86 | BU212: 654.8 | BV212: 0.01 | BW212: 0.24 | BX212: 0.31 | BY212: 0.2 | BZ212: null | CA212: 0 | CB212: 0 | CC212: 0 | CD212: 18 | CE212: 0 | CF212: 0 | CG212: 0 | CH212: 0.57 | CI212: 40.22 | CJ212: 0 | CK212: 475.56 | CL212: 1923.76 | CM212: 202400 | CN212: 4 | CO212: 28855.9 | CP212: 5764.17 | CQ212: 0.8 | CR212: 0.88 | CS212: Região: NE | CT212: 0 | CU212: 0 | CV212: 60 | CW212: 104.57 | CX212: 60 | CY212: 171.25 | CZ212: 60 | DA212: 1309.6 | DB212: TRUE | DC212: FALSE | DD212: Cargo: MODELO EQUIPE ATIVA ATUAL | DE212: 3 | DF212: 60 | DG212: 202400 | DH212: 82e77a44-efb3-4b4b-8a52-80c940d2bdfc
A213: =F213&"x"&W213&"x"&S213 -> BR04xBR04x29020738.0 | B213: =F213&"x"&W213&"x"&S213&Q213 -> BR04xBR04x29020738.0Pallets: 42 | C213: EMPURRADA_1_9_2026 | D213: 07526557001505_CERV | E213: CAMAÇARI | F213: BR04 | I213: Geo NE | J213: 20618821000799 | K213: OPERALOG | L213: 390268 | N213: 1 | Q213: Pallets: 42 | R213: Unidade: 10282568-COMPANHIA BRASILEIRA DISTRIBUICAO(S4) | Região: 0 | S213: 29020738.0 | T213: 782998.0 | U213: FALSE | V213: Unidade: CERVEJARIA CAMAÇARI | Região: NE | W213: BR04 | X213: 421 | Y213: 12500 | Z213: 2984.4 | AA213: 3105.7 | AB213: 1440 | AC213: 36000 | AD213: CERVEJARIA CAMAÇARI_10282568-COMPANHIA BRASILEIRA DISTRIBUICAO(S4)_42_false | AE213: null | AF213: null | AG213: 1.92 | AH213: 115.5 | AI213: 0 | AJ213: 25 | AK213: 3.53 | AL213: 1.92 | AM213: 3 | AN213: 2.88 | AO213: FALSE | AP213: 23902.25 | AQ213: 29930.2 | AR213: 23635.88 | AS213: 23902.25 | AT213: 26338.57 | AU213: 3.53 | AV213: 0.01 | AW213: 0.22 | AX213: 0.2 | AY213: 0.31 | AZ213: 0 | BA213: 0.57 | BB213: 0.76 | BC213: 0 | BD213: 10103.18 | BE213: 20.37 | BF213: 616.45 | BG213: 571.88 | BH213: 873.98 | BI213: 8424.86 | BJ213: 1636.47 | BK213: 1388.69 | BL213: 0 | BM213: FALSE | BN213: 1440 | BO213: 12 | BP213: 3642.25 | BQ213: 1428.25 | BR213: 2864.4 | BS213: 30233.41 | BT213: 29052.58 | BU213: 1436.15 | BV213: 0.01 | BW213: 0.22 | BX213: 0.31 | BY213: 0.2 | BZ213: null | CA213: 0 | CB213: 0 | CC213: 0 | CD213: 12 | CE213: 0 | CF213: 0 | CG213: 0 | CH213: 0.57 | CI213: 40.22 | CJ213: 0 | CK213: 475.56 | CL213: 1923.76 | CM213: 202400 | CN213: 4 | CO213: 30233.41 | CP213: 5764.17 | CQ213: 0.76 | CR213: 0.42 | CS213: Região: NE | CT213: 0 | CU213: 0 | CV213: 60 | CW213: 60 | CX213: 60 | CY213: 181.3 | CZ213: 60 | DA213: 2864.4 | DB213: TRUE | DC213: FALSE | DD213: Cargo: MODELO EQUIPE ATIVA ATUAL | DE213: 3 | DF213: 60 | DG213: 202400 | DH213: c964c63d-e2bf-45e4-a326-b8952cb25417
A214: =F214&"x"&W214&"x"&S214 -> BR04xBR02xBR5D | B214: =F214&"x"&W214&"x"&S214&Q214 -> BR04xBR02xBR5DPallets: 42 | C214: EMPURRADA_1_9_2026 | D214: 07526557001505_CERV | E214: CAMAÇARI | F214: BR04 | I214: Geo NE | J214: 20618821000799 | K214: OPERALOG | L214: 390268 | N214: 1 | Q214: Pallets: 42 | R214: Unidade: CDR BAHIA | Região: NE | S214: BR5D | T214: 505 | U214: FALSE | V214: Unidade: CERVEJARIA ESTÂNCIA | Região: NE | W214: BR02 | X214: 205 | Y214: 12500 | Z214: 570.8 | AA214: 787.31 | AB214: 1440 | AC214: 36000 | AD214: CERVEJARIA ESTÂNCIA_CDR BAHIA_42_false | AE214: null | AF214: null | AG214: 1.92 | AH214: 115.5 | AI214: 0 | AJ214: 25 | AK214: 3.53 | AL214: 1.92 | AM214: 3 | AN214: 2.88 | AO214: FALSE | AP214: 4587.2 | AQ214: 5744.05 | AR214: 4536.08 | AS214: 4587.2 | AT214: 5054.76 | AU214: 3.53 | AV214: 0.01 | AW214: 0.35 | AX214: 0.2 | AY214: 0.31 | AZ214: 0 | BA214: 0.57 | BB214: 0.93 | BC214: 0 | BD214: 1590.04 | BE214: 3.9 | BF214: 156.27 | BG214: 90 | BH214: 137.55 | BI214: 1963.9 | BJ214: 257.55 | BK214: 336.87 | BL214: 0 | BM214: FALSE | BN214: 1440 | BO214: 12 | BP214: 699 | BQ214: 225.4 | BR214: 450.8 | BS214: 24877.72 | BT214: 18036.35 | BU214: 225.4 | BV214: 0.01 | BW214: 0.35 | BX214: 0.31 | BY214: 0.2 | BZ214: null | CA214: 0 | CB214: 0 | CC214: 0 | CD214: 12 | CE214: 0 | CF214: 0 | CG214: 0 | CH214: 0.57 | CI214: 40.22 | CJ214: 0 | CK214: 475.56 | CL214: 1923.76 | CM214: 202400 | CN214: 4 | CO214: 24877.72 | CP214: 5764.17 | CQ214: 0.93 | CR214: 2.21 | CS214: Região: NE | CT214: 0 | CU214: 0 | CV214: 60 | CW214: 183.71 | CX214: 60 | CY214: 152.8 | CZ214: 60 | DA214: 450.8 | DB214: TRUE | DC214: FALSE | DD214: Cargo: MODELO EQUIPE ATIVA ATUAL | DE214: 3 | DF214: 60 | DG214: 202400 | DH214: d70a4811-137e-440b-84ca-27ac51160406
A215: =F215&"x"&W215&"x"&S215 -> BR04xBR04x29032075.0 | B215: =F215&"x"&W215&"x"&S215&Q215 -> BR04xBR04x29032075.0Pallets: 42 | C215: EMPURRADA_1_9_2026 | D215: 07526557001505_CERV | E215: CAMAÇARI | F215: BR04 | I215: Geo NE | J215: 20618821000799 | K215: OPERALOG | L215: 390268 | N215: 1 | Q215: Pallets: 42 | R215: Unidade: 10265686-SENDAS DISTRIBUIDORA SA(S4) | Região: 0 | S215: 29032075.0 | T215: 862258.0 | U215: FALSE | V215: Unidade: CERVEJARIA CAMAÇARI | Região: NE | W215: BR04 | X215: 421 | Y215: 12500 | Z215: 1448 | AA215: 1569.3 | AB215: 1440 | AC215: 36000 | AD215: CERVEJARIA CAMAÇARI_10265686-SENDAS DISTRIBUIDORA SA(S4)_42_false | AE215: null | AF215: null | AG215: 1.92 | AH215: 115.5 | AI215: 0 | AJ215: 25 | AK215: 3.53 | AL215: 1.92 | AM215: 3 | AN215: 2.88 | AO215: FALSE | AP215: 12269.53 | AQ215: 16487.98 | AR215: 12122.91 | AS215: 12269.53 | AT215: 13520.14 | AU215: 3.53 | AV215: 0.01 | AW215: 0.23 | AX215: 0.2 | AY215: 0.31 | AZ215: 0 | BA215: 0.57 | BB215: 0.8 | BC215: 0 | BD215: 4684.06 | BE215: 9.88 | BF215: 311.49 | BG215: 265.14 | BH215: 405.2 | BI215: 5014.66 | BJ215: 758.7 | BK215: 673.78 | BL215: 0 | BM215: FALSE | BN215: 1440 | BO215: 18 | BP215: 3035.76 | BQ215: 664 | BR215: 1328 | BS215: 28889.5 | BT215: 26656.47 | BU215: 664 | BV215: 0.01 | BW215: 0.23 | BX215: 0.31 | BY215: 0.2 | BZ215: null | CA215: 0 | CB215: 0 | CC215: 0 | CD215: 18 | CE215: 0 | CF215: 0 | CG215: 0 | CH215: 0.57 | CI215: 40.22 | CJ215: 0 | CK215: 475.56 | CL215: 1923.76 | CM215: 202400 | CN215: 4 | CO215: 28889.5 | CP215: 5764.17 | CQ215: 0.8 | CR215: 0.87 | CS215: Região: NE | CT215: 0 | CU215: 0 | CV215: 60 | CW215: 60 | CX215: 60 | CY215: 181.3 | CZ215: 60 | DA215: 1328 | DB215: TRUE | DC215: FALSE | DD215: Cargo: MODELO EQUIPE ATIVA ATUAL | DE215: 3 | DF215: 60 | DG215: 202400 | DH215: 6fcdc79a-62cc-4dbf-afe4-344aded72339
A216: =F216&"x"&W216&"x"&S216 -> BR04xBR06xBR02 | B216: =F216&"x"&W216&"x"&S216&Q216 -> BR04xBR06xBR02Pallets: 42 | C216: EMPURRADA_1_9_2026 | D216: 07526557001505_CERV | E216: CAMAÇARI | F216: BR04 | I216: Geo NE | J216: 20618821000799 | K216: OPERALOG | L216: 390268 | N216: 1 | Q216: Pallets: 42 | R216: Unidade: CERVEJARIA ESTÂNCIA | Região: NE | S216: BR02 | T216: 205 | U216: FALSE | V216: Unidade: CDR JOAO PESSOA | Região: NE | W216: BR06 | X216: 426 | Y216: 12500 | Z216: 1434.2 | AA216: 1690.93 | AB216: 1440 | AC216: 36000 | AD216: CDR JOAO PESSOA_CERVEJARIA ESTÂNCIA_42_false | AE216: null | AF216: null | AG216: 1.92 | AH216: 115.5 | AI216: 0 | AJ216: 25 | AK216: 3.53 | AL216: 1.92 | AM216: 3 | AN216: 2.88 | AO216: FALSE | AP216: 9386.14 | AQ216: 11753.25 | AR216: 9281.54 | AS216: 9386.14 | AT216: 10342.86 | AU216: 3.53 | AV216: 0.01 | AW216: 0.26 | AX216: 0.2 | AY216: 0.31 | AZ216: 0 | BA216: 0.57 | BB216: 0.8 | BC216: 0 | BD216: 4635.39 | BE216: 9.79 | BF216: 335.63 | BG216: 262.38 | BH216: 400.99 | BI216: 2040.13 | BJ216: 750.82 | BK216: 846.42 | BL216: 0 | BM216: FALSE | BN216: 1440 | BO216: 12 | BP216: 1430.27 | BQ216: 657.1 | BR216: 1314.2 | BS216: 28864.38 | BT216: 24481.97 | BU216: 657.1 | BV216: 0.01 | BW216: 0.26 | BX216: 0.31 | BY216: 0.2 | BZ216: null | CA216: 0 | CB216: 0 | CC216: 0 | CD216: 12 | CE216: 0 | CF216: 0 | CG216: 0 | CH216: 0.57 | CI216: 40.22 | CJ216: 0 | CK216: 475.56 | CL216: 1923.76 | CM216: 202400 | CN216: 4 | CO216: 28864.38 | CP216: 5764.17 | CQ216: 0.8 | CR216: 0.88 | CS216: Região: NE | CT216: 0 | CU216: 0 | CV216: 60 | CW216: 92.43 | CX216: 60 | CY216: 284.3 | CZ216: 60 | DA216: 1314.2 | DB216: TRUE | DC216: FALSE | DD216: Cargo: MODELO EQUIPE ATIVA ATUAL | DE216: 3 | DF216: 60 | DG216: 202400 | DH216: 388affd4-4974-4a76-84be-a733e2a43683
A217: =F217&"x"&W217&"x"&S217 -> BR04xBR12xBR2P | B217: =F217&"x"&W217&"x"&S217&Q217 -> BR04xBR12xBR2PPallets: 42 | C217: EMPURRADA_1_9_2026 | D217: 07526557001505_CERV | E217: CAMAÇARI | F217: BR04 | I217: Geo NE | J217: 20618821000799 | K217: OPERALOG | L217: 390268 | N217: 1 | Q217: Pallets: 42 | R217: Unidade: CD F.SANTANA | Região: NE | S217: BR2P | T217: 180 | U217: FALSE | V217: Unidade: CERVEJARIA CEBRASA | Região: CO | W217: BR12 | X217: 240 | Y217: 12500 | Z217: 3087 | AA217: 3278.39 | AB217: 1440 | AC217: 36000 | AD217: CERVEJARIA CEBRASA_CD F.SANTANA_42_false | AE217: null | AF217: null | AG217: 1.92 | AH217: 115.5 | AI217: 0 | AJ217: 25 | AK217: 3.53 | AL217: 1.92 | AM217: 3 | AN217: 2.88 | AO217: FALSE | AP217: 23816.75 | AQ217: 29823.13 | AR217: 23551.34 | AS217: 23816.75 | AT217: 26244.36 | AU217: 3.53 | AV217: 0.01 | AW217: 0.22 | AX217: 0.2 | AY217: 0.31 | AZ217: 0 | BA217: 0.57 | BB217: 0.76 | BC217: 0 | BD217: 10465.07 | BE217: 21.07 | BF217: 650.73 | BG217: 592.36 | BH217: 905.28 | BI217: 7399.9 | BJ217: 1695.09 | BK217: 1821.84 | BL217: 0 | BM217: FALSE | BN217: 1440 | BO217: 12 | BP217: 3629.22 | BQ217: 1483.5 | BR217: 2967 | BS217: 30275.51 | BT217: 28508.05 | BU217: 1483.5 | BV217: 0.01 | BW217: 0.22 | BX217: 0.31 | BY217: 0.2 | BZ217: null | CA217: 0 | CB217: 0 | CC217: 0 | CD217: 12 | CE217: 0 | CF217: 0 | CG217: 0 | CH217: 0.57 | CI217: 40.22 | CJ217: 0 | CK217: 475.56 | CL217: 1923.76 | CM217: 202400 | CN217: 4 | CO217: 30275.51 | CP217: 5764.17 | CQ217: 0.76 | CR217: 0.41 | CS217: Região: NE | CT217: 0 | CU217: 0 | CV217: 60 | CW217: 99.5 | CX217: 60 | CY217: 211.89 | CZ217: 60 | DA217: 2967 | DB217: TRUE | DC217: FALSE | DD217: Cargo: MODELO EQUIPE ATIVA ATUAL | DE217: 3 | DF217: 60 | DG217: 202400 | DH217: f8ba935d-e00f-43d0-a736-ea816216b73f
A218: =F218&"x"&W218&"x"&S218 -> BR04xBR04x29035242.0 | B218: =F218&"x"&W218&"x"&S218&Q218 -> BR04xBR04x29035242.0Pallets: 42 | C218: EMPURRADA_1_9_2026 | D218: 07526557001505_CERV | E218: CAMAÇARI | F218: BR04 | I218: Geo NE | J218: 20618821000799 | K218: OPERALOG | L218: 390268 | N218: 1 | Q218: Pallets: 42 | R218: Unidade: 10275330-ATAKAREJO DISTRIBUIDOR DE ALIMENTOS(S4) | Região: 0 | S218: 29035242.0 | T218: 895563.0 | U218: FALSE | V218: Unidade: CERVEJARIA CAMAÇARI | Região: NE | W218: BR04 | X218: 421 | Y218: 12500 | Z218: 183.58 | AA218: 304.88 | AB218: 1440 | AC218: 36000 | AD218: CERVEJARIA CAMAÇARI_10275330-ATAKAREJO DISTRIBUIDOR DE ALIMENTOS(S4)_42_false | AE218: null | AF218: null | AG218: 1.92 | AH218: 0 | AI218: 31 | AJ218: 25 | AK218: 3.53 | AL218: 1.92 | AM218: 3 | AN218: 2.88 | AO218: FALSE | AP218: 1843.44 | AQ218: 2477.24 | AR218: 1821.41 | AS218: 1843.44 | AT218: 2031.34 | AU218: 3.53 | AV218: 0.02 | AW218: 0.95 | AX218: 0.2 | AY218: 0.31 | AZ218: 0 | BA218: 0.57 | BB218: 2.11 | BC218: 0 | BD218: 224.26 | BE218: 1.25 | BF218: 60.52 | BG218: 12.69 | BH218: 19.4 | BI218: 1381.55 | BJ218: 36.32 | BK218: 85.42 | BL218: 0 | BM218: FALSE | BN218: 1440 | BO218: 18 | BP218: 456.11 | BQ218: 31.98 | BR218: 63.58 | BS218: 10909.52 | BT218: 6569.04 | BU218: 31.6 | BV218: 0.02 | BW218: 0.95 | BX218: 0.31 | BY218: 0.2 | BZ218: null | CA218: 0 | CB218: 0 | CC218: 0 | CD218: 18 | CE218: 0 | CF218: 0 | CG218: 0 | CH218: 0.57 | CI218: 40.22 | CJ218: 0 | CK218: 475.56 | CL218: 1923.76 | CM218: 202400 | CN218: 4 | CO218: 10909.52 | CP218: 5764.17 | CQ218: 2.11 | CR218: 6.86 | CS218: Região: NE | CT218: 0 | CU218: 0 | CV218: 60 | CW218: 60 | CX218: 60 | CY218: 181.3 | CZ218: 60 | DA218: 63.58 | DB218: FALSE | DC218: TRUE | DD218: Cargo: MODELO EQUIPE ATIVA ATUAL | DE218: 3 | DF218: 60 | DG218: 202400 | DH218: 862ab978-17b7-4c9a-a7b3-475ac6827747
A219: =F219&"x"&W219&"x"&S219 -> BR04xBR04x29006471.0 | B219: =F219&"x"&W219&"x"&S219&Q219 -> BR04xBR04x29006471.0Pallets: 42 | C219: EMPURRADA_1_9_2026 | D219: 07526557001505_CERV | E219: CAMAÇARI | F219: BR04 | I219: Geo NE | J219: 20618821000799 | K219: OPERALOG | L219: 390268 | N219: 1 | Q219: Pallets: 42 | R219: Unidade: 10241994-MIX IDEAL ATACADO E DISTRIBUIDORA D(S4) | S219: 29006471.0 | T219: 664057.0 | U219: FALSE | V219: Unidade: CERVEJARIA CAMAÇARI | Região: NE | W219: BR04 | X219: 421 | Y219: 12500 | Z219: 170 | AA219: 291.3 | AB219: 1440 | AC219: 36000 | AD219: CERVEJARIA CAMAÇARI_10241994-MIX IDEAL ATACADO E DISTRIBUIDORA D(S4)_42_false | AE219: null | AF219: null | AG219: 1.92 | AH219: 0 | AI219: 31 | AJ219: 25 | AK219: 3.53 | AL219: 1.92 | AM219: 3 | AN219: 2.88 | AO219: FALSE | AP219: 1834.53 | AQ219: 2465.27 | AR219: 1812.61 | AS219: 1834.53 | AT219: 2021.52 | AU219: 3.53 | AV219: 0.02 | AW219: 1.16 | AX219: 0.2 | AY219: 0.31 | AZ219: 0 | BA219: 0.57 | BB219: 2.49 | BC219: 0 | BD219: 176.36 | BE219: 1.16 | BF219: 57.82 | BG219: 9.98 | BH219: 15.26 | BI219: 1444.36 | BJ219: 28.57 | BK219: 79.1 | BL219: 0 | BM219: FALSE | BN219: 1440 | BO219: 18 | BP219: 453.9 | BQ219: 25 | BR219: 50 | BS219: 9264.71 | BT219: 5406.8 | BU219: 25 | BV219: 0.02 | BW219: 1.16 | BX219: 0.31 | BY219: 0.2 | BZ219: null | CA219: 0 | CB219: 0 | CC219: 0 | CD219: 18 | CE219: 0 | CF219: 0 | CG219: 0 | CH219: 0.57 | CI219: 40.22 | CJ219: 0 | CK219: 475.56 | CL219: 1923.76 | CM219: 202400 | CN219: 4 | CO219: 9264.71 | CP219: 5764.17 | CQ219: 2.49 | CR219: 7.41 | CS219: Região: NE | CT219: 0 | CU219: 0 | CV219: 60 | CW219: 60 | CX219: 60 | CY219: 181.3 | CZ219: 60 | DA219: 50 | DB219: FALSE | DC219: TRUE | DD219: Cargo: MODELO EQUIPE ATIVA ATUAL | DE219: 3 | DF219: 60 | DG219: 202400 | DH219: 34821ad7-7fac-411a-a170-eb9259f3291d
... A235: =F235&"x"&W235&"x"&S235 -> BR04xBR04x29021249.0 | B235: =F235&"x"&W235&"x"&S235&Q235 -> BR04xBR04x29021249.0Pallets: 42 | C235: EMPURRADA_1_9_2026 | D235: 07526557001505_CERV | E235: CAMAÇARI | F235: BR04 | I235: Geo NE | J235: 20618821000799 | K235: OPERALOG | L235: 390268 | N235: 1 | Q235: Pallets: 42 | R235: Unidade: 10260986-SENDAS DISTRIBUIDORA SA(S4) | Região: 0 | S235: 29021249.0 | T235: 787329.0 | U235: FALSE | V235: Unidade: CERVEJARIA CAMAÇARI | Região: NE | W235: BR04 | X235: 421 | Y235: 12500 | Z235: 1231.84 | AA235: 1353.14 | AB235: 1440 | AC235: 36000 | AD235: CERVEJARIA CAMAÇARI_10260986-SENDAS DISTRIBUIDORA SA(S4)_42_false | AE235: null | AF235: null | AG235: 1.92 | AH235: 115.5 | AI235: 0 | AJ235: 25 | AK235: 3.53 | AL235: 1.92 | AM235: 3 | AN235: 2.88 | AO235: FALSE | AP235: 10182.88 | AQ235: 12750.92 | AR235: 10069.4 | AS235: 10182.88 | AT235: 11220.81 | AU235: 3.53 | AV235: 0.01 | AW235: 0.24 | AX235: 0.2 | AY235: 0.31 | AZ235: 0 | BA235: 0.57 | BB235: 0.81 | BC235: 0 | BD235: 3921.63 | BE235: 8.41 | BF235: 268.59 | BG235: 221.98 | BH235: 339.24 | BI235: 4101.15 | BJ235: 635.21 | BK235: 573.2 | BL235: 0 | BM235: FALSE | BN235: 1440 | BO235: 12 | BP235: 1551.68 | BQ235: 558.07 | BR235: 1111.84 | BS235: 28431.42 | BT235: 25882.73 | BU235: 553.77 | BV235: 0.01 | BW235: 0.24 | BX235: 0.31 | BY235: 0.2 | BZ235: null | CA235: 0 | CB235: 0 | CC235: 0 | CD235: 12 | CE235: 0 | CF235: 0 | CG235: 0 | CH235: 0.57 | CI235: 40.22 | CJ235: 0 | CK235: 475.56 | CL235: 1923.76 | CM235: 202400 | CN235: 4 | CO235: 28431.42 | CP235: 5764.17 | CQ235: 0.81 | CR235: 1.02 | CS235: Região: NE | CT235: 0 | CU235: 0 | CV235: 60 | CW235: 60 | CX235: 60 | CY235: 181.3 | CZ235: 60 | DA235: 1111.84 | DB235: TRUE | DC235: FALSE | DD235: Cargo: MODELO EQUIPE ATIVA ATUAL | DE235: 3 | DF235: 60 | DG235: 202400 | DH235: 6eab62cd-2d50-49a9-a070-ea91a3653d51
A236: =F236&"x"&W236&"x"&S236 -> BR04xBR04xBR2G | B236: =F236&"x"&W236&"x"&S236&Q236 -> BR04xBR04xBR2GPallets: 28 | C236: EMPURRADA_1_9_2026 | D236: 07526557001505_CERV | E236: CAMAÇARI | F236: BR04 | I236: Geo NE | J236: 20618821000799 | K236: OPERALOG | L236: 390268 | N236: 1 | Q236: Pallets: 28 | R236: Unidade: CD SALVADOR | Região: NE | S236: BR2G | T236: 71 | U236: FALSE | V236: Unidade: CERVEJARIA CAMAÇARI | Região: NE | W236: BR04 | X236: 421 | Y236: 12500 | Z236: 229.72 | AA236: 445.18 | AB236: 1440 | AC236: 36000 | AD236: CERVEJARIA CAMAÇARI_CD SALVADOR_28_false | AG236: 1.92 | AH236: 0 | AI236: 31 | AJ236: 25 | AK236: 3.53 | AL236: 1.92 | AM236: 3 | AN236: 2.88 | AO236: FALSE | AP236: 1224.27 | AQ236: 1533.02 | AR236: 1210.62 | AS236: 1224.27 | AT236: 1349.05 | AU236: 3.53 | AV236: 0.02 | AW236: 1.32 | AX236: 0.1 | AY236: 0.31 | AZ236: 0 | BA236: 0.39 | BB236: 1.51 | BC236: 0 | BD236: 236.32 | BE236: 1.57 | BF236: 88.36 | BG236: 6.69 | BH236: 20.44 | BI236: 748.66 | BJ236: 25.99 | BK236: 82.59 | BL236: 0 | BM236: FALSE | BN236: 1440 | BO236: 12 | BP236: 186.55 | BQ236: 33.5 | BR236: 67 | BS236: 9187.43 | BT236: 4740.82 | BU236: 33.5 | BV236: 0.02 | BW236: 1.32 | BX236: 0.31 | BY236: 0.1 | CA236: 0 | CB236: 0 | CC236: 0 | CD236: 12 | CE236: 0 | CF236: 0 | CG236: 0 | CH236: 0.39 | CI236: 28.22 | CJ236: 0 | CK236: 437.68 | CL236: 1907.11 | CM236: 202400 | CN236: 3 | CO236: 9187.43 | CP236: 4611.33 | CQ236: 1.51 | CR236: 5.49 | CS236: Região: NE | CT236: 0 | CU236: 0 | CV236: 60 | CW236: 164.21 | CX236: 60 | CY236: 171.25 | CZ236: 60 | DA236: 109.72 | DB236: FALSE | DC236: TRUE | DD236: Cargo: MODELO EQUIPE ATIVA ATUAL | DE236: 3 | DF236: 36.64 | DG236: 202400 | DH236: b1f8c184-a51c-4e49-b802-3de1a5a4234d
A237: =F237&"x"&W237&"x"&S237 -> BR04xBR04xBR2G | B237: =F237&"x"&W237&"x"&S237&Q237 -> BR04xBR04xBR2GPallets: 42 | C237: EMPURRADA_1_9_2026 | D237: 07526557001505_CERV | E237: CAMAÇARI | F237: BR04 | I237: Geo NE | J237: 20618821000799 | K237: OPERALOG | L237: 390268 | N237: 1 | Q237: Pallets: 42 | R237: Unidade: CD SALVADOR | Região: NE | S237: BR2G | T237: 71 | U237: FALSE | V237: Unidade: CERVEJARIA CAMAÇARI | Região: NE | W237: BR04 | X237: 421 | Y237: 12500 | Z237: 240.68 | AA237: 456.14 | AB237: 1440 | AC237: 36000 | AD237: CERVEJARIA CAMAÇARI_CD SALVADOR_42_false | AE237: null | AF237: null | AG237: 1.92 | AH237: 0 | AI237: 31 | AJ237: 25 | AK237: 3.53 | AL237: 1.92 | AM237: 3 | AN237: 2.88 | AO237: FALSE | AP237: 1360.38 | AQ237: 1828.09 | AR237: 1344.12 | AS237: 1360.38 | AT237: 1499.04 | AU237: 3.53 | AV237: 0.02 | AW237: 1.35 | AX237: 0.2 | AY237: 0.31 | AZ237: 0 | BA237: 0.57 | BB237: 2.63 | BC237: 0 | BD237: 236.32 | BE237: 1.64 | BF237: 90.54 | BG237: 13.38 | BH237: 20.44 | BI237: 819.35 | BJ237: 38.28 | BK237: 124.17 | BL237: 0 | BM237: FALSE | BN237: 1440 | BO237: 18 | BP237: 336.59 | BQ237: 33.5 | BR237: 67 | BS237: 8768.74 | BT237: 4626.82 | BU237: 33.5 | BV237: 0.02 | BW237: 1.35 | BX237: 0.31 | BY237: 0.2 | BZ237: null | CA237: 0 | CB237: 0 | CC237: 0 | CD237: 18 | CE237: 0 | CF237: 0 | CG237: 0 | CH237: 0.57 | CI237: 40.22 | CJ237: 0 | CK237: 475.56 | CL237: 1923.76 | CM237: 202400 | CN237: 4 | CO237: 8768.74 | CP237: 5764.17 | CQ237: 2.63 | CR237: 5.24 | CS237: Região: NE | CT237: 0 | CU237: 0 | CV237: 60 | CW237: 164.21 | CX237: 60 | CY237: 171.25 | CZ237: 60 | DA237: 120.68 | DB237: FALSE | DC237: TRUE | DD237: Cargo: MODELO EQUIPE ATIVA ATUAL | DE237: 3 | DF237: 33.31 | DG237: 202400 | DH237: 59af3339-d902-4bd1-914e-b63e363710b2
A238: =F238&"x"&W238&"x"&S238 -> BR04xBR12xBR2F | B238: =F238&"x"&W238&"x"&S238&Q238 -> BR04xBR12xBR2FPallets: 42 | C238: EMPURRADA_1_9_2026 | D238: 07526557001505_CERV | E238: CAMAÇARI | F238: BR04 | I238: Geo NE | J238: 20618821000799 | K238: OPERALOG | L238: 390268 | N238: 1 | Q238: Pallets: 42 | R238: Unidade: CD ILHEUS | Região: NE | S238: BR2F | T238: 70 | U238: FALSE | V238: Unidade: CERVEJARIA CEBRASA | Região: CO | W238: BR12 | X238: 240 | Y238: 12500 | Z238: 3223.24 | AA238: 3477.72 | AB238: 1440 | AC238: 36000 | AD238: CERVEJARIA CEBRASA_CD ILHEUS_42_false | AE238: null | AF238: null | AG238: 1.92 | AH238: 115.5 | AI238: 0 | AJ238: 25 | AK238: 3.53 | AL238: 1.92 | AM238: 3 | AN238: 2.88 | AO238: FALSE | AP238: 20591.94 | AQ238: 25785.05 | AR238: 20362.46 | AS238: 20591.94 | AT238: 22690.84 | AU238: 3.53 | AV238: 0.01 | AW238: 0.22 | AX238: 0.2 | AY238: 0.31 | AZ238: 0 | BA238: 0.57 | BB238: 0.76 | BC238: 0 | BD238: 10945.61 | BE238: 22 | BF238: 690.3 | BG238: 619.56 | BH238: 946.85 | BI238: 3462.97 | BJ238: 1772.92 | BK238: 1902.25 | BL238: 0 | BM238: FALSE | BN238: 1440 | BO238: 12 | BP238: 3137.82 | BQ238: 1550.24 | BR238: 3103.24 | BS238: 30327.27 | BT238: 28108.09 | BU238: 1553 | BV238: 0.01 | BW238: 0.22 | BX238: 0.31 | BY238: 0.2 | BZ238: null | CA238: 0 | CB238: 0 | CC238: 0 | CD238: 12 | CE238: 0 | CF238: 0 | CG238: 0 | CH238: 0.57 | CI238: 40.22 | CJ238: 0 | CK238: 475.56 | CL238: 1923.76 | CM238: 202400 | CN238: 4 | CO238: 30327.27 | CP238: 5764.17 | CQ238: 0.76 | CR238: 0.39 | CS238: Região: NE | CT238: 0 | CU238: 0 | CV238: 60 | CW238: 162.59 | CX238: 60 | CY238: 211.89 | CZ238: 60 | DA238: 3103.24 | DB238: TRUE | DC238: FALSE | DD238: Cargo: MODELO EQUIPE ATIVA ATUAL | DE238: 3 | DF238: 60 | DG238: 202400 | DH238: 316e2e6b-3507-4fb1-9279-57c1264ce973
A239: =F239&"x"&W239&"x"&S239 -> BR04xBR46xBR2P | B239: =F239&"x"&W239&"x"&S239&Q239 -> BR04xBR46xBR2PPallets: 42 | C239: EMPURRADA_1_9_2026 | D239: 07526557001505_CERV | E239: CAMAÇARI | F239: BR04 | I239: Geo NE | J239: 20618821000799 | K239: OPERALOG | L239: 390268 | N239: 1 | Q239: Pallets: 42 | R239: Unidade: CD F.SANTANA | Região: NE | S239: BR2P | T239: 180 | U239: FALSE | V239: Unidade: CERVEJARIA UBERLÂNDIA | Região: MG | W239: BR46 | X239: 74 | Y239: 12500 | Z239: 3209.72 | AA239: 3312.2 | AB239: 1440 | AC239: 36000 | AD239: CERVEJARIA UBERLÂNDIA_CD F.SANTANA_42_false | AE239: null | AF239: null | AG239: 1.92 | AH239: 115.5 | AI239: 0 | AJ239: 25 | AK239: 3.53 | AL239: 1.92 | AM239: 3 | AN239: 2.88 | AO239: FALSE | AP239: 21974.78 | AQ239: 27516.63 | AR239: 21729.89 | AS239: 21974.78 | AT239: 24214.64 | AU239: 3.53 | AV239: 0.01 | AW239: 0.21 | AX239: 0.2 | AY239: 0.31 | AZ239: 0 | BA239: 0.57 | BB239: 0.76 | BC239: 0 | BD239: 10897.92 | BE239: 21.91 | BF239: 657.44 | BG239: 616.86 | BH239: 942.73 | BI239: 4933.56 | BJ239: 1765.2 | BK239: 1894.27 | BL239: 0 | BM239: FALSE | BN239: 1440 | BO239: 12 | BP239: 3348.54 | BQ239: 1520.72 | BR239: 3089.72 | BS239: 30322.33 | BT239: 29384.15 | BU239: 1569 | BV239: 0.01 | BW239: 0.21 | BX239: 0.31 | BY239: 0.2 | BZ239: null | CA239: 0 | CB239: 0 | CC239: 0 | CD239: 12 | CE239: 0 | CF239: 0 | CG239: 0 | CH239: 0.57 | CI239: 40.22 | CJ239: 0 | CK239: 475.56 | CL239: 1923.76 | CM239: 202400 | CN239: 4 | CO239: 30322.33 | CP239: 5764.17 | CQ239: 0.76 | CR239: 0.39 | CS239: Região: NE | CT239: 0 | CU239: 0 | CV239: 60 | CW239: 99.5 | CX239: 60 | CY239: 122.98 | CZ239: 60 | DA239: 3089.72 | DB239: TRUE | DC239: FALSE | DD239: Cargo: MODELO EQUIPE ATIVA ATUAL | DE239: 3 | DF239: 60 | DG239: 202400 | DH239: 248cec7c-f27d-4189-bef6-3f1063262128
A240: =F240&"x"&W240&"x"&S240 -> BR04xBR04xBR5E | B240: =F240&"x"&W240&"x"&S240&Q240 -> BR04xBR04xBR5EPallets: 28 | C240: EMPURRADA_1_9_2026 | D240: 07526557001505_CERV | E240: CAMAÇARI | F240: BR04 | I240: Geo NE | J240: 20618821000799 | K240: OPERALOG | L240: 390268 | N240: 1 | Q240: Pallets: 28 | R240: Unidade: CD IMPERATRIZ | Região: NO | S240: BR5E | T240: 603 | U240: FALSE | V240: Unidade: CERVEJARIA CAMAÇARI | Região: NE | W240: BR04 | X240: 421 | Y240: 12500 | Z240: 3113.6 | AA240: 3316.19 | AB240: 1440 | AC240: 36000 | AD240: CERVEJARIA CAMAÇARI_CD IMPERATRIZ_28_false | AG240: 1.92 | AH240: 115.5 | AI240: 0 | AJ240: 25 | AK240: 3.53 | AL240: 1.92 | AM240: 3 | AN240: 2.88 | AO240: FALSE | AP240: 25090 | AQ240: 31417.48 | AR240: 24810.39 | AS240: 25090 | AT240: 27647.38 | AU240: 3.53 | AV240: 0.02 | AW240: 0.59 | AX240: 0.1 | AY240: 0.31 | AZ240: 0 | BA240: 0.39 | BB240: 1.22 | BC240: 0 | BD240: 3961.35 | BE240: 21.25 | BF240: 658.24 | BG240: 112.11 | BH240: 342.68 | BI240: 18813.41 | BJ240: 435.74 | BK240: 465.61 | BL240: 0 | BM240: FALSE | BN240: 1440 | BO240: 12 | BP240: 3823.24 | BQ240: 561.55 | BR240: 1123.1 | BS240: 11362.29 | BT240: 10668.15 | BU240: 561.55 | BV240: 0.02 | BW240: 0.59 | BX240: 0.31 | BY240: 0.1 | BZ240: null | CA240: 0 | CB240: 0 | CC240: 0 | CD240: 12 | CE240: 0 | CF240: 0 | CG240: 0 | CH240: 0.39 | CI240: 28.22 | CJ240: 0 | CK240: 437.68 | CL240: 1907.11 | CM240: 202400 | CN240: 3 | CO240: 11362.29 | CP240: 4611.33 | CQ240: 1.22 | CR240: 0.4 | CS240: Região: NE | CT240: 0 | CU240: 0 | CV240: 60 | CW240: 151.34 | CX240: 60 | CY240: 171.25 | CZ240: 60 | DA240: 2993.6 | DB240: TRUE | DC240: FALSE | DD240: Cargo: MODELO EQUIPE ATIVA ATUAL | DE240: 3 | DF240: 22.51 | DG240: 202400 | DH240: 9d422888-af97-481c-9814-b41a8599ba0a
A241: =F241&"x"&W241&"x"&S241 -> BR04xBR12xBR5D | B241: =F241&"x"&W241&"x"&S241&Q241 -> BR04xBR12xBR5DPallets: 42 | C241: EMPURRADA_1_9_2026 | D241: 07526557001505_CERV | E241: CAMAÇARI | F241: BR04 | I241: Geo NE | J241: 20618821000799 | K241: OPERALOG | L241: 390268 | N241: 1 | Q241: Pallets: 42 | R241: Unidade: CDR BAHIA | Região: NE | S241: BR5D | T241: 505 | U241: FALSE | V241: Unidade: CERVEJARIA CEBRASA | Região: CO | W241: BR12 | X241: 240 | Y241: 12500 | Z241: 3246.36 | AA241: 3521.96 | AB241: 1440 | AC241: 36000 | AD241: CERVEJARIA CEBRASA_CDR BAHIA_42_false | AE241: null | AF241: null | AG241: 1.92 | AH241: 115.5 | AI241: 0 | AJ241: 25 | AK241: 3.53 | AL241: 1.92 | AM241: 3 | AN241: 2.88 | AO241: FALSE | AP241: 26038.06 | AQ241: 32604.63 | AR241: 25747.88 | AS241: 26038.06 | AT241: 28692.07 | AU241: 3.53 | AV241: 0.01 | AW241: 0.22 | AX241: 0.2 | AY241: 0.31 | AZ241: 0 | BA241: 0.57 | BB241: 0.76 | BC241: 0 | BD241: 11027.15 | BE241: 22.16 | BF241: 699.08 | BG241: 624.18 | BH241: 953.91 | BI241: 8719.39 | BJ241: 1786.13 | BK241: 1915.89 | BL241: 0 | BM241: FALSE | BN241: 1440 | BO241: 12 | BP241: 3967.7 | BQ241: 1568.76 | BR241: 3126.36 | BS241: 30335.62 | BT241: 27961.8 | BU241: 1557.6 | BV241: 0.01 | BW241: 0.22 | BX241: 0.31 | BY241: 0.2 | BZ241: null | CA241: 0 | CB241: 0 | CC241: 0 | CD241: 12 | CE241: 0 | CF241: 0 | CG241: 0 | CH241: 0.57 | CI241: 40.22 | CJ241: 0 | CK241: 475.56 | CL241: 1923.76 | CM241: 202400 | CN241: 4 | CO241: 30335.62 | CP241: 5764.17 | CQ241: 0.76 | CR241: 0.39 | CS241: Região: NE | CT241: 0 | CU241: 0 | CV241: 60 | CW241: 183.71 | CX241: 60 | CY241: 211.89 | CZ241: 60 | DA241: 3126.36 | DB241: TRUE | DC241: FALSE | DD241: Cargo: MODELO EQUIPE ATIVA ATUAL | DE241: 3 | DF241: 60 | DG241: 202400 | DH241: 75a3ddde-62e7-410a-96a6-dfbe57f84a0c
A242: =F242&"x"&W242&"x"&S242 -> BR04xBR04xBR51 | B242: =F242&"x"&W242&"x"&S242&Q242 -> BR04xBR04xBR51Pallets: 42 | C242: EMPURRADA_1_9_2026 | D242: 07526557001505_CERV | E242: CAMAÇARI | F242: BR04 | I242: Geo NE | J242: 20618821000799 | K242: OPERALOG | L242: 390268 | N242: 1 | Q242: Pallets: 42 | R242: Unidade: R CACHOEIRO DE MACACU | Região: RJ CAPITAL | S242: BR51 | T242: 320 | U242: FALSE | V242: Unidade: CERVEJARIA CAMAÇARI | Região: NE | W242: BR04 | X242: 421 | Y242: 12500 | Z242: 8769.8 | AA242: 9010.04 | AB242: 1440 | AC242: 36000 | AD242: CERVEJARIA CAMAÇARI_R CACHOEIRO DE MACACU_42_false | AE242: null | AF242: null | AG242: 1.92 | AH242: 115.5 | AI242: 0 | AJ242: 25 | AK242: 3.53 | AL242: 1.92 | AM242: 3 | AN242: 2.88 | AO242: FALSE | AP242: 26674.76 | AQ242: 31606.1 | AR242: 26393.3 | AS242: 26674.76 | AT242: 29393.67 | AU242: 3.53 | AV242: 0.02 | AW242: 0.57 | AX242: 0.2 | AY242: 0.31 | AZ242: 0 | BA242: 0.57 | BB242: 2.04 | BC242: 0 | BD242: 11115.51 | BE242: 59.86 | BF242: 1788.41 | BG242: 629.18 | BH242: 961.55 | BI242: 8216.91 | BJ242: 1800.44 | BK242: 1821.44 | BL242: 0 | BM242: FALSE | BN242: 1440 | BO242: 7 | BP242: 2229.53 | BQ242: 1575.41 | BR242: 3151.41 | BS242: 11319.46 | BT242: 11017.65 | BU242: 1576 | BV242: 0.02 | BW242: 0.57 | BX242: 0.31 | BY242: 0.2 | BZ242: null | CA242: 0 | CB242: 0 | CC242: 0 | CD242: 7 | CE242: 0 | CF242: 0 | CG242: 0 | CH242: 0.57 | CI242: 40.22 | CJ242: 0 | CK242: 475.56 | CL242: 1923.76 | CM242: 202400 | CN242: 4 | CO242: 11319.46 | CP242: 5764.17 | CQ242: 2.04 | CR242: 0.14 | CS242: Região: NE | CT242: 0 | CU242: 0 | CV242: 60 | CW242: 188.99 | CX242: 60 | CY242: 171.25 | CZ242: 60 | DA242: 8649.8 | DB242: TRUE | DC242: FALSE | DD242: Cargo: MODELO EQUIPE ATIVA ATUAL | DE242: 3 | DF242: 21.86 | DG242: 202400 | DH242: 4d367ea2-fb0e-42e3-aca7-7048e4193932
A243: =F243&"x"&W243&"x"&S243 -> BR04xBR04xBR36 | B243: =F243&"x"&W243&"x"&S243&Q243 -> BR04xBR04xBR36Pallets: 42 | C243: EMPURRADA_1_9_2026 | D243: 07526557001505_CERV | E243: CAMAÇARI | F243: BR04 | I243: Geo NE | J243: 20618821000799 | K243: OPERALOG | L243: 390268 | N243: 1 | Q243: Pallets: 42 | R243: Unidade: CERVEJARIA EQUATORIAL | Região: NE | S243: BR36 | T243: 991 | U243: FALSE | V243: Unidade: CERVEJARIA CAMAÇARI | Região: NE | W243: BR04 | X243: 421 | Y243: 12500 | Z243: 3197.4 | AA243: 3530.51 | AB243: 1440 | AC243: 36000 | AD243: CERVEJARIA CAMAÇARI_CERVEJARIA EQUATORIAL_42_false | AE243: null | AF243: null | AG243: 1.92 | AH243: 115.5 | AI243: 0 | AJ243: 25 | AK243: 3.53 | AL243: 1.92 | AM243: 3 | AN243: 2.88 | AO243: FALSE | AP243: 21261.01 | AQ243: 26622.86 | AR243: 21024.08 | AS243: 21261.01 | AT243: 23428.11 | AU243: 3.53 | AV243: 0.01 | AW243: 0.23 | AX243: 0.2 | AY243: 0.31 | AZ243: 0 | BA243: 0.57 | BB243: 0.76 | BC243: 0 | BD243: 10854.46 | BE243: 21.82 | BF243: 700.78 | BG243: 614.4 | BH243: 938.97 | BI243: 4248.48 | BJ243: 1758.16 | BK243: 1887 | BL243: 0 | BM243: FALSE | BN243: 1440 | BO243: 12 | BP243: 3239.77 | BQ243: 1538.7 | BR243: 3077.4 | BS243: 30317.79 | BT243: 27457.25 | BU243: 1538.7 | BV243: 0.01 | BW243: 0.23 | BX243: 0.31 | BY243: 0.2 | BZ243: null | CA243: 0 | CB243: 0 | CC243: 0 | CD243: 12 | CE243: 0 | CF243: 0 | CG243: 0 | CH243: 0.57 | CI243: 40.22 | CJ243: 0 | CK243: 475.56 | CL243: 1923.76 | CM243: 202400 | CN243: 4 | CO243: 30317.79 | CP243: 5764.17 | CQ243: 0.76 | CR243: 0.39 | CS243: Região: NE | CT243: 0 | CU243: 0 | CV243: 60 | CW243: 281.86 | CX243: 60 | CY243: 171.25 | CZ243: 60 | DA243: 3077.4 | DB243: TRUE | DC243: FALSE | DD243: Cargo: MODELO EQUIPE ATIVA ATUAL | DE243: 3 | DF243: 60 | DG243: 202400 | DH243: 0b68abb6-66bc-4335-a019-aecef3d48565
A244: =F244&"x"&W244&"x"&S244 -> BR04xBR04xBR46 | B244: =F244&"x"&W244&"x"&S244&Q244 -> BR04xBR04xBR46Pallets: 42 | C244: EMPURRADA_1_9_2026 | D244: 07526557001505_CERV | E244: CAMAÇARI | F244: BR04 | I244: Geo NE | J244: 20618821000799 | K244: OPERALOG | L244: 390268 | N244: 1 | Q244: Pallets: 42 | R244: Unidade: CERVEJARIA UBERLÂNDIA | Região: MG | S244: BR46 | T244: 74 | U244: FALSE | V244: Unidade: CERVEJARIA CAMAÇARI | Região: NE | W244: BR04 | X244: 421 | Y244: 12500 | Z244: 9184.28 | AA244: 9408.99 | AB244: 1440 | AC244: 36000 | AD244: CERVEJARIA CAMAÇARI_CERVEJARIA UBERLÂNDIA_42_false | AE244: null | AF244: null | AG244: 1.92 | AH244: 115.5 | AI244: 0 | AJ244: 25 | AK244: 3.53 | AL244: 1.92 | AM244: 3 | AN244: 2.88 | AO244: FALSE | AP244: 22010.8 | AQ244: 26079.92 | AR244: 21778.56 | AS244: 22010.8 | AT244: 24254.33 | AU244: 3.53 | AV244: 0.02 | AW244: 0.56 | AX244: 0.2 | AY244: 0.31 | AZ244: 0 | BA244: 0.57 | BB244: 2.02 | BC244: 0 | BD244: 11738.72 | BE244: 62.69 | BF244: 1867.6 | BG244: 664.46 | BH244: 1015.46 | BI244: 2608.42 | BJ244: 1901.39 | BK244: 1919.82 | BL244: 0 | BM244: FALSE | BN244: 1440 | BO244: 7 | BP244: 1839.71 | BQ244: 1664.1 | BR244: 3328.1 | BS244: 11414.63 | BT244: 11142.02 | BU244: 1664 | BV244: 0.02 | BW244: 0.56 | BX244: 0.31 | BY244: 0.2 | BZ244: null | CA244: 0 | CB244: 0 | CC244: 0 | CD244: 7 | CE244: 0 | CF244: 0 | CG244: 0 | CH244: 0.57 | CI244: 40.22 | CJ244: 0 | CK244: 475.56 | CL244: 1923.76 | CM244: 202400 | CN244: 4 | CO244: 11414.63 | CP244: 5764.17 | CQ244: 2.02 | CR244: 0.14 | CS244: Região: NE | CT244: 0 | CU244: 0 | CV244: 60 | CW244: 173.46 | CX244: 60 | CY244: 171.25 | CZ244: 60 | DA244: 9064.28 | DB244: TRUE | DC244: FALSE | DD244: Cargo: MODELO EQUIPE ATIVA ATUAL | DE244: 3 | DF244: 22.03 | DG244: 202400 | DH244: e593c873-0114-4ab7-8b73-34fc56a79fea
A245: =F245&"x"&W245&"x"&S245 -> BR04xBR46xBR2G | B245: =F245&"x"&W245&"x"&S245&Q245 -> BR04xBR46xBR2GPallets: 42 | C245: EMPURRADA_1_9_2026 | D245: 07526557001505_CERV | E245: CAMAÇARI | F245: BR04 | I245: Geo NE | J245: 20618821000799 | K245: OPERALOG | L245: 390268 | N245: 1 | Q245: Pallets: 42 | R245: Unidade: CD SALVADOR | Região: NE | S245: BR2G | T245: 71 | U245: FALSE | V245: Unidade: CERVEJARIA UBERLÂNDIA | Região: MG | W245: BR46 | X245: 74 | Y245: 12500 | Z245: 3340.05 | AA245: 3507.24 | AB245: 1440 | AC245: 36000 | AD245: CERVEJARIA UBERLÂNDIA_CD SALVADOR_42_false | AE245: null | AF245: null | AG245: 1.92 | AH245: 115.5 | AI245: 0 | AJ245: 25 | AK245: 3.53 | AL245: 1.92 | AM245: 3 | AN245: 2.88 | AO245: FALSE | AP245: 22564.71 | AQ245: 28255.33 | AR245: 22313.25 | AS245: 22564.71 | AT245: 24864.69 | AU245: 3.53 | AV245: 0.01 | AW245: 0.22 | AX245: 0.2 | AY245: 0.31 | AZ245: 0 | BA245: 0.57 | BB245: 0.76 | BC245: 0 | BD245: 11357.61 | BE245: 22.8 | BF245: 696.16 | BG245: 642.88 | BH245: 982.49 | BI245: 4800.45 | BJ245: 1839.66 | BK245: 1971.19 | BL245: 0 | BM245: FALSE | BN245: 1440 | BO245: 12 | BP245: 3438.43 | BQ245: 1612.05 | BR245: 3220.05 | BS245: 30368.28 | BT245: 28920.63 | BU245: 1608 | BV245: 0.01 | BW245: 0.22 | BX245: 0.31 | BY245: 0.2 | BZ245: null | CA245: 0 | CB245: 0 | CC245: 0 | CD245: 12 | CE245: 0 | CF245: 0 | CG245: 0 | CH245: 0.57 | CI245: 40.22 | CJ245: 0 | CK245: 475.56 | CL245: 1923.76 | CM245: 202400 | CN245: 4 | CO245: 30368.28 | CP245: 5764.17 | CQ245: 0.76 | CR245: 0.38 | CS245: Região: NE | CT245: 0 | CU245: 0 | CV245: 60 | CW245: 164.21 | CX245: 60 | CY245: 122.98 | CZ245: 60 | DA245: 3220.05 | DB245: TRUE | DC245: FALSE | DD245: Cargo: MODELO EQUIPE ATIVA ATUAL | DE245: 3 | DF245: 60 | DG245: 202400 | DH245: a48fd2f1-c3e5-47f8-8524-20572c04c110
A246: =F246&"x"&W246&"x"&S246 -> BR04xBR04xBR40 | B246: =F246&"x"&W246&"x"&S246&Q246 -> BR04xBR04xBR40Pallets: 42 | C246: EMPURRADA_1_9_2026 | D246: 07526557001505_CERV | E246: CAMAÇARI | F246: BR04 | I246: Geo NE | J246: 20618821000799 | K246: OPERALOG | L246: 390268 | N246: 1 | Q246: Pallets: 42 | R246: Unidade: CERVEJARIA PIRAÍ | Região: RJ CAPITAL | S246: BR40 | T246: 781 | U246: FALSE | V246: Unidade: CERVEJARIA CAMAÇARI | Região: NE | W246: BR04 | X246: 421 | Y246: 12500 | Z246: 9083.49 | AA246: 9308.95 | AB246: 1440 | AC246: 36000 | AD246: CERVEJARIA CAMAÇARI_CERVEJARIA PIRAÍ_42_false | AE246: null | AF246: null | AG246: 1.92 | AH246: 115.5 | AI246: 0 | AJ246: 25 | AK246: 3.53 | AL246: 1.92 | AM246: 3 | AN246: 2.88 | AO246: FALSE | AP246: 26696.44 | AQ246: 31631.79 | AR246: 26414.76 | AS246: 26696.44 | AT246: 29417.56 | AU246: 3.53 | AV246: 0.02 | AW246: 0.57 | AX246: 0.2 | AY246: 0.31 | AZ246: 0 | BA246: 0.57 | BB246: 2.07 | BC246: 0 | BD246: 11344.74 | BE246: 62 | BF246: 1847.75 | BG246: 642.15 | BH246: 981.38 | BI246: 7841.54 | BJ246: 1837.57 | BK246: 1857.62 | BL246: 0 | BM246: FALSE | BN246: 1440 | BO246: 7 | BP246: 2231.34 | BQ246: 1609.4 | BR246: 3216.4 | BS246: 11153.93 | BT246: 10883.78 | BU246: 1607 | BV246: 0.02 | BW246: 0.57 | BX246: 0.31 | BY246: 0.2 | BZ246: null | CA246: 0 | CB246: 0 | CC246: 0 | CD246: 7 | CE246: 0 | CF246: 0 | CG246: 0 | CH246: 0.57 | CI246: 40.22 | CJ246: 0 | CK246: 475.56 | CL246: 1923.76 | CM246: 202400 | CN246: 4 | CO246: 11153.93 | CP246: 5764.17 | CQ246: 2.07 | CR246: 0.14 | CS246: Região: NE | CT246: 0 | CU246: 0 | CV246: 60 | CW246: 174.21 | CX246: 60 | CY246: 171.25 | CZ246: 60 | DA246: 8963.49 | DB246: TRUE | DC246: FALSE | DD246: Cargo: MODELO EQUIPE ATIVA ATUAL | DE246: 3 | DF246: 21.53 | DG246: 202400 | DH246: 9e6b9f09-4482-40eb-8879-2034227b836e
A247: =F247&"x"&W247&"x"&S247 -> BR04xBR04xBR19 | B247: =F247&"x"&W247&"x"&S247&Q247 -> BR04xBR04xBR19Pallets: 42 | C247: EMPURRADA_1_9_2026 | D247: 07526557001505_CERV | E247: CAMAÇARI | F247: BR04 | I247: Geo NE | J247: 20618821000799 | K247: OPERALOG | L247: 390268 | N247: 1 | Q247: Pallets: 42 | R247: Unidade: CERVEJARIA NOVA RIO | Região: RJ CAPITAL | S247: BR19 | T247: 185 | U247: FALSE | V247: Unidade: CERVEJARIA CAMAÇARI | Região: NE | W247: BR04 | X247: 421 | Y247: 12500 | Z247: 9057.34 | AA247: 9332.54 | AB247: 1440 | AC247: 36000 | AD247: CERVEJARIA CAMAÇARI_CERVEJARIA NOVA RIO_42_false | AE247: null | AF247: null | AG247: 1.92 | AH247: 115.5 | AI247: 0 | AJ247: 25 | AK247: 3.53 | AL247: 1.92 | AM247: 3 | AN247: 2.88 | AO247: FALSE | AP247: 21428.5 | AQ247: 25389.98 | AR247: 21202.41 | AS247: 21428.5 | AT247: 23612.68 | AU247: 3.53 | AV247: 0.02 | AW247: 0.57 | AX247: 0.2 | AY247: 0.31 | AZ247: 0 | BA247: 0.57 | BB247: 2.03 | BC247: 0 | BD247: 11500.78 | BE247: 61.82 | BF247: 1852.43 | BG247: 650.99 | BH247: 994.88 | BI247: 2396.4 | BJ247: 1862.85 | BK247: 1882.26 | BL247: 0 | BM247: FALSE | BN247: 1440 | BO247: 7 | BP247: 1791.04 | BQ247: 1629.64 | BR247: 3260.64 | BS247: 11339.99 | BT247: 11005.59 | BU247: 1631 | BV247: 0.02 | BW247: 0.57 | BX247: 0.31 | BY247: 0.2 | BZ247: null | CA247: 0 | CB247: 0 | CC247: 0 | CD247: 7 | CE247: 0 | CF247: 0 | CG247: 0 | CH247: 0.57 | CI247: 40.22 | CJ247: 0 | CK247: 475.56 | CL247: 1923.76 | CM247: 202400 | CN247: 4 | CO247: 11339.99 | CP247: 5764.17 | CQ247: 2.03 | CR247: 0.14 | CS247: Região: NE | CT247: 0 | CU247: 0 | CV247: 60 | CW247: 223.95 | CX247: 60 | CY247: 171.25 | CZ247: 60 | DA247: 8937.34 | DB247: TRUE | DC247: FALSE | DD247: Cargo: MODELO EQUIPE ATIVA ATUAL | DE247: 3 | DF247: 21.89 | DG247: 202400 | DH247: b1a43c7a-9bb1-4733-8d7b-6478a8c37d95
A248: =F248&"x"&W248&"x"&S248 -> BR04xBR04xBR12 | B248: =F248&"x"&W248&"x"&S248&Q248 -> BR04xBR04xBR12Pallets: 42 | C248: EMPURRADA_1_9_2026 | D248: 07526557001505_CERV | E248: CAMAÇARI | F248: BR04 | I248: Geo NE | J248: 20618821000799 | K248: OPERALOG | L248: 390268 | N248: 1 | Q248: Pallets: 42 | R248: Unidade: CERVEJARIA CEBRASA | Região: CO | S248: BR12 | T248: 240 | U248: FALSE | V248: Unidade: CERVEJARIA CAMAÇARI | Região: NE | W248: BR04 | X248: 421 | Y248: 12500 | Z248: 8716.99 | AA248: 9211.92 | AB248: 1440 | AC248: 36000 | AD248: CERVEJARIA CAMAÇARI_CERVEJARIA CEBRASA_42_false | AE248: null | AF248: null | AG248: 1.92 | AH248: 115.5 | AI248: 0 | AJ248: 25 | AK248: 3.53 | AL248: 1.92 | AM248: 3 | AN248: 2.88 | AO248: FALSE | AP248: 25123.36 | AQ248: 31459.25 | AR248: 24843.38 | AS248: 25123.36 | AT248: 27684.14 | AU248: 3.53 | AV248: 0.02 | AW248: 0.58 | AX248: 0.2 | AY248: 0.31 | AZ248: 0 | BA248: 0.57 | BB248: 2.02 | BC248: 0 | BD248: 11138.61 | BE248: 59.5 | BF248: 1828.49 | BG248: 630.49 | BH248: 963.55 | BI248: 6593.47 | BJ248: 1804.18 | BK248: 1825.09 | BL248: 0 | BM248: FALSE | BN248: 1440 | BO248: 12 | BP248: 3828.32 | BQ248: 1578.96 | BR248: 3157.96 | BS248: 11411.71 | BT248: 10798.59 | BU248: 1579 | BV248: 0.02 | BW248: 0.58 | BX248: 0.31 | BY248: 0.2 | BZ248: null | CA248: 0 | CB248: 0 | CC248: 0 | CD248: 12 | CE248: 0 | CF248: 0 | CG248: 0 | CH248: 0.57 | CI248: 40.22 | CJ248: 0 | CK248: 475.56 | CL248: 1923.76 | CM248: 202400 | CN248: 4 | CO248: 11411.71 | CP248: 5764.17 | CQ248: 2.02 | CR248: 0.14 | CS248: Região: NE | CT248: 0 | CU248: 0 | CV248: 60 | CW248: 443.68 | CX248: 60 | CY248: 171.25 | CZ248: 60 | DA248: 8596.99 | DB248: TRUE | DC248: FALSE | DD248: Cargo: MODELO EQUIPE ATIVA ATUAL | DE248: 3 | DF248: 22.04 | DG248: 202400 | DH248: 053baa60-b957-4724-b49b-8e179d876314
A249: =F249&"x"&W249&"x"&S249 -> BR04xBR46xBR5D | B249: =F249&"x"&W249&"x"&S249&Q249 -> BR04xBR46xBR5DPallets: 42 | C249: EMPURRADA_1_9_2026 | D249: 07526557001505_CERV | E249: CAMAÇARI | F249: BR04 | I249: Geo NE | J249: 20618821000799 | K249: OPERALOG | L249: 390268 | N249: 1 | Q249: Pallets: 42 | R249: Unidade: CDR BAHIA | Região: NE | S249: BR5D | T249: 505 | U249: FALSE | V249: Unidade: CERVEJARIA UBERLÂNDIA | Região: MG | W249: BR46 | X249: 74 | Y249: 12500 | Z249: 3448.7 | AA249: 3635.39 | AB249: 1440 | AC249: 36000 | AD249: CERVEJARIA UBERLÂNDIA_CDR BAHIA_42_false | AE249: null | AF249: null | AG249: 1.92 | AH249: 115.5 | AI249: 0 | AJ249: 25 | AK249: 3.53 | AL249: 1.92 | AM249: 3 | AN249: 2.88 | AO249: FALSE | AP249: 23295.78 | AQ249: 29170.77 | AR249: 23036.17 | AS249: 23295.78 | AT249: 25670.28 | AU249: 3.53 | AV249: 0.01 | AW249: 0.22 | AX249: 0.2 | AY249: 0.31 | AZ249: 0 | BA249: 0.57 | BB249: 0.76 | BC249: 0 | BD249: 11740.84 | BE249: 23.54 | BF249: 721.59 | BG249: 664.57 | BH249: 1015.65 | BI249: 4932.93 | BJ249: 1901.73 | BK249: 2035.31 | BL249: 0 | BM249: FALSE | BN249: 1440 | BO249: 12 | BP249: 3549.83 | BQ249: 1665.5 | BR249: 3328.7 | BS249: 30403.93 | BT249: 28842.59 | BU249: 1663.2 | BV249: 0.01 | BW249: 0.22 | BX249: 0.31 | BY249: 0.2 | BZ249: null | CA249: 0 | CB249: 0 | CC249: 0 | CD249: 12 | CE249: 0 | CF249: 0 | CG249: 0 | CH249: 0.57 | CI249: 40.22 | CJ249: 0 | CK249: 475.56 | CL249: 1923.76 | CM249: 202400 | CN249: 4 | CO249: 30403.93 | CP249: 5764.17 | CQ249: 0.76 | CR249: 0.37 | CS249: Região: NE | CT249: 0 | CU249: 0 | CV249: 60 | CW249: 183.71 | CX249: 60 | CY249: 122.98 | CZ249: 60 | DA249: 3328.7 | DB249: TRUE | DC249: FALSE | DD249: Cargo: MODELO EQUIPE ATIVA ATUAL | DE249: 3 | DF249: 60 | DG249: 202400 | DH249: 5ba02365-1391-4f72-9bac-3480f21a1d6f
A250: =F250&"x"&W250&"x"&S250 -> BR04xBR04xBR2I | B250: =F250&"x"&W250&"x"&S250&Q250 -> BR04xBR04xBR2IPallets: 42 | C250: EMPURRADA_1_9_2026 | D250: 07526557001505_CERV | E250: CAMAÇARI | F250: BR04 | I250: Geo NE | J250: 20618821000799 | K250: OPERALOG | L250: 390268 | N250: 1 | Q250: Pallets: 42 | R250: Unidade: CD CARUARU | Região: NE | S250: BR2I | T250: 598 | U250: FALSE | V250: Unidade: CERVEJARIA CAMAÇARI | Região: NE | W250: BR04 | X250: 421 | Y250: 12500 | Z250: 1508 | AA250: 1670.43 | AB250: 1440 | AC250: 36000 | AD250: CERVEJARIA CAMAÇARI_CD CARUARU_42_false | AE250: null | AF250: null | AG250: 1.92 | AH250: 115.5 | AI250: 0 | AJ250: 25 | AK250: 3.53 | AL250: 1.92 | AM250: 3 | AN250: 2.88 | AO250: FALSE | AP250: 9764.27 | AQ250: 12226.73 | AR250: 9655.45 | AS250: 9764.27 | AT250: 10759.52 | AU250: 3.53 | AV250: 0.01 | AW250: 0.24 | AX250: 0.2 | AY250: 0.31 | AZ250: 0 | BA250: 0.57 | BB250: 0.8 | BC250: 0 | BD250: 4895.69 | BE250: 10.29 | BF250: 331.57 | BG250: 277.11 | BH250: 423.5 | BI250: 2034.33 | BJ250: 792.98 | BK250: 889.97 | BL250: 0 | BM250: FALSE | BN250: 1440 | BO250: 12 | BP250: 1487.89 | BQ250: 694 | BR250: 1388 | BS250: 28993.37 | BT250: 26174.1 | BU250: 694 | BV250: 0.01 | BW250: 0.24 | BX250: 0.31 | BY250: 0.2 | BZ250: null | CA250: 0 | CB250: 0 | CC250: 0 | CD250: 12 | CE250: 0 | CF250: 0 | CG250: 0 | CH250: 0.57 | CI250: 40.22 | CJ250: 0 | CK250: 475.56 | CL250: 1923.76 | CM250: 202400 | CN250: 4 | CO250: 28993.37 | CP250: 5764.17 | CQ250: 0.8 | CR250: 0.84 | CS250: Região: NE | CT250: 0 | CU250: 0 | CV250: 60 | CW250: 111.18 | CX250: 60 | CY250: 171.25 | CZ250: 60 | DA250: 1388 | DB250: TRUE | DC250: FALSE | DD250: Cargo: MODELO EQUIPE ATIVA ATUAL | DE250: 3 | DF250: 60 | DG250: 202400 | DH250: 08429bb4-93e8-4839-94aa-b71cd96a4a6a
A251: =F251&"x"&W251&"x"&S251 -> BR04xBR04xBR6A | B251: =F251&"x"&W251&"x"&S251&Q251 -> BR04xBR04xBR6APallets: 42 | C251: EMPURRADA_1_9_2026 | D251: 07526557001505_CERV | E251: CAMAÇARI | F251: BR04 | I251: Geo NE | J251: 20618821000799 | K251: OPERALOG | L251: 390268 | N251: 1 | Q251: Pallets: 42 | R251: Unidade: CDR LOUVEIRA | Região: SP CAPITAL | S251: BR6A | T251: 424 | U251: FALSE | V251: Unidade: CERVEJARIA CAMAÇARI | Região: NE | W251: BR04 | X251: 421 | Y251: 12500 | Z251: 12266.88 | AA251: 12466.06 | AB251: 1440 | AC251: 36000 | AD251: CERVEJARIA CAMAÇARI_CDR LOUVEIRA_42_false | AE251: null | AF251: null | AG251: 1.92 | AH251: 115.5 | AI251: 0 | AJ251: 25 | AK251: 3.53 | AL251: 1.92 | AM251: 3 | AN251: 2.88 | AO251: FALSE | AP251: 30971.98 | AQ251: 36697.74 | AR251: 30645.18 | AS251: 30971.98 | AT251: 34128.9 | AU251: 3.53 | AV251: 0.02 | AW251: 0.64 | AX251: 0.2 | AY251: 0.31 | AZ251: 0 | BA251: 0.57 | BB251: 2.31 | BC251: 0 | BD251: 13710.05 | BE251: 83.73 | BF251: 2474.4 | BG251: 776.04 | BH251: 1185.99 | BI251: 7963.28 | BJ251: 2220.7 | BK251: 2231 | BL251: 0 | BM251: FALSE | BN251: 1440 | BO251: 7 | BP251: 2588.7 | BQ251: 1942 | BR251: 3887 | BS251: 9981.39 | BT251: 9821.91 | BU251: 1945 | BV251: 0.02 | BW251: 0.64 | BX251: 0.31 | BY251: 0.2 | BZ251: null | CA251: 0 | CB251: 0 | CC251: 0 | CD251: 7 | CE251: 0 | CF251: 0 | CG251: 0 | CH251: 0.57 | CI251: 40.22 | CJ251: 0 | CK251: 475.56 | CL251: 1923.76 | CM251: 202400 | CN251: 4 | CO251: 9981.39 | CP251: 5764.17 | CQ251: 2.31 | CR251: 0.1 | CS251: Região: NE | CT251: 0 | CU251: 0 | CV251: 60 | CW251: 147.93 | CX251: 60 | CY251: 171.25 | CZ251: 60 | DA251: 12146.88 | DB251: TRUE | DC251: FALSE | DD251: Cargo: MODELO EQUIPE ATIVA ATUAL | DE251: 3 | DF251: 19.2 | DG251: 202400 | DH251: 48f74efc-344a-4cf5-8c35-f7e40f268dbe
A252: =F252&"x"&W252&"x"&S252 -> BR04xBR04x29035477.0 | B252: =F252&"x"&W252&"x"&S252&Q252 -> BR04xBR04x29035477.0Pallets: 42 | C252: EMPURRADA_1_9_2026 | D252: 07526557001505_CERV | E252: CAMAÇARI | F252: BR04 | I252: Geo NE | J252: 20618821000799 | K252: OPERALOG | L252: 390268 | N252: 1 | Q252: Pallets: 42 | R252: Unidade: 10275546-DMA DISTRIBUIDORA S/A(S4) | Região: 0 | S252: 29035477.0 | T252: 897868.0 | U252: FALSE | V252: Unidade: CERVEJARIA CAMAÇARI | Região: NE | W252: BR04 | X252: 421 | Y252: 12500 | Z252: 1496.52 | AA252: 1617.82 | AB252: 1440 | AC252: 36000 | AD252: CERVEJARIA CAMAÇARI_10275546-DMA DISTRIBUIDORA S/A(S4)_42_false | AE252: null | AF252: null | AG252: 1.92 | AH252: 115.5 | AI252: 0 | AJ252: 25 | AK252: 3.53 | AL252: 1.92 | AM252: 3 | AN252: 2.88 | AO252: FALSE | AP252: 11156.67 | AQ252: 14992.5 | AR252: 11023.35 | AS252: 11156.67 | AT252: 12293.85 | AU252: 3.53 | AV252: 0.01 | AW252: 0.23 | AX252: 0.2 | AY252: 0.31 | AZ252: 0 | BA252: 0.57 | BB252: 0.8 | BC252: 0 | BD252: 4855.2 | BE252: 10.21 | BF252: 321.12 | BG252: 274.82 | BH252: 420 | BI252: 3659.21 | BJ252: 786.42 | BK252: 696.36 | BL252: 0 | BM252: FALSE | BN252: 1440 | BO252: 18 | BP252: 2760.41 | BQ252: 689.57 | BR252: 1376.52 | BS252: 28974.14 | BT252: 26801.73 | BU252: 686.95 | BV252: 0.01 | BW252: 0.23 | BX252: 0.31 | BY252: 0.2 | BZ252: null | CA252: 0 | CB252: 0 | CC252: 0 | CD252: 18 | CE252: 0 | CF252: 0 | CG252: 0 | CH252: 0.57 | CI252: 40.22 | CJ252: 0 | CK252: 475.56 | CL252: 1923.76 | CM252: 202400 | CN252: 4 | CO252: 28974.14 | CP252: 5764.17 | CQ252: 0.8 | CR252: 0.84 | CS252: Região: NE | CT252: 0 | CU252: 0 | CV252: 60 | CW252: 60 | CX252: 60 | CY252: 181.3 | CZ252: 60 | DA252: 1376.52 | DB252: TRUE | DC252: FALSE | DD252: Cargo: MODELO EQUIPE ATIVA ATUAL | DE252: 3 | DF252: 60 | DG252: 202400 | DH252: 18592547-9a0e-4613-9452-03392d50b718
... A319: =F319&"x"&W319&"x"&S319 -> BR04xBR04x29015799.0 | B319: =F319&"x"&W319&"x"&S319&Q319 -> BR04xBR04x29015799.0Pallets: 42 | C319: EMPURRADA_1_9_2026 | D319: 07526557001505_CERV | E319: CAMAÇARI | F319: BR04 | I319: Geo NE | J319: 20618821000799 | K319: OPERALOG | L319: 390268 | N319: 1 | Q319: Pallets: 42 | R319: Unidade: 10258314-ATACADAO S A(S4) | Região: 0 | S319: 29015799.0 | T319: 734144.0 | U319: FALSE | V319: Unidade: CERVEJARIA CAMAÇARI | Região: NE | W319: BR04 | X319: 421 | Y319: 12500 | Z319: 1700.44 | AA319: 1821.74 | AB319: 1440 | AC319: 36000 | AD319: CERVEJARIA CAMAÇARI_10258314-ATACADAO S A(S4)_42_false | AE319: null | AF319: null | AG319: 1.92 | AH319: 115.5 | AI319: 0 | AJ319: 25 | AK319: 3.53 | AL319: 1.92 | AM319: 3 | AN319: 2.88 | AO319: FALSE | AP319: 13798.33 | AQ319: 17278.15 | AR319: 13644.56 | AS319: 13798.33 | AT319: 15204.77 | AU319: 3.53 | AV319: 0.01 | AW319: 0.23 | AX319: 0.2 | AY319: 0.31 | AZ319: 0 | BA319: 0.57 | BB319: 0.79 | BC319: 0 | BD319: 5574.46 | BE319: 11.61 | BF319: 361.6 | BG319: 315.53 | BH319: 482.22 | BI319: 5204.97 | BJ319: 902.93 | BK319: 791.24 | BL319: 0 | BM319: FALSE | BN319: 1440 | BO319: 12 | BP319: 2102.6 | BQ319: 792.91 | BR319: 1580.44 | BS319: 29277.05 | BT319: 27327.64 | BU319: 787.53 | BV319: 0.01 | BW319: 0.23 | BX319: 0.31 | BY319: 0.2 | BZ319: null | CA319: 0 | CB319: 0 | CC319: 0 | CD319: 12 | CE319: 0 | CF319: 0 | CG319: 0 | CH319: 0.57 | CI319: 40.22 | CJ319: 0 | CK319: 475.56 | CL319: 1923.76 | CM319: 202400 | CN319: 4 | CO319: 29277.05 | CP319: 5764.17 | CQ319: 0.79 | CR319: 0.74 | CS319: Região: NE | CT319: 0 | CU319: 0 | CV319: 60 | CW319: 60 | CX319: 60 | CY319: 181.3 | CZ319: 60 | DA319: 1580.44 | DB319: TRUE | DC319: FALSE | DD319: Cargo: MODELO EQUIPE ATIVA ATUAL | DE319: 3 | DF319: 60 | DG319: 202400 | DH319: 3e69f274-990b-428c-ba71-c26bc6935cfb
A320: =F320&"x"&W320&"x"&S320 -> BR04xBR04xBR2E | B320: =F320&"x"&W320&"x"&S320&Q320 -> BR04xBR04xBR2EPallets: 28 | C320: EMPURRADA_1_9_2026 | D320: 07526557001505_CERV | E320: CAMAÇARI | F320: BR04 | I320: Geo NE | J320: 20618821000799 | K320: OPERALOG | L320: 390268 | N320: 1 | Q320: Pallets: 28 | R320: Unidade: CD OLINDA | Região: NE | S320: BR2E | T320: 546 | U320: FALSE | V320: Unidade: CERVEJARIA CAMAÇARI | Região: NE | W320: BR04 | X320: 421 | Y320: 12500 | Z320: 3962.55 | AA320: 4112.27 | AB320: 1440 | AC320: 36000 | AD320: CERVEJARIA CAMAÇARI_CD OLINDA_28_false | AG320: 1.92 | AH320: 115.5 | AI320: 0 | AJ320: 25 | AK320: 3.53 | AL320: 1.92 | AM320: 3 | AN320: 2.88 | AO320: FALSE | AP320: 9409.21 | AQ320: 11782.14 | AR320: 9304.36 | AS320: 9409.21 | AT320: 10368.28 | AU320: 3.53 | AV320: 0.02 | AW320: 0.52 | AX320: 0.1 | AY320: 0.31 | AZ320: 0 | BA320: 0.39 | BB320: 1.11 | BC320: 0 | BD320: 5531.99 | BE320: 27.05 | BF320: 816.25 | BG320: 156.57 | BH320: 478.55 | BI320: 695.03 | BJ320: 608.51 | BK320: 990.42 | BL320: 0 | BM320: FALSE | BN320: 1440 | BO320: 12 | BP320: 1433.79 | BQ320: 784.2 | BR320: 1568.4 | BS320: 12467.89 | BT320: 12013.95 | BU320: 784.2 | BV320: 0.02 | BW320: 0.52 | BX320: 0.31 | BY320: 0.1 | CA320: 0 | CB320: 0 | CC320: 0 | CD320: 12 | CE320: 0 | CF320: 0 | CG320: 0 | CH320: 0.39 | CI320: 28.22 | CJ320: 0 | CK320: 437.68 | CL320: 1907.11 | CM320: 202400 | CN320: 3 | CO320: 12467.89 | CP320: 4611.33 | CQ320: 1.11 | CR320: 0.32 | CS320: Região: NE | CT320: 0 | CU320: 0 | CV320: 60 | CW320: 98.47 | CX320: 60 | CY320: 171.25 | CZ320: 60 | DA320: 3842.55 | DB320: TRUE | DC320: FALSE | DD320: Cargo: MODELO EQUIPE ATIVA ATUAL | DE320: 3 | DF320: 24.49 | DG320: 202400 | DH320: 7edd555a-36f2-4806-a216-77886db8703e
A321: =F321&"x"&W321&"x"&S321 -> BR04xBR04x29022977.0 | B321: =F321&"x"&W321&"x"&S321&Q321 -> BR04xBR04x29022977.0Pallets: 42 | C321: EMPURRADA_1_9_2026 | D321: 07526557001505_CERV | E321: CAMAÇARI | F321: BR04 | I321: Geo NE | J321: 20618821000799 | K321: OPERALOG | L321: 390268 | N321: 1 | Q321: Pallets: 42 | R321: Unidade: 10262178-DISTCARNES DISTRIBUIDORA CARNES(S4) | Região: 0 | S321: 29022977.0 | T321: 814237.0 | U321: FALSE | V321: Unidade: CERVEJARIA CAMAÇARI | Região: NE | W321: BR04 | X321: 421 | Y321: 12500 | Z321: 1679.85 | AA321: 1801.15 | AB321: 1440 | AC321: 36000 | AD321: CERVEJARIA CAMAÇARI_10262178-DISTCARNES DISTRIBUIDORA CARNES(S4)_42_false | AE321: null | AF321: null | AG321: 1.92 | AH321: 115.5 | AI321: 0 | AJ321: 25 | AK321: 3.53 | AL321: 1.92 | AM321: 3 | AN321: 2.88 | AO321: FALSE | AP321: 14030.6 | AQ321: 17568.99 | AR321: 13874.24 | AS321: 14030.6 | AT321: 15460.71 | AU321: 3.53 | AV321: 0.01 | AW321: 0.23 | AX321: 0.2 | AY321: 0.31 | AZ321: 0 | BA321: 0.57 | BB321: 0.79 | BC321: 0 | BD321: 5501.83 | BE321: 11.47 | BF321: 357.51 | BG321: 311.42 | BH321: 475.94 | BI321: 5543.24 | BJ321: 891.16 | BK321: 781.66 | BL321: 0 | BM321: FALSE | BN321: 1440 | BO321: 12 | BP321: 2138 | BQ321: 782.03 | BR321: 1559.85 | BS321: 29249.8 | BT321: 27279.95 | BU321: 777.82 | BV321: 0.01 | BW321: 0.23 | BX321: 0.31 | BY321: 0.2 | BZ321: null | CA321: 0 | CB321: 0 | CC321: 0 | CD321: 12 | CE321: 0 | CF321: 0 | CG321: 0 | CH321: 0.57 | CI321: 40.22 | CJ321: 0 | CK321: 475.56 | CL321: 1923.76 | CM321: 202400 | CN321: 4 | CO321: 29249.8 | CP321: 5764.17 | CQ321: 0.79 | CR321: 0.75 | CS321: Região: NE | CT321: 0 | CU321: 0 | CV321: 60 | CW321: 60 | CX321: 60 | CY321: 181.3 | CZ321: 60 | DA321: 1559.85 | DB321: TRUE | DC321: FALSE | DD321: Cargo: MODELO EQUIPE ATIVA ATUAL | DE321: 3 | DF321: 60 | DG321: 202400 | DH321: 58656c76-68a9-4e3b-9e38-1b7bb9c42089
A322: =F322&"x"&W322&"x"&S322 -> BR04xBR04x29021312.0 | B322: =F322&"x"&W322&"x"&S322&Q322 -> BR04xBR04x29021312.0Pallets: 42 | C322: EMPURRADA_1_9_2026 | D322: 07526557001505_CERV | E322: CAMAÇARI | F322: BR04 | I322: Geo NE | J322: 20618821000799 | K322: OPERALOG | L322: 390268 | N322: 1 | Q322: Pallets: 42 | R322: Unidade: 10261032-SENDAS DISTRIBUIDORA SA(S4) | Região: 0 | S322: 29021312.0 | T322: 788732.0 | U322: FALSE | V322: Unidade: CERVEJARIA CAMAÇARI | Região: NE | W322: BR04 | X322: 421 | Y322: 12500 | Z322: 1682.25 | AA322: 1803.55 | AB322: 1440 | AC322: 36000 | AD322: CERVEJARIA CAMAÇARI_10261032-SENDAS DISTRIBUIDORA SA(S4)_42_false | AE322: null | AF322: null | AG322: 1.92 | AH322: 115.5 | AI322: 0 | AJ322: 25 | AK322: 3.53 | AL322: 1.92 | AM322: 3 | AN322: 2.88 | AO322: FALSE | AP322: 13666.91 | AQ322: 17113.58 | AR322: 13514.6 | AS322: 13666.91 | AT322: 15059.95 | AU322: 3.53 | AV322: 0.01 | AW322: 0.23 | AX322: 0.2 | AY322: 0.31 | AZ322: 0 | BA322: 0.57 | BB322: 0.79 | BC322: 0 | BD322: 5510.3 | BE322: 11.48 | BF322: 357.99 | BG322: 311.9 | BH322: 476.67 | BI322: 5170.95 | BJ322: 892.53 | BK322: 782.78 | BL322: 0 | BM322: FALSE | BN322: 1440 | BO322: 12 | BP322: 2082.58 | BQ322: 784.43 | BR322: 1562.25 | BS322: 29253.01 | BT322: 27285.56 | BU322: 777.82 | BV322: 0.01 | BW322: 0.23 | BX322: 0.31 | BY322: 0.2 | BZ322: null | CA322: 0 | CB322: 0 | CC322: 0 | CD322: 12 | CE322: 0 | CF322: 0 | CG322: 0 | CH322: 0.57 | CI322: 40.22 | CJ322: 0 | CK322: 475.56 | CL322: 1923.76 | CM322: 202400 | CN322: 4 | CO322: 29253.01 | CP322: 5764.17 | CQ322: 0.79 | CR322: 0.75 | CS322: Região: NE | CT322: 0 | CU322: 0 | CV322: 60 | CW322: 60 | CX322: 60 | CY322: 181.3 | CZ322: 60 | DA322: 1562.25 | DB322: TRUE | DC322: FALSE | DD322: Cargo: MODELO EQUIPE ATIVA ATUAL | DE322: 3 | DF322: 60 | DG322: 202400 | DH322: 773a1318-1517-4104-b767-5f9ce3c6ac51
A323: =F323&"x"&W323&"x"&S323 -> BR04xBR04x29006105.0 | B323: =F323&"x"&W323&"x"&S323&Q323 -> BR04xBR04x29006105.0Pallets: 42 | C323: EMPURRADA_1_9_2026 | D323: 07526557001505_CERV | E323: CAMAÇARI | F323: BR04 | I323: Geo NE | J323: 20618821000799 | K323: OPERALOG | L323: 390268 | N323: 1 | Q323: Pallets: 42 | R323: Unidade: 10240548-WMS SUPERMERCADOS DO BRASIL LTDA(S4) | Região: 0.0 | S323: 29006105.0 | T323: 654264.0 | U323: FALSE | V323: Unidade: CERVEJARIA CAMAÇARI | Região: NE | W323: BR04 | X323: 421 | Y323: 12500 | Z323: 1692.92 | AA323: 1814.22 | AB323: 1440 | AC323: 36000 | AD323: CERVEJARIA CAMAÇARI_10240548-WMS SUPERMERCADOS DO BRASIL LTDA(S4)_42_false | AE323: null | AF323: null | AG323: 1.92 | AH323: 115.5 | AI323: 0 | AJ323: 25 | AK323: 3.53 | AL323: 1.92 | AM323: 3 | AN323: 2.88 | AO323: FALSE | AP323: 13733.59 | AQ323: 17197.09 | AR323: 13580.54 | AS323: 13733.59 | AT323: 15133.44 | AU323: 3.53 | AV323: 0.01 | AW323: 0.23 | AX323: 0.2 | AY323: 0.31 | AZ323: 0 | BA323: 0.57 | BB323: 0.79 | BC323: 0 | BD323: 5547.93 | BE323: 11.55 | BF323: 360.11 | BG323: 314.03 | BH323: 479.93 | BI323: 5180.62 | BJ323: 898.63 | BK323: 787.74 | BL323: 0 | BM323: FALSE | BN323: 1440 | BO323: 12 | BP323: 2092.74 | BQ323: 788.73 | BR323: 1572.92 | BS323: 29267.17 | BT323: 27310.35 | BU323: 784.19 | BV323: 0.01 | BW323: 0.23 | BX323: 0.31 | BY323: 0.2 | BZ323: null | CA323: 0 | CB323: 0 | CC323: 0 | CD323: 12 | CE323: 0 | CF323: 0 | CG323: 0 | CH323: 0.57 | CI323: 40.22 | CJ323: 0 | CK323: 475.56 | CL323: 1923.76 | CM323: 202400 | CN323: 4 | CO323: 29267.17 | CP323: 5764.17 | CQ323: 0.79 | CR323: 0.74 | CS323: Região: NE | CT323: 0 | CU323: 0 | CV323: 60 | CW323: 60 | CX323: 60 | CY323: 181.3 | CZ323: 60 | DA323: 1572.92 | DB323: TRUE | DC323: FALSE | DD323: Cargo: MODELO EQUIPE ATIVA ATUAL | DE323: 3 | DF323: 60 | DG323: 202400 | DH323: b0a5fa4a-89ab-436f-b6f5-5660df187f6a
A324: =F324&"x"&W324&"x"&S324 -> BR04xBR04x29031715.0 | B324: =F324&"x"&W324&"x"&S324&Q324 -> BR04xBR04x29031715.0Pallets: 42 | C324: EMPURRADA_1_9_2026 | D324: 07526557001505_CERV | E324: CAMAÇARI | F324: BR04 | I324: Geo NE | J324: 20618821000799 | K324: OPERALOG | L324: 390268 | N324: 1 | Q324: Pallets: 42 | R324: Unidade: 10265367-ATACADAO S A(S4) | Região: 0 | S324: 29031715.0 | T324: 858501.0 | U324: FALSE | V324: Unidade: CERVEJARIA CAMAÇARI | Região: NE | W324: BR04 | X324: 421 | Y324: 12500 | Z324: 1705.77 | AA324: 1827.07 | AB324: 1440 | AC324: 36000 | AD324: CERVEJARIA CAMAÇARI_10265367-ATACADAO S A(S4)_42_false | AE324: null | AF324: null | AG324: 1.92 | AH324: 115.5 | AI324: 0 | AJ324: 25 | AK324: 3.53 | AL324: 1.92 | AM324: 3 | AN324: 2.88 | AO324: FALSE | AP324: 13838.46 | AQ324: 17328.39 | AR324: 13684.24 | AS324: 13838.46 | AT324: 15248.99 | AU324: 3.53 | AV324: 0.01 | AW324: 0.23 | AX324: 0.2 | AY324: 0.31 | AZ324: 0 | BA324: 0.57 | BB324: 0.79 | BC324: 0 | BD324: 5593.26 | BE324: 11.64 | BF324: 362.66 | BG324: 316.6 | BH324: 483.85 | BI324: 5216.54 | BJ324: 905.97 | BK324: 793.72 | BL324: 0 | BM324: FALSE | BN324: 1440 | BO324: 12 | BP324: 2108.72 | BQ324: 795.5 | BR324: 1585.77 | BS324: 29283.99 | BT324: 27339.81 | BU324: 790.27 | BV324: 0.01 | BW324: 0.23 | BX324: 0.31 | BY324: 0.2 | BZ324: null | CA324: 0 | CB324: 0 | CC324: 0 | CD324: 12 | CE324: 0 | CF324: 0 | CG324: 0 | CH324: 0.57 | CI324: 40.22 | CJ324: 0 | CK324: 475.56 | CL324: 1923.76 | CM324: 202400 | CN324: 4 | CO324: 29283.99 | CP324: 5764.17 | CQ324: 0.79 | CR324: 0.74 | CS324: Região: NE | CT324: 0 | CU324: 0 | CV324: 60 | CW324: 60 | CX324: 60 | CY324: 181.3 | CZ324: 60 | DA324: 1585.77 | DB324: TRUE | DC324: FALSE | DD324: Cargo: MODELO EQUIPE ATIVA ATUAL | DE324: 3 | DF324: 60 | DG324: 202400 | DH324: 2912c58a-968b-4f91-91ae-20972fa7039c
A325: =F325&"x"&W325&"x"&S325 -> BR04xBR04x29021241.0 | B325: =F325&"x"&W325&"x"&S325&Q325 -> BR04xBR04x29021241.0Pallets: 42 | C325: EMPURRADA_1_9_2026 | D325: 07526557001505_CERV | E325: CAMAÇARI | F325: BR04 | I325: Geo NE | J325: 20618821000799 | K325: OPERALOG | L325: 390268 | N325: 1 | Q325: Pallets: 42 | R325: Unidade: 10260978-SENDAS DISTRIBUIDORA SA(S4) | Região: 0 | S325: 29021241.0 | T325: 787965.0 | U325: FALSE | V325: Unidade: CERVEJARIA CAMAÇARI | Região: NE | W325: BR04 | X325: 421 | Y325: 12500 | Z325: 828.55 | AA325: 949.85 | AB325: 1440 | AC325: 36000 | AD325: CERVEJARIA CAMAÇARI_10260978-SENDAS DISTRIBUIDORA SA(S4)_42_false | AE325: null | AF325: null | AG325: 1.92 | AH325: 115.5 | AI325: 0 | AJ325: 25 | AK325: 3.53 | AL325: 1.92 | AM325: 3 | AN325: 2.88 | AO325: FALSE | AP325: 6389.71 | AQ325: 8586.59 | AR325: 6313.35 | AS325: 6389.71 | AT325: 7041 | AU325: 3.53 | AV325: 0.01 | AW325: 0.27 | AX325: 0.2 | AY325: 0.31 | AZ325: 0 | BA325: 0.57 | BB325: 0.86 | BC325: 0 | BD325: 2499.17 | BE325: 5.66 | BF325: 188.54 | BG325: 141.46 | BH325: 216.19 | BI325: 2472 | BJ325: 404.8 | BK325: 385.54 | BL325: 0 | BM325: FALSE | BN325: 1440 | BO325: 18 | BP325: 1580.96 | BQ325: 355.54 | BR325: 708.55 | BS325: 26937.81 | BT325: 23497.74 | BU325: 353.01 | BV325: 0.01 | BW325: 0.27 | BX325: 0.31 | BY325: 0.2 | BZ325: null | CA325: 0 | CB325: 0 | CC325: 0 | CD325: 18 | CE325: 0 | CF325: 0 | CG325: 0 | CH325: 0.57 | CI325: 40.22 | CJ325: 0 | CK325: 475.56 | CL325: 1923.76 | CM325: 202400 | CN325: 4 | CO325: 26937.81 | CP325: 5764.17 | CQ325: 0.86 | CR325: 1.52 | CS325: Região: NE | CT325: 0 | CU325: 0 | CV325: 60 | CW325: 60 | CX325: 60 | CY325: 181.3 | CZ325: 60 | DA325: 708.55 | DB325: TRUE | DC325: FALSE | DD325: Cargo: MODELO EQUIPE ATIVA ATUAL | DE325: 3 | DF325: 60 | DG325: 202400 | DH325: 469b9d94-bd7a-42d6-af9e-455ea6342b2c
A326: =F326&"x"&W326&"x"&S326 -> BR04xBR04xBR2Q | B326: =F326&"x"&W326&"x"&S326&Q326 -> BR04xBR04xBR2QPallets: 28 | C326: EMPURRADA_1_9_2026 | D326: 07526557001505_CERV | E326: CAMAÇARI | F326: BR04 | I326: Geo NE | J326: 20618821000799 | K326: OPERALOG | L326: 390268 | N326: 1 | Q326: Pallets: 28 | R326: Unidade: CD ARACAJU | Região: NE | S326: BR2Q | T326: 581 | U326: FALSE | V326: Unidade: CERVEJARIA CAMAÇARI | Região: NE | W326: BR04 | X326: 421 | Y326: 12500 | Z326: 1118.12 | AA326: 1288.08 | AB326: 1440 | AC326: 36000 | AD326: CERVEJARIA CAMAÇARI_CD ARACAJU_28_false | AG326: 1.92 | AH326: 115.5 | AI326: 0 | AJ326: 25 | AK326: 3.53 | AL326: 1.92 | AM326: 3 | AN326: 2.88 | AO326: FALSE | AP326: 3770.56 | AQ326: 4721.46 | AR326: 3728.54 | AS326: 3770.56 | AT326: 4154.88 | AU326: 3.53 | AV326: 0.01 | AW326: 0.44 | AX326: 0.1 | AY326: 0.31 | AZ326: 0 | BA326: 0.39 | BB326: 0.84 | BC326: 0 | BD326: 2061.27 | BE326: 7.63 | BF326: 255.67 | BG326: 58.34 | BH326: 178.31 | BI326: 596.6 | BJ326: 226.74 | BK326: 343.98 | BL326: 0 | BM326: FALSE | BN326: 1440 | BO326: 12 | BP326: 574.56 | BQ326: 292.2 | BR326: 584.4 | BS326: 16463.87 | BT326: 14291.49 | BU326: 292.2 | BV326: 0.01 | BW326: 0.44 | BX326: 0.31 | BY326: 0.1 | CA326: 0 | CB326: 0 | CC326: 0 | CD326: 12 | CE326: 0 | CF326: 0 | CG326: 0 | CH326: 0.39 | CI326: 28.22 | CJ326: 0 | CK326: 437.68 | CL326: 1907.11 | CM326: 202400 | CN326: 3 | CO326: 16463.87 | CP326: 4611.33 | CQ326: 0.84 | CR326: 1.13 | CS326: Região: NE | CT326: 0 | CU326: 0 | CV326: 60 | CW326: 118.71 | CX326: 60 | CY326: 171.25 | CZ326: 60 | DA326: 998.12 | DB326: TRUE | DC326: FALSE | DD326: Cargo: MODELO EQUIPE ATIVA ATUAL | DE326: 3 | DF326: 35.13 | DG326: 202400 | DH326: 4e9ec105-b423-4ac4-a811-5f90c8b2b6fb
A327: =F327&"x"&W327&"x"&S327 -> BR04xBR04x29021310.0 | B327: =F327&"x"&W327&"x"&S327&Q327 -> BR04xBR04x29021310.0Pallets: 42 | C327: EMPURRADA_1_9_2026 | D327: 07526557001505_CERV | E327: CAMAÇARI | F327: BR04 | I327: Geo NE | J327: 20618821000799 | K327: OPERALOG | L327: 390268 | N327: 1 | Q327: Pallets: 42 | R327: Unidade: 10261030-SENDAS DISTRIBUIDORA SA(S4) | Região: 0 | S327: 29021310.0 | T327: 788716.0 | U327: FALSE | V327: Unidade: CERVEJARIA CAMAÇARI | Região: NE | W327: BR04 | X327: 421 | Y327: 12500 | Z327: 1712.47 | AA327: 1833.77 | AB327: 1440 | AC327: 36000 | AD327: CERVEJARIA CAMAÇARI_10261030-SENDAS DISTRIBUIDORA SA(S4)_42_false | AE327: null | AF327: null | AG327: 1.92 | AH327: 115.5 | AI327: 0 | AJ327: 25 | AK327: 3.53 | AL327: 1.92 | AM327: 3 | AN327: 2.88 | AO327: FALSE | AP327: 13888.2 | AQ327: 17390.68 | AR327: 13733.43 | AS327: 13888.2 | AT327: 15303.8 | AU327: 3.53 | AV327: 0.01 | AW327: 0.23 | AX327: 0.2 | AY327: 0.31 | AZ327: 0 | BA327: 0.57 | BB327: 0.79 | BC327: 0 | BD327: 5616.89 | BE327: 11.69 | BF327: 363.99 | BG327: 317.94 | BH327: 485.89 | BI327: 5230.4 | BJ327: 909.8 | BK327: 796.84 | BL327: 0 | BM327: FALSE | BN327: 1440 | BO327: 12 | BP327: 2116.3 | BQ327: 798.71 | BR327: 1592.47 | BS327: 29292.66 | BT327: 27355.01 | BU327: 793.76 | BV327: 0.01 | BW327: 0.23 | BX327: 0.31 | BY327: 0.2 | BZ327: null | CA327: 0 | CB327: 0 | CC327: 0 | CD327: 12 | CE327: 0 | CF327: 0 | CG327: 0 | CH327: 0.57 | CI327: 40.22 | CJ327: 0 | CK327: 475.56 | CL327: 1923.76 | CM327: 202400 | CN327: 4 | CO327: 29292.66 | CP327: 5764.17 | CQ327: 0.79 | CR327: 0.74 | CS327: Região: NE | CT327: 0 | CU327: 0 | CV327: 60 | CW327: 60 | CX327: 60 | CY327: 181.3 | CZ327: 60 | DA327: 1592.47 | DB327: TRUE | DC327: FALSE | DD327: Cargo: MODELO EQUIPE ATIVA ATUAL | DE327: 3 | DF327: 60 | DG327: 202400 | DH327: 03887acf-aac7-442a-843f-e1a754398393
A328: =F328&"x"&W328&"x"&S328 -> BR04xBR04x29021311.0 | B328: =F328&"x"&W328&"x"&S328&Q328 -> BR04xBR04x29021311.0Pallets: 42 | C328: EMPURRADA_1_9_2026 | D328: 07526557001505_CERV | E328: CAMAÇARI | F328: BR04 | I328: Geo NE | J328: 20618821000799 | K328: OPERALOG | L328: 390268 | N328: 1 | Q328: Pallets: 42 | R328: Unidade: 10261031-SENDAS DISTRIBUIDORA SA(S4) | Região: 0 | S328: 29021311.0 | T328: 788724.0 | U328: FALSE | V328: Unidade: CERVEJARIA CAMAÇARI | Região: NE | W328: BR04 | X328: 421 | Y328: 12500 | Z328: 1712.47 | AA328: 1833.77 | AB328: 1440 | AC328: 36000 | AD328: CERVEJARIA CAMAÇARI_10261031-SENDAS DISTRIBUIDORA SA(S4)_42_false | AE328: null | AF328: null | AG328: 1.92 | AH328: 115.5 | AI328: 0 | AJ328: 25 | AK328: 3.53 | AL328: 1.92 | AM328: 3 | AN328: 2.88 | AO328: FALSE | AP328: 13888.2 | AQ328: 17390.68 | AR328: 13733.43 | AS328: 13888.2 | AT328: 15303.8 | AU328: 3.53 | AV328: 0.01 | AW328: 0.23 | AX328: 0.2 | AY328: 0.31 | AZ328: 0 | BA328: 0.57 | BB328: 0.79 | BC328: 0 | BD328: 5616.89 | BE328: 11.69 | BF328: 363.99 | BG328: 317.94 | BH328: 485.89 | BI328: 5230.4 | BJ328: 909.8 | BK328: 796.84 | BL328: 0 | BM328: FALSE | BN328: 1440 | BO328: 12 | BP328: 2116.3 | BQ328: 798.71 | BR328: 1592.47 | BS328: 29292.66 | BT328: 27355.01 | BU328: 793.76 | BV328: 0.01 | BW328: 0.23 | BX328: 0.31 | BY328: 0.2 | BZ328: null | CA328: 0 | CB328: 0 | CC328: 0 | CD328: 12 | CE328: 0 | CF328: 0 | CG328: 0 | CH328: 0.57 | CI328: 40.22 | CJ328: 0 | CK328: 475.56 | CL328: 1923.76 | CM328: 202400 | CN328: 4 | CO328: 29292.66 | CP328: 5764.17 | CQ328: 0.79 | CR328: 0.74 | CS328: Região: NE | CT328: 0 | CU328: 0 | CV328: 60 | CW328: 60 | CX328: 60 | CY328: 181.3 | CZ328: 60 | DA328: 1592.47 | DB328: TRUE | DC328: FALSE | DD328: Cargo: MODELO EQUIPE ATIVA ATUAL | DE328: 3 | DF328: 60 | DG328: 202400 | DH328: 57aa5ae0-b158-4b97-a59f-f43a254e5026
A329: =F329&"x"&W329&"x"&S329 -> BR04xBR04x29009026.0 | B329: =F329&"x"&W329&"x"&S329&Q329 -> BR04xBR04x29009026.0Pallets: 42 | C329: EMPURRADA_1_9_2026 | D329: 07526557001505_CERV | E329: CAMAÇARI | F329: BR04 | I329: Geo NE | J329: 20618821000799 | K329: OPERALOG | L329: 390268 | N329: 1 | Q329: Pallets: 42 | R329: Unidade: 10244863-SUPERMERCADOS CASAGRANDE LTDA(S4) | Região: 0 | S329: 29009026.0 | T329: 601179.0 | U329: FALSE | V329: Unidade: CERVEJARIA CAMAÇARI | Região: NE | W329: BR04 | X329: 421 | Y329: 12500 | Z329: 1704.17 | AA329: 1825.47 | AB329: 1440 | AC329: 36000 | AD329: CERVEJARIA CAMAÇARI_10244863-SUPERMERCADOS CASAGRANDE LTDA(S4)_42_false | AE329: null | AF329: null | AG329: 1.92 | AH329: 115.5 | AI329: 0 | AJ329: 25 | AK329: 3.53 | AL329: 1.92 | AM329: 3 | AN329: 2.88 | AO329: FALSE | AP329: 12533.84 | AQ329: 16843.17 | AR329: 12384.07 | AS329: 12533.84 | AT329: 13811.4 | AU329: 3.53 | AV329: 0.01 | AW329: 0.23 | AX329: 0.2 | AY329: 0.31 | AZ329: 0 | BA329: 0.57 | BB329: 0.79 | BC329: 0 | BD329: 5587.61 | BE329: 11.63 | BF329: 362.34 | BG329: 316.28 | BH329: 483.36 | BI329: 3924.81 | BJ329: 905.06 | BK329: 792.98 | BL329: 0 | BM329: FALSE | BN329: 1440 | BO329: 18 | BP329: 3101.16 | BQ329: 793.37 | BR329: 1584.17 | BS329: 29281.91 | BT329: 27336.17 | BU329: 790.8 | BV329: 0.01 | BW329: 0.23 | BX329: 0.31 | BY329: 0.2 | BZ329: null | CA329: 0 | CB329: 0 | CC329: 0 | CD329: 18 | CE329: 0 | CF329: 0 | CG329: 0 | CH329: 0.57 | CI329: 40.22 | CJ329: 0 | CK329: 475.56 | CL329: 1923.76 | CM329: 202400 | CN329: 4 | CO329: 29281.91 | CP329: 5764.17 | CQ329: 0.79 | CR329: 0.74 | CS329: Região: NE | CT329: 0 | CU329: 0 | CV329: 60 | CW329: 60 | CX329: 60 | CY329: 181.3 | CZ329: 60 | DA329: 1584.17 | DB329: TRUE | DC329: FALSE | DD329: Cargo: MODELO EQUIPE ATIVA ATUAL | DE329: 3 | DF329: 60 | DG329: 202400 | DH329: 6d7d5df3-5496-40fa-8f3b-5c731e7ebf4c
A330: =F330&"x"&W330&"x"&S330 -> BR04xBR04x29029496.0 | B330: =F330&"x"&W330&"x"&S330&Q330 -> BR04xBR04x29029496.0Pallets: 42 | C330: EMPURRADA_1_9_2026 | D330: 07526557001505_CERV | E330: CAMAÇARI | F330: BR04 | I330: Geo NE | J330: 20618821000799 | K330: OPERALOG | L330: 390268 | N330: 1 | Q330: Pallets: 42 | R330: Unidade: 10263488-ATACADAO S A(S4) | Região: 0 | S330: 29029496.0 | T330: 833282.0 | U330: FALSE | V330: Unidade: CERVEJARIA CAMAÇARI | Região: NE | W330: BR04 | X330: 421 | Y330: 12500 | Z330: 1705.47 | AA330: 1826.77 | AB330: 1440 | AC330: 36000 | AD330: CERVEJARIA CAMAÇARI_10263488-ATACADAO S A(S4)_42_false | AE330: null | AF330: null | AG330: 1.92 | AH330: 115.5 | AI330: 0 | AJ330: 25 | AK330: 3.53 | AL330: 1.92 | AM330: 3 | AN330: 2.88 | AO330: FALSE | AP330: 12533.87 | AQ330: 16843.21 | AR330: 12384.1 | AS330: 12533.87 | AT330: 13811.43 | AU330: 3.53 | AV330: 0.01 | AW330: 0.23 | AX330: 0.2 | AY330: 0.31 | AZ330: 0 | BA330: 0.57 | BB330: 0.79 | BC330: 0 | BD330: 5592.2 | BE330: 11.64 | BF330: 362.6 | BG330: 316.54 | BH330: 483.76 | BI330: 3917.99 | BJ330: 905.8 | BK330: 793.58 | BL330: 0 | BM330: FALSE | BN330: 1440 | BO330: 18 | BP330: 3101.16 | BQ330: 793.88 | BR330: 1585.47 | BS330: 29283.6 | BT330: 27339.13 | BU330: 791.59 | BV330: 0.01 | BW330: 0.23 | BX330: 0.31 | BY330: 0.2 | BZ330: null | CA330: 0 | CB330: 0 | CC330: 0 | CD330: 18 | CE330: 0 | CF330: 0 | CG330: 0 | CH330: 0.57 | CI330: 40.22 | CJ330: 0 | CK330: 475.56 | CL330: 1923.76 | CM330: 202400 | CN330: 4 | CO330: 29283.6 | CP330: 5764.17 | CQ330: 0.79 | CR330: 0.74 | CS330: Região: NE | CT330: 0 | CU330: 0 | CV330: 60 | CW330: 60 | CX330: 60 | CY330: 181.3 | CZ330: 60 | DA330: 1585.47 | DB330: TRUE | DC330: FALSE | DD330: Cargo: MODELO EQUIPE ATIVA ATUAL | DE330: 3 | DF330: 60 | DG330: 202400 | DH330: 76031a85-ba82-4bd8-a699-80358c7a5f65
A331: =F331&"x"&W331&"x"&S331 -> BR04xBR04x29021163.0 | B331: =F331&"x"&W331&"x"&S331&Q331 -> BR04xBR04x29021163.0Pallets: 42 | C331: EMPURRADA_1_9_2026 | D331: 07526557001505_CERV | E331: CAMAÇARI | F331: BR04 | I331: Geo NE | J331: 20618821000799 | K331: OPERALOG | L331: 390268 | N331: 1 | Q331: Pallets: 42 | R331: Unidade: 10260909-SENDAS DISTRIBUIDORA SA(S4) | S331: 29021163.0 | T331: 787280.0 | U331: FALSE | V331: Unidade: CERVEJARIA CAMAÇARI | Região: NE | W331: BR04 | X331: 421 | Y331: 12500 | Z331: 2217.92 | AA331: 2339.22 | AB331: 1440 | AC331: 36000 | AD331: CERVEJARIA CAMAÇARI_10260909-SENDAS DISTRIBUIDORA SA(S4)_42_false | AE331: null | AF331: null | AG331: 1.92 | AH331: 115.5 | AI331: 0 | AJ331: 25 | AK331: 3.53 | AL331: 1.92 | AM331: 3 | AN331: 2.88 | AO331: FALSE | AP331: 17949.99 | AQ331: 22476.82 | AR331: 17749.95 | AS331: 17949.99 | AT331: 19779.6 | AU331: 3.53 | AV331: 0.01 | AW331: 0.22 | AX331: 0.2 | AY331: 0.31 | AZ331: 0 | BA331: 0.57 | BB331: 0.77 | BC331: 0 | BD331: 7399.69 | BE331: 15.14 | BF331: 464.31 | BG331: 418.85 | BH331: 640.11 | BI331: 6581.24 | BJ331: 1198.57 | BK331: 1032.04 | BL331: 0 | BM331: FALSE | BN331: 1440 | BO331: 12 | BP331: 2735.24 | BQ331: 1052.08 | BR331: 2097.92 | BS331: 29795.7 | BT331: 28250.65 | BU331: 1045.84 | BV331: 0.01 | BW331: 0.22 | BX331: 0.31 | BY331: 0.2 | BZ331: null | CA331: 0 | CB331: 0 | CC331: 0 | CD331: 12 | CE331: 0 | CF331: 0 | CG331: 0 | CH331: 0.57 | CI331: 40.22 | CJ331: 0 | CK331: 475.56 | CL331: 1923.76 | CM331: 202400 | CN331: 4 | CO331: 29795.7 | CP331: 5764.17 | CQ331: 0.77 | CR331: 0.57 | CS331: Região: NE | CT331: 0 | CU331: 0 | CV331: 60 | CW331: 60 | CX331: 60 | CY331: 181.3 | CZ331: 60 | DA331: 2097.92 | DB331: TRUE | DC331: FALSE | DD331: Cargo: MODELO EQUIPE ATIVA ATUAL | DE331: 3 | DF331: 60 | DG331: 202400 | DH331: 944d2a9b-54fc-4a29-8a35-7bbca442fa6e
A332: =F332&"x"&W332&"x"&S332 -> BR04xBR04x29015404.0 | B332: =F332&"x"&W332&"x"&S332&Q332 -> BR04xBR04x29015404.0Pallets: 42 | C332: EMPURRADA_1_9_2026 | D332: 07526557001505_CERV | E332: CAMAÇARI | F332: BR04 | I332: Geo NE | J332: 20618821000799 | K332: OPERALOG | L332: 390268 | N332: 1 | Q332: Pallets: 42 | R332: Unidade: 10258088-EXPRESSO DISTRIBUICAO E VAREJO LTDA(S4) | Região: 0 | S332: 29015404.0 | T332: 728063.0 | U332: FALSE | V332: Unidade: CERVEJARIA CAMAÇARI | Região: NE | W332: BR04 | X332: 421 | Y332: 12500 | Z332: 2205.37 | AA332: 2326.67 | AB332: 1440 | AC332: 36000 | AD332: CERVEJARIA CAMAÇARI_10258088-EXPRESSO DISTRIBUICAO E VAREJO LTDA(S4)_42_false | AE332: null | AF332: null | AG332: 1.92 | AH332: 115.5 | AI332: 0 | AJ332: 25 | AK332: 3.53 | AL332: 1.92 | AM332: 3 | AN332: 2.88 | AO332: FALSE | AP332: 17718.58 | AQ332: 22187.06 | AR332: 17521.13 | AS332: 17718.58 | AT332: 19524.61 | AU332: 3.53 | AV332: 0.01 | AW332: 0.22 | AX332: 0.2 | AY332: 0.31 | AZ332: 0 | BA332: 0.57 | BB332: 0.77 | BC332: 0 | BD332: 7355.42 | BE332: 15.05 | BF332: 461.82 | BG332: 416.34 | BH332: 636.28 | BI332: 6418.6 | BJ332: 1191.4 | BK332: 1026.2 | BL332: 0 | BM332: FALSE | BN332: 1440 | BO332: 12 | BP332: 2699.97 | BQ332: 1045.86 | BR332: 2085.37 | BS332: 29786 | BT332: 28233.12 | BU332: 1039.51 | BV332: 0.01 | BW332: 0.22 | BX332: 0.31 | BY332: 0.2 | BZ332: null | CA332: 0 | CB332: 0 | CC332: 0 | CD332: 12 | CE332: 0 | CF332: 0 | CG332: 0 | CH332: 0.57 | CI332: 40.22 | CJ332: 0 | CK332: 475.56 | CL332: 1923.76 | CM332: 202400 | CN332: 4 | CO332: 29786 | CP332: 5764.17 | CQ332: 0.77 | CR332: 0.57 | CS332: Região: NE | CT332: 0 | CU332: 0 | CV332: 60 | CW332: 60 | CX332: 60 | CY332: 181.3 | CZ332: 60 | DA332: 2085.37 | DB332: TRUE | DC332: FALSE | DD332: Cargo: MODELO EQUIPE ATIVA ATUAL | DE332: 3 | DF332: 60 | DG332: 202400 | DH332: 2e0dd2ca-d9d8-4db2-a6b5-2bd341b600c1
A333: =F333&"x"&W333&"x"&S333 -> BR04xBR04x29035220.0 | B333: =F333&"x"&W333&"x"&S333&Q333 -> BR04xBR04x29035220.0Pallets: 42 | C333: EMPURRADA_1_9_2026 | D333: 07526557001505_CERV | E333: CAMAÇARI | F333: BR04 | I333: Geo NE | J333: 20618821000799 | K333: OPERALOG | L333: 390268 | N333: 1 | Q333: Pallets: 42 | R333: Unidade: 10275309-SENDAS DISTRIBUIDORA SA(S4) | Região: 0 | S333: 29035220.0 | T333: 895334.0 | U333: FALSE | V333: Unidade: CERVEJARIA CAMAÇARI | Região: NE | W333: BR04 | X333: 421 | Y333: 12500 | Z333: 852.36 | AA333: 973.66 | AB333: 1440 | AC333: 36000 | AD333: CERVEJARIA CAMAÇARI_10275309-SENDAS DISTRIBUIDORA SA(S4)_42_false | AE333: null | AF333: null | AG333: 1.92 | AH333: 115.5 | AI333: 0 | AJ333: 25 | AK333: 3.53 | AL333: 1.92 | AM333: 3 | AN333: 2.88 | AO333: FALSE | AP333: 6651.14 | AQ333: 8937.91 | AR333: 6571.66 | AS333: 6651.14 | AT333: 7329.08 | AU333: 3.53 | AV333: 0.01 | AW333: 0.26 | AX333: 0.2 | AY333: 0.31 | AZ333: 0 | BA333: 0.57 | BB333: 0.85 | BC333: 0 | BD333: 2583.15 | BE333: 5.82 | BF333: 193.26 | BG333: 146.22 | BH333: 223.46 | BI333: 2604.74 | BJ333: 418.41 | BK333: 396.62 | BL333: 0 | BM333: FALSE | BN333: 1440 | BO333: 18 | BP333: 1645.64 | BQ333: 366.5 | BR333: 732.36 | BS333: 27065.25 | BT333: 23693.42 | BU333: 365.86 | BV333: 0.01 | BW333: 0.26 | BX333: 0.31 | BY333: 0.2 | BZ333: null | CA333: 0 | CB333: 0 | CC333: 0 | CD333: 18 | CE333: 0 | CF333: 0 | CG333: 0 | CH333: 0.57 | CI333: 40.22 | CJ333: 0 | CK333: 475.56 | CL333: 1923.76 | CM333: 202400 | CN333: 4 | CO333: 27065.25 | CP333: 5764.17 | CQ333: 0.85 | CR333: 1.48 | CS333: Região: NE | CT333: 0 | CU333: 0 | CV333: 60 | CW333: 60 | CX333: 60 | CY333: 181.3 | CZ333: 60 | DA333: 732.36 | DB333: TRUE | DC333: FALSE | DD333: Cargo: MODELO EQUIPE ATIVA ATUAL | DE333: 3 | DF333: 60 | DG333: 202400 | DH333: 752e0f84-26bc-4f22-8555-7cdbb496dd72
A334: =F334&"x"&W334&"x"&S334 -> BR04xBR04x29010563.0 | B334: =F334&"x"&W334&"x"&S334&Q334 -> BR04xBR04x29010563.0Pallets: 42 | C334: EMPURRADA_1_9_2026 | D334: 07526557001505_CERV | E334: CAMAÇARI | F334: BR04 | I334: Geo NE | J334: 20618821000799 | K334: OPERALOG | L334: 390268 | N334: 1 | Q334: Pallets: 42 | R334: Unidade: 10241322-WAL MART BRASIL LTDA(S4) | S334: 29010563.0 | T334: 610542.0 | U334: FALSE | V334: Unidade: CERVEJARIA CAMAÇARI | Região: NE | W334: BR04 | X334: 421 | Y334: 12500 | Z334: 2222.24 | AA334: 2343.54 | AB334: 1440 | AC334: 36000 | AD334: CERVEJARIA CAMAÇARI_10241322-WAL MART BRASIL LTDA(S4)_42_false | AE334: null | AF334: null | AG334: 1.92 | AH334: 115.5 | AI334: 0 | AJ334: 25 | AK334: 3.53 | AL334: 1.92 | AM334: 3 | AN334: 2.88 | AO334: FALSE | AP334: 17950.12 | AQ334: 22476.99 | AR334: 17750.09 | AS334: 17950.12 | AT334: 19779.75 | AU334: 3.53 | AV334: 0.01 | AW334: 0.22 | AX334: 0.2 | AY334: 0.31 | AZ334: 0 | BA334: 0.57 | BB334: 0.77 | BC334: 0 | BD334: 7414.92 | BE334: 15.17 | BF334: 465.17 | BG334: 419.71 | BH334: 641.43 | BI334: 6558.59 | BJ334: 1201.04 | BK334: 1034.05 | BL334: 0 | BM334: FALSE | BN334: 1440 | BO334: 12 | BP334: 2735.26 | BQ334: 1053.83 | BR334: 2102.24 | BS334: 29799.01 | BT334: 28256.64 | BU334: 1048.41 | BV334: 0.01 | BW334: 0.22 | BX334: 0.31 | BY334: 0.2 | BZ334: null | CA334: 0 | CB334: 0 | CC334: 0 | CD334: 12 | CE334: 0 | CF334: 0 | CG334: 0 | CH334: 0.57 | CI334: 40.22 | CJ334: 0 | CK334: 475.56 | CL334: 1923.76 | CM334: 202400 | CN334: 4 | CO334: 29799.01 | CP334: 5764.17 | CQ334: 0.77 | CR334: 0.57 | CS334: Região: NE | CT334: 0 | CU334: 0 | CV334: 60 | CW334: 60 | CX334: 60 | CY334: 181.3 | CZ334: 60 | DA334: 2102.24 | DB334: TRUE | DC334: FALSE | DD334: Cargo: MODELO EQUIPE ATIVA ATUAL | DE334: 3 | DF334: 60 | DG334: 202400 | DH334: e974e3ae-c158-46b2-b594-13ffeeface24
A335: =F335&"x"&W335&"x"&S335 -> BR04xBR04x29023761.0 | B335: =F335&"x"&W335&"x"&S335&Q335 -> BR04xBR04x29023761.0Pallets: 42 | C335: EMPURRADA_1_9_2026 | D335: 07526557001505_CERV | E335: CAMAÇARI | F335: BR04 | I335: Geo NE | J335: 20618821000799 | K335: OPERALOG | L335: 390268 | N335: 1 | Q335: Pallets: 42 | R335: Unidade: 10262647-CENTRAL DISTRIBUICAO REDE MAIS LTDA(S4) | Região: 0 | S335: 29023761.0 | T335: 821977.0 | U335: FALSE | V335: Unidade: CERVEJARIA CAMAÇARI | Região: NE | W335: BR04 | X335: 421 | Y335: 12500 | Z335: 2222.6 | AA335: 2343.9 | AB335: 1440 | AC335: 36000 | AD335: CERVEJARIA CAMAÇARI_10262647-CENTRAL DISTRIBUICAO REDE MAIS LTDA(S4)_42_false | AE335: null | AF335: null | AG335: 1.92 | AH335: 115.5 | AI335: 0 | AJ335: 25 | AK335: 3.53 | AL335: 1.92 | AM335: 3 | AN335: 2.88 | AO335: FALSE | AP335: 17950.14 | AQ335: 22477 | AR335: 17750.1 | AS335: 17950.14 | AT335: 19779.76 | AU335: 3.53 | AV335: 0.01 | AW335: 0.22 | AX335: 0.2 | AY335: 0.31 | AZ335: 0 | BA335: 0.57 | BB335: 0.77 | BC335: 0 | BD335: 7416.19 | BE335: 15.17 | BF335: 465.24 | BG335: 419.78 | BH335: 641.54 | BI335: 6556.71 | BJ335: 1201.24 | BK335: 1034.21 | BL335: 0 | BM335: FALSE | BN335: 1440 | BO335: 12 | BP335: 2735.26 | BQ335: 1053.95 | BR335: 2102.6 | BS335: 29799.29 | BT335: 28257.14 | BU335: 1048.65 | BV335: 0.01 | BW335: 0.22 | BX335: 0.31 | BY335: 0.2 | BZ335: null | CA335: 0 | CB335: 0 | CC335: 0 | CD335: 12 | CE335: 0 | CF335: 0 | CG335: 0 | CH335: 0.57 | CI335: 40.22 | CJ335: 0 | CK335: 475.56 | CL335: 1923.76 | CM335: 202400 | CN335: 4 | CO335: 29799.29 | CP335: 5764.17 | CQ335: 0.77 | CR335: 0.57 | CS335: Região: NE | CT335: 0 | CU335: 0 | CV335: 60 | CW335: 60 | CX335: 60 | CY335: 181.3 | CZ335: 60 | DA335: 2102.6 | DB335: TRUE | DC335: FALSE | DD335: Cargo: MODELO EQUIPE ATIVA ATUAL | DE335: 3 | DF335: 60 | DG335: 202400 | DH335: e85c5f95-3fce-41f8-918d-94d539769545
A336: =F336&"x"&W336&"x"&S336 -> BR04xBR04x29033672.0 | B336: =F336&"x"&W336&"x"&S336&Q336 -> BR04xBR04x29033672.0Pallets: 42 | C336: EMPURRADA_1_9_2026 | D336: 07526557001505_CERV | E336: CAMAÇARI | F336: BR04 | I336: Geo NE | J336: 20618821000799 | K336: OPERALOG | L336: 390268 | N336: 1 | Q336: Pallets: 42 | R336: Unidade: 10273857-ATACADAO S A(S4) | Região: 0 | S336: 29033672.0 | T336: 878588.0 | U336: FALSE | V336: Unidade: CERVEJARIA CAMAÇARI | Região: NE | W336: BR04 | X336: 421 | Y336: 12500 | Z336: 269.69 | AA336: 390.99 | AB336: 1440 | AC336: 36000 | AD336: CERVEJARIA CAMAÇARI_10273857-ATACADAO S A(S4)_42_false | AE336: null | AF336: null | AG336: 1.92 | AH336: 0 | AI336: 31 | AJ336: 25 | AK336: 3.53 | AL336: 1.92 | AM336: 3 | AN336: 2.88 | AO336: FALSE | AP336: 2556.39 | AQ336: 3435.31 | AR336: 2525.84 | AS336: 2556.39 | AT336: 2816.96 | AU336: 3.53 | AV336: 0.01 | AW336: 0.52 | AX336: 0.2 | AY336: 0.31 | AZ336: 0 | BA336: 0.57 | BB336: 1.32 | BC336: 0 | BD336: 527.98 | BE336: 1.84 | BF336: 77.61 | BG336: 29.89 | BH336: 45.67 | BI336: 1631.84 | BJ336: 85.52 | BK336: 125.49 | BL336: 0 | BM336: FALSE | BN336: 1440 | BO336: 18 | BP336: 632.51 | BQ336: 74.56 | BR336: 149.69 | BS336: 17483.91 | BT336: 12059.73 | BU336: 75.13 | BV336: 0.01 | BW336: 0.52 | BX336: 0.31 | BY336: 0.2 | BZ336: null | CA336: 0 | CB336: 0 | CC336: 0 | CD336: 18 | CE336: 0 | CF336: 0 | CG336: 0 | CH336: 0.57 | CI336: 40.22 | CJ336: 0 | CK336: 475.56 | CL336: 1923.76 | CM336: 202400 | CN336: 4 | CO336: 17483.91 | CP336: 5764.17 | CQ336: 1.32 | CR336: 4.67 | CS336: Região: NE | CT336: 0 | CU336: 0 | CV336: 60 | CW336: 60 | CX336: 60 | CY336: 181.3 | CZ336: 60 | DA336: 149.69 | DB336: FALSE | DC336: TRUE | DD336: Cargo: MODELO EQUIPE ATIVA ATUAL | DE336: 3 | DF336: 60 | DG336: 202400 | DH336: 0772fc2f-3bdd-4324-841c-0ea830c3755f
A337: =F337&"x"&W337&"x"&S337 -> BR04xBR04x29012277.0 | B337: =F337&"x"&W337&"x"&S337&Q337 -> BR04xBR04x29012277.0Pallets: 42 | C337: EMPURRADA_1_9_2026 | D337: 07526557001505_CERV | E337: CAMAÇARI | F337: BR04 | I337: Geo NE | J337: 20618821000799 | K337: OPERALOG | L337: 390268 | N337: 1 | Q337: Pallets: 42 | R337: Unidade: 10244583-ATACADAO S A(S4) | S337: 29012277.0 | T337: 540706.0 | U337: FALSE | V337: Unidade: CERVEJARIA CAMAÇARI | Região: NE | W337: BR04 | X337: 421 | Y337: 12500 | Z337: 2222.24 | AA337: 2343.54 | AB337: 1440 | AC337: 36000 | AD337: CERVEJARIA CAMAÇARI_10244583-ATACADAO S A(S4)_42_false | AE337: null | AF337: null | AG337: 1.92 | AH337: 115.5 | AI337: 0 | AJ337: 25 | AK337: 3.53 | AL337: 1.92 | AM337: 3 | AN337: 2.88 | AO337: FALSE | AP337: 17950.12 | AQ337: 22476.99 | AR337: 17750.09 | AS337: 17950.12 | AT337: 19779.75 | AU337: 3.53 | AV337: 0.01 | AW337: 0.22 | AX337: 0.2 | AY337: 0.31 | AZ337: 0 | BA337: 0.57 | BB337: 0.77 | BC337: 0 | BD337: 7414.92 | BE337: 15.17 | BF337: 465.17 | BG337: 419.71 | BH337: 641.43 | BI337: 6558.59 | BJ337: 1201.04 | BK337: 1034.05 | BL337: 0 | BM337: FALSE | BN337: 1440 | BO337: 12 | BP337: 2735.26 | BQ337: 1054.69 | BR337: 2102.24 | BS337: 29799.01 | BT337: 28256.64 | BU337: 1047.55 | BV337: 0.01 | BW337: 0.22 | BX337: 0.31 | BY337: 0.2 | BZ337: null | CA337: 0 | CB337: 0 | CC337: 0 | CD337: 12 | CE337: 0 | CF337: 0 | CG337: 0 | CH337: 0.57 | CI337: 40.22 | CJ337: 0 | CK337: 475.56 | CL337: 1923.76 | CM337: 202400 | CN337: 4 | CO337: 29799.01 | CP337: 5764.17 | CQ337: 0.77 | CR337: 0.57 | CS337: Região: NE | CT337: 0 | CU337: 0 | CV337: 60 | CW337: 60 | CX337: 60 | CY337: 181.3 | CZ337: 60 | DA337: 2102.24 | DB337: TRUE | DC337: FALSE | DD337: Cargo: MODELO EQUIPE ATIVA ATUAL | DE337: 3 | DF337: 60 | DG337: 202400 | DH337: e6acbd4a-dd5b-4865-b401-b42ec9edcd8e
A338: =F338&"x"&W338&"x"&S338 -> BR04xBR04x29006255.0 | B338: =F338&"x"&W338&"x"&S338&Q338 -> BR04xBR04x29006255.0Pallets: 42 | C338: EMPURRADA_1_9_2026 | D338: 07526557001505_CERV | E338: CAMAÇARI | F338: BR04 | I338: Geo NE | J338: 20618821000799 | K338: OPERALOG | L338: 390268 | N338: 1 | Q338: Pallets: 42 | R338: Unidade: 10242661-WMS SUPERMERCADOS DO BRASIL LTDA(S4) | S338: 29006255.0 | T338: 684252.0 | U338: FALSE | V338: Unidade: CERVEJARIA CAMAÇARI | Região: NE | W338: BR04 | X338: 421 | Y338: 12500 | Z338: 2213.02 | AA338: 2334.32 | AB338: 1440 | AC338: 36000 | AD338: CERVEJARIA CAMAÇARI_10242661-WMS SUPERMERCADOS DO BRASIL LTDA(S4)_42_false | AE338: null | AF338: null | AG338: 1.92 | AH338: 115.5 | AI338: 0 | AJ338: 25 | AK338: 3.53 | AL338: 1.92 | AM338: 3 | AN338: 2.88 | AO338: FALSE | AP338: 17835.18 | AQ338: 22333.05 | AR338: 17636.42 | AS338: 17835.18 | AT338: 19653.09 | AU338: 3.53 | AV338: 0.01 | AW338: 0.22 | AX338: 0.2 | AY338: 0.31 | AZ338: 0 | BA338: 0.57 | BB338: 0.77 | BC338: 0 | BD338: 7382.4 | BE338: 15.1 | BF338: 463.34 | BG338: 417.87 | BH338: 638.62 | BI338: 6493.55 | BJ338: 1195.77 | BK338: 1029.76 | BL338: 0 | BM338: FALSE | BN338: 1440 | BO338: 12 | BP338: 2717.74 | BQ338: 1053.49 | BR338: 2093.02 | BS338: 29791.93 | BT338: 28243.83 | BU338: 1039.53 | BV338: 0.01 | BW338: 0.22 | BX338: 0.31 | BY338: 0.2 | BZ338: null | CA338: 0 | CB338: 0 | CC338: 0 | CD338: 12 | CE338: 0 | CF338: 0 | CG338: 0 | CH338: 0.57 | CI338: 40.22 | CJ338: 0 | CK338: 475.56 | CL338: 1923.76 | CM338: 202400 | CN338: 4 | CO338: 29791.93 | CP338: 5764.17 | CQ338: 0.77 | CR338: 0.57 | CS338: Região: NE | CT338: 0 | CU338: 0 | CV338: 60 | CW338: 60 | CX338: 60 | CY338: 181.3 | CZ338: 60 | DA338: 2093.02 | DB338: TRUE | DC338: FALSE | DD338: Cargo: MODELO EQUIPE ATIVA ATUAL | DE338: 3 | DF338: 60 | DG338: 202400 | DH338: 4f2e7713-1db5-461c-9689-14a49af7f3b3
... A382: =F382&"x"&W382&"x"&S382 -> BR04xBR04x29005327.0 | B382: =F382&"x"&W382&"x"&S382&Q382 -> BR04xBR04x29005327.0Pallets: 42 | C382: EMPURRADA_1_9_2026 | D382: 07526557001505_CERV | E382: CAMAÇARI | F382: BR04 | I382: Geo NE | J382: 20618821000799 | K382: OPERALOG | L382: 390268 | N382: 1 | Q382: Pallets: 42 | R382: Unidade: 10241014-ITAO SUPERMERCADOS IMPORTACOES E(S4) | Região: 0 | S382: 29005327.0 | T382: 695785.0 | U382: FALSE | V382: Unidade: CERVEJARIA CAMAÇARI | Região: NE | W382: BR04 | X382: 421 | Y382: 12500 | Z382: 971.64 | AA382: 1092.94 | AB382: 1440 | AC382: 36000 | AD382: CERVEJARIA CAMAÇARI_10241014-ITAO SUPERMERCADOS IMPORTACOES E(S4)_42_false | AE382: null | AF382: null | AG382: 1.92 | AH382: 115.5 | AI382: 0 | AJ382: 25 | AK382: 3.53 | AL382: 1.92 | AM382: 3 | AN382: 2.88 | AO382: FALSE | AP382: 7375.39 | AQ382: 9911.17 | AR382: 7287.26 | AS382: 7375.39 | AT382: 8127.16 | AU382: 3.53 | AV382: 0.01 | AW382: 0.25 | AX382: 0.2 | AY382: 0.31 | AZ382: 0 | BA382: 0.57 | BB382: 0.84 | BC382: 0 | BD382: 3003.87 | BE382: 6.63 | BF382: 216.94 | BG382: 170.03 | BH382: 259.85 | BI382: 2691.27 | BJ382: 486.55 | BK382: 452.12 | BL382: 0 | BM382: FALSE | BN382: 1440 | BO382: 18 | BP382: 1824.84 | BQ382: 426.85 | BR382: 851.64 | BS382: 27609.67 | BT382: 24545.41 | BU382: 424.79 | BV382: 0.01 | BW382: 0.25 | BX382: 0.31 | BY382: 0.2 | BZ382: null | CA382: 0 | CB382: 0 | CC382: 0 | CD382: 18 | CE382: 0 | CF382: 0 | CG382: 0 | CH382: 0.57 | CI382: 40.22 | CJ382: 0 | CK382: 475.56 | CL382: 1923.76 | CM382: 202400 | CN382: 4 | CO382: 27609.67 | CP382: 5764.17 | CQ382: 0.84 | CR382: 1.3 | CS382: Região: NE | CT382: 0 | CU382: 0 | CV382: 60 | CW382: 60 | CX382: 60 | CY382: 181.3 | CZ382: 60 | DA382: 851.64 | DB382: TRUE | DC382: FALSE | DD382: Cargo: MODELO EQUIPE ATIVA ATUAL | DE382: 3 | DF382: 60 | DG382: 202400 | DH382: b1bc592b-435d-4a26-ab6f-434cb40a7b0b
A383: =F383&"x"&W383&"x"&S383 -> BR04xBR04xBR06 | B383: =F383&"x"&W383&"x"&S383&Q383 -> BR04xBR04xBR06Pallets: 28 | C383: EMPURRADA_1_9_2026 | D383: 07526557001505_CERV | E383: CAMAÇARI | F383: BR04 | I383: Geo NE | J383: 20618821000799 | K383: OPERALOG | L383: 390268 | N383: 1 | Q383: Pallets: 28 | R383: Unidade: CDR JOAO PESSOA | Região: NE | S383: BR06 | T383: 426 | U383: FALSE | V383: Unidade: CERVEJARIA CAMAÇARI | Região: NE | W383: BR04 | X383: 421 | Y383: 12500 | Z383: 4272.94 | AA383: 4570.02 | AB383: 1440 | AC383: 36000 | AD383: CERVEJARIA CAMAÇARI_CDR JOAO PESSOA_28_false | AG383: 1.92 | AH383: 115.5 | AI383: 0 | AJ383: 25 | AK383: 3.53 | AL383: 1.92 | AM383: 3 | AN383: 2.88 | AO383: FALSE | AP383: 10778.29 | AQ383: 13496.48 | AR383: 10658.18 | AS383: 10778.29 | AT383: 11876.9 | AU383: 3.53 | AV383: 0.02 | AW383: 0.51 | AX383: 0.1 | AY383: 0.31 | AZ383: 0 | BA383: 0.39 | BB383: 1.06 | BC383: 0 | BD383: 6225.43 | BE383: 29.16 | BF383: 907.11 | BG383: 176.19 | BH383: 538.53 | BI383: 860.49 | BJ383: 684.79 | BK383: 1236.47 | BL383: 0 | BM383: FALSE | BN383: 1440 | BO383: 12 | BP383: 1642.41 | BQ383: 882.5 | BR383: 1765 | BS383: 13011.53 | BT383: 12165.7 | BU383: 882.5 | BV383: 0.02 | BW383: 0.51 | BX383: 0.31 | BY383: 0.1 | CA383: 0 | CB383: 0 | CC383: 0 | CD383: 12 | CE383: 0 | CF383: 0 | CG383: 0 | CH383: 0.39 | CI383: 28.22 | CJ383: 0 | CK383: 437.68 | CL383: 1907.11 | CM383: 202400 | CN383: 3 | CO383: 13011.53 | CP383: 4611.33 | CQ383: 1.06 | CR383: 0.29 | CS383: Região: NE | CT383: 0 | CU383: 0 | CV383: 60 | CW383: 245.83 | CX383: 60 | CY383: 171.25 | CZ383: 60 | DA383: 4152.94 | DB383: TRUE | DC383: FALSE | DD383: Cargo: MODELO EQUIPE ATIVA ATUAL | DE383: 3 | DF383: 25.5 | DG383: 202400 | DH383: 13d43c47-0506-4dfa-8b70-e5a32f31249c
A384: =F384&"x"&W384&"x"&S384 -> BR04xBR5DxBR06 | B384: =F384&"x"&W384&"x"&S384&Q384 -> BR04xBR5DxBR06Pallets: 42 | C384: EMPURRADA_1_9_2026 | D384: 07526557001505_CERV | E384: CAMAÇARI | F384: BR04 | I384: Geo NE | J384: 20618821000799 | K384: OPERALOG | L384: 390268 | N384: 1 | Q384: Pallets: 42 | R384: Unidade: CDR JOAO PESSOA | Região: NE | S384: BR06 | T384: 426 | U384: FALSE | V384: Unidade: CDR BAHIA | Região: NE | W384: BR5D | X384: 505 | Y384: 12500 | Z384: 1890.2 | AA384: 2176.13 | AB384: 1440 | AC384: 36000 | AD384: CDR BAHIA_CDR JOAO PESSOA_42_false | AE384: null | AF384: null | AG384: 1.92 | AH384: 115.5 | AI384: 0 | AJ384: 25 | AK384: 3.53 | AL384: 1.92 | AM384: 3 | AN384: 2.88 | AO384: FALSE | AP384: 15016.4 | AQ384: 18803.41 | AR384: 14849.06 | AS384: 15016.4 | AT384: 16547 | AU384: 3.53 | AV384: 0.01 | AW384: 0.24 | AX384: 0.2 | AY384: 0.31 | AZ384: 0 | BA384: 0.57 | BB384: 0.78 | BC384: 0 | BD384: 6243.77 | BE384: 12.9 | BF384: 431.94 | BG384: 353.42 | BH384: 540.12 | BI384: 5140.04 | BJ384: 1011.34 | BK384: 1115.53 | BL384: 0 | BM384: FALSE | BN384: 1440 | BO384: 12 | BP384: 2288.21 | BQ384: 885.1 | BR384: 1770.2 | BS384: 29500.21 | BT384: 25624.07 | BU384: 885.1 | BV384: 0.01 | BW384: 0.24 | BX384: 0.31 | BY384: 0.2 | BZ384: null | CA384: 0 | CB384: 0 | CC384: 0 | CD384: 12 | CE384: 0 | CF384: 0 | CG384: 0 | CH384: 0.57 | CI384: 40.22 | CJ384: 0 | CK384: 475.56 | CL384: 1923.76 | CM384: 202400 | CN384: 4 | CO384: 29500.21 | CP384: 5764.17 | CQ384: 0.78 | CR384: 0.67 | CS384: Região: NE | CT384: 0 | CU384: 0 | CV384: 60 | CW384: 245.83 | CX384: 60 | CY384: 160.1 | CZ384: 60 | DA384: 1770.2 | DB384: TRUE | DC384: FALSE | DD384: Cargo: MODELO EQUIPE ATIVA ATUAL | DE384: 3 | DF384: 60 | DG384: 202400 | DH384: 4fc107fc-da6c-4a39-b43c-50ef37747256
A385: =F385&"x"&W385&"x"&S385 -> BR04xBR04x29021219.0 | B385: =F385&"x"&W385&"x"&S385&Q385 -> BR04xBR04x29021219.0Pallets: 42 | C385: EMPURRADA_1_9_2026 | D385: 07526557001505_CERV | E385: CAMAÇARI | F385: BR04 | I385: Geo NE | J385: 20618821000799 | K385: OPERALOG | L385: 390268 | N385: 1 | Q385: Pallets: 42 | R385: Unidade: 10260957-SENDAS DISTRIBUIDORA SA(S4) | Região: 0 | S385: 29021219.0 | T385: 787957.0 | U385: FALSE | V385: Unidade: CERVEJARIA CAMAÇARI | Região: NE | W385: BR04 | X385: 421 | Y385: 12500 | Z385: 1893.32 | AA385: 2014.62 | AB385: 1440 | AC385: 36000 | AD385: CERVEJARIA CAMAÇARI_10260957-SENDAS DISTRIBUIDORA SA(S4)_42_false | AE385: null | AF385: null | AG385: 1.92 | AH385: 115.5 | AI385: 0 | AJ385: 25 | AK385: 3.53 | AL385: 1.92 | AM385: 3 | AN385: 2.88 | AO385: FALSE | AP385: 15333.19 | AQ385: 19200.09 | AR385: 15162.32 | AS385: 15333.19 | AT385: 16896.08 | AU385: 3.53 | AV385: 0.01 | AW385: 0.23 | AX385: 0.2 | AY385: 0.31 | AZ385: 0 | BA385: 0.57 | BB385: 0.78 | BC385: 0 | BD385: 6254.77 | BE385: 12.92 | BF385: 399.88 | BG385: 354.04 | BH385: 541.07 | BI385: 5705.51 | BJ385: 1013.12 | BK385: 880.99 | BL385: 0 | BM385: FALSE | BN385: 1440 | BO385: 12 | BP385: 2336.49 | BQ385: 888.63 | BR385: 1773.32 | BS385: 29503.51 | BT385: 27727.1 | BU385: 884.69 | BV385: 0.01 | BW385: 0.23 | BX385: 0.31 | BY385: 0.2 | BZ385: null | CA385: 0 | CB385: 0 | CC385: 0 | CD385: 12 | CE385: 0 | CF385: 0 | CG385: 0 | CH385: 0.57 | CI385: 40.22 | CJ385: 0 | CK385: 475.56 | CL385: 1923.76 | CM385: 202400 | CN385: 4 | CO385: 29503.51 | CP385: 5764.17 | CQ385: 0.78 | CR385: 0.67 | CS385: Região: NE | CT385: 0 | CU385: 0 | CV385: 60 | CW385: 60 | CX385: 60 | CY385: 181.3 | CZ385: 60 | DA385: 1773.32 | DB385: TRUE | DC385: FALSE | DD385: Cargo: MODELO EQUIPE ATIVA ATUAL | DE385: 3 | DF385: 60 | DG385: 202400 | DH385: 50d100ce-13ac-4852-8302-54200f958a44
A386: =F386&"x"&W386&"x"&S386 -> BR04xBR04x29005276.0 | B386: =F386&"x"&W386&"x"&S386&Q386 -> BR04xBR04x29005276.0Pallets: 42 | C386: EMPURRADA_1_9_2026 | D386: 07526557001505_CERV | E386: CAMAÇARI | F386: BR04 | I386: Geo NE | J386: 20618821000799 | K386: OPERALOG | L386: 390268 | N386: 1 | Q386: Pallets: 42 | R386: Unidade: 10241896-ATACADAO S A(S4) | Região: 0 | S386: 29005276.0 | T386: 650773.0 | U386: FALSE | V386: Unidade: CERVEJARIA CAMAÇARI | Região: NE | W386: BR04 | X386: 421 | Y386: 12500 | Z386: 1894.41 | AA386: 2015.71 | AB386: 1440 | AC386: 36000 | AD386: CERVEJARIA CAMAÇARI_10241896-ATACADAO S A(S4)_42_false | AE386: null | AF386: null | AG386: 1.92 | AH386: 115.5 | AI386: 0 | AJ386: 25 | AK386: 3.53 | AL386: 1.92 | AM386: 3 | AN386: 2.88 | AO386: FALSE | AP386: 15333.23 | AQ386: 19200.13 | AR386: 15162.35 | AS386: 15333.23 | AT386: 16896.12 | AU386: 3.53 | AV386: 0.01 | AW386: 0.23 | AX386: 0.2 | AY386: 0.31 | AZ386: 0 | BA386: 0.57 | BB386: 0.78 | BC386: 0 | BD386: 6258.62 | BE386: 12.93 | BF386: 400.1 | BG386: 354.26 | BH386: 541.4 | BI386: 5699.79 | BJ386: 1013.74 | BK386: 881.5 | BL386: 0 | BM386: FALSE | BN386: 1440 | BO386: 12 | BP386: 2336.49 | BQ386: 888.89 | BR386: 1774.41 | BS386: 29504.66 | BT386: 27729.15 | BU386: 885.52 | BV386: 0.01 | BW386: 0.23 | BX386: 0.31 | BY386: 0.2 | BZ386: null | CA386: 0 | CB386: 0 | CC386: 0 | CD386: 12 | CE386: 0 | CF386: 0 | CG386: 0 | CH386: 0.57 | CI386: 40.22 | CJ386: 0 | CK386: 475.56 | CL386: 1923.76 | CM386: 202400 | CN386: 4 | CO386: 29504.66 | CP386: 5764.17 | CQ386: 0.78 | CR386: 0.67 | CS386: Região: NE | CT386: 0 | CU386: 0 | CV386: 60 | CW386: 60 | CX386: 60 | CY386: 181.3 | CZ386: 60 | DA386: 1774.41 | DB386: TRUE | DC386: FALSE | DD386: Cargo: MODELO EQUIPE ATIVA ATUAL | DE386: 3 | DF386: 60 | DG386: 202400 | DH386: e4e09ca2-95ab-4141-b547-c9308101b46b
A387: =F387&"x"&W387&"x"&S387 -> BR04xBR04x29001884.0 | B387: =F387&"x"&W387&"x"&S387&Q387 -> BR04xBR04x29001884.0Pallets: 42 | C387: EMPURRADA_1_9_2026 | D387: 07526557001505_CERV | E387: CAMAÇARI | F387: BR04 | I387: Geo NE | J387: 20618821000799 | K387: OPERALOG | L387: 390268 | N387: 1 | Q387: Pallets: 42 | R387: Unidade: 10242014-ATACADAO S A(S4) | Região: 0 | S387: 29001884.0 | T387: 667439.0 | U387: FALSE | V387: Unidade: CERVEJARIA CAMAÇARI | Região: NE | W387: BR04 | X387: 421 | Y387: 12500 | Z387: 988.83 | AA387: 1110.13 | AB387: 1440 | AC387: 36000 | AD387: CERVEJARIA CAMAÇARI_10242014-ATACADAO S A(S4)_42_false | AE387: null | AF387: null | AG387: 1.92 | AH387: 115.5 | AI387: 0 | AJ387: 25 | AK387: 3.53 | AL387: 1.92 | AM387: 3 | AN387: 2.88 | AO387: FALSE | AP387: 7531.64 | AQ387: 10121.13 | AR387: 7441.64 | AS387: 7531.64 | AT387: 8299.33 | AU387: 3.53 | AV387: 0.01 | AW387: 0.25 | AX387: 0.2 | AY387: 0.31 | AZ387: 0 | BA387: 0.57 | BB387: 0.83 | BC387: 0 | BD387: 3064.5 | BE387: 6.75 | BF387: 220.35 | BG387: 173.46 | BH387: 265.1 | BI387: 2754.99 | BJ387: 496.37 | BK387: 460.12 | BL387: 0 | BM387: FALSE | BN387: 1440 | BO387: 18 | BP387: 1863.5 | BQ387: 434.17 | BR387: 868.83 | BS387: 27677.3 | BT387: 24653.1 | BU387: 434.66 | BV387: 0.01 | BW387: 0.25 | BX387: 0.31 | BY387: 0.2 | BZ387: null | CA387: 0 | CB387: 0 | CC387: 0 | CD387: 18 | CE387: 0 | CF387: 0 | CG387: 0 | CH387: 0.57 | CI387: 40.22 | CJ387: 0 | CK387: 475.56 | CL387: 1923.76 | CM387: 202400 | CN387: 4 | CO387: 27677.3 | CP387: 5764.17 | CQ387: 0.83 | CR387: 1.27 | CS387: Região: NE | CT387: 0 | CU387: 0 | CV387: 60 | CW387: 60 | CX387: 60 | CY387: 181.3 | CZ387: 60 | DA387: 868.83 | DB387: TRUE | DC387: FALSE | DD387: Cargo: MODELO EQUIPE ATIVA ATUAL | DE387: 3 | DF387: 60 | DG387: 202400 | DH387: c43a500d-d9a0-4075-b603-cb9764631624
A388: =F388&"x"&W388&"x"&S388 -> BR04xBR04x29032672.0 | B388: =F388&"x"&W388&"x"&S388&Q388 -> BR04xBR04x29032672.0Pallets: 42 | C388: EMPURRADA_1_9_2026 | D388: 07526557001505_CERV | E388: CAMAÇARI | F388: BR04 | I388: Geo NE | J388: 20618821000799 | K388: OPERALOG | L388: 390268 | N388: 1 | Q388: Pallets: 42 | R388: Unidade: 10273015-CARDOSO DA COSTA & CIA LTDA(S4) | Região: 0 | S388: 29032672.0 | T388: 868230.0 | U388: FALSE | V388: Unidade: CERVEJARIA CAMAÇARI | Região: NE | W388: BR04 | X388: 421 | Y388: 12500 | Z388: 1922 | AA388: 2043.3 | AB388: 1440 | AC388: 36000 | AD388: CERVEJARIA CAMAÇARI_10273015-CARDOSO DA COSTA & CIA LTDA(S4)_42_false | AE388: null | AF388: null | AG388: 1.92 | AH388: 115.5 | AI388: 0 | AJ388: 25 | AK388: 3.53 | AL388: 1.92 | AM388: 3 | AN388: 2.88 | AO388: FALSE | AP388: 15473.1 | AQ388: 19375.28 | AR388: 15300.66 | AS388: 15473.1 | AT388: 17050.24 | AU388: 3.53 | AV388: 0.01 | AW388: 0.23 | AX388: 0.2 | AY388: 0.31 | AZ388: 0 | BA388: 0.57 | BB388: 0.78 | BC388: 0 | BD388: 6355.93 | BE388: 13.12 | BF388: 405.58 | BG388: 359.77 | BH388: 549.82 | BI388: 5692.6 | BJ388: 1029.51 | BK388: 894.34 | BL388: 0 | BM388: FALSE | BN388: 1440 | BO388: 12 | BP388: 2357.81 | BQ388: 901 | BR388: 1802 | BS388: 29533.3 | BT388: 27780.06 | BU388: 901 | BV388: 0.01 | BW388: 0.23 | BX388: 0.31 | BY388: 0.2 | BZ388: null | CA388: 0 | CB388: 0 | CC388: 0 | CD388: 12 | CE388: 0 | CF388: 0 | CG388: 0 | CH388: 0.57 | CI388: 40.22 | CJ388: 0 | CK388: 475.56 | CL388: 1923.76 | CM388: 202400 | CN388: 4 | CO388: 29533.3 | CP388: 5764.17 | CQ388: 0.78 | CR388: 0.66 | CS388: Região: NE | CT388: 0 | CU388: 0 | CV388: 60 | CW388: 60 | CX388: 60 | CY388: 181.3 | CZ388: 60 | DA388: 1802 | DB388: TRUE | DC388: FALSE | DD388: Cargo: MODELO EQUIPE ATIVA ATUAL | DE388: 3 | DF388: 60 | DG388: 202400 | DH388: 8d331735-8847-425f-a9f2-0fce19f38aa7
A389: =F389&"x"&W389&"x"&S389 -> BR04xBR5DxBR2F | B389: =F389&"x"&W389&"x"&S389&Q389 -> BR04xBR5DxBR2FPallets: 42 | C389: EMPURRADA_1_9_2026 | D389: 07526557001505_CERV | E389: CAMAÇARI | F389: BR04 | I389: Geo NE | J389: 20618821000799 | K389: OPERALOG | L389: 390268 | N389: 1 | Q389: Pallets: 42 | R389: Unidade: CD ILHEUS | Região: NE | S389: BR2F | T389: 70 | U389: FALSE | V389: Unidade: CDR BAHIA | Região: NE | W389: BR5D | X389: 505 | Y389: 12500 | Z389: 981.2 | AA389: 1183.89 | AB389: 1440 | AC389: 36000 | AD389: CDR BAHIA_CD ILHEUS_42_false | AE389: null | AF389: null | AG389: 1.92 | AH389: 115.5 | AI389: 0 | AJ389: 25 | AK389: 3.53 | AL389: 1.92 | AM389: 3 | AN389: 2.88 | AO389: FALSE | AP389: 5478.9 | AQ389: 7362.63 | AR389: 5413.43 | AS389: 5478.9 | AT389: 6037.36 | AU389: 3.53 | AV389: 0.01 | AW389: 0.27 | AX389: 0.2 | AY389: 0.31 | AZ389: 0 | BA389: 0.57 | BB389: 0.83 | BC389: 0 | BD389: 3037.59 | BE389: 6.7 | BF389: 234.99 | BG389: 171.94 | BH389: 262.77 | BI389: 628.36 | BJ389: 492.02 | BK389: 579.07 | BL389: 0 | BM389: FALSE | BN389: 1440 | BO389: 18 | BP389: 1355.6 | BQ389: 430.6 | BR389: 861.2 | BS389: 27647.57 | BT389: 22914.12 | BU389: 430.6 | BV389: 0.01 | BW389: 0.27 | BX389: 0.31 | BY389: 0.2 | BZ389: null | CA389: 0 | CB389: 0 | CC389: 0 | CD389: 18 | CE389: 0 | CF389: 0 | CG389: 0 | CH389: 0.57 | CI389: 40.22 | CJ389: 0 | CK389: 475.56 | CL389: 1923.76 | CM389: 202400 | CN389: 4 | CO389: 27647.57 | CP389: 5764.17 | CQ389: 0.83 | CR389: 1.28 | CS389: Região: NE | CT389: 0 | CU389: 0 | CV389: 60 | CW389: 162.59 | CX389: 60 | CY389: 160.1 | CZ389: 60 | DA389: 861.2 | DB389: TRUE | DC389: FALSE | DD389: Cargo: MODELO EQUIPE ATIVA ATUAL | DE389: 3 | DF389: 60 | DG389: 202400 | DH389: 5062dd09-6a6c-4aff-8aa5-300a45d8682c
A390: =F390&"x"&W390&"x"&S390 -> BR04xBR04x29022696.0 | B390: =F390&"x"&W390&"x"&S390&Q390 -> BR04xBR04x29022696.0Pallets: 42 | C390: EMPURRADA_1_9_2026 | D390: 07526557001505_CERV | E390: CAMAÇARI | F390: BR04 | I390: Geo NE | J390: 20618821000799 | K390: OPERALOG | L390: 390268 | N390: 1 | Q390: Pallets: 42 | R390: Unidade: 10262021-SENDAS DISTRIBUIDORA SA(S4) | Região: 0 | S390: 29022696.0 | T390: 811653.0 | U390: FALSE | V390: Unidade: CERVEJARIA CAMAÇARI | Região: NE | W390: BR04 | X390: 421 | Y390: 12500 | Z390: 974 | AA390: 1095.3 | AB390: 1440 | AC390: 36000 | AD390: CERVEJARIA CAMAÇARI_10262021-SENDAS DISTRIBUIDORA SA(S4)_42_false | AE390: null | AF390: null | AG390: 1.92 | AH390: 115.5 | AI390: 0 | AJ390: 25 | AK390: 3.53 | AL390: 1.92 | AM390: 3 | AN390: 2.88 | AO390: FALSE | AP390: 7374.49 | AQ390: 9909.94 | AR390: 7286.36 | AS390: 7374.49 | AT390: 8126.15 | AU390: 3.53 | AV390: 0.01 | AW390: 0.25 | AX390: 0.2 | AY390: 0.31 | AZ390: 0 | BA390: 0.57 | BB390: 0.83 | BC390: 0 | BD390: 3012.19 | BE390: 6.65 | BF390: 217.41 | BG390: 170.5 | BH390: 260.57 | BI390: 2677.92 | BJ390: 487.9 | BK390: 453.22 | BL390: 0 | BM390: FALSE | BN390: 1440 | BO390: 18 | BP390: 1824.61 | BQ390: 427 | BR390: 854 | BS390: 27619.1 | BT390: 24560.39 | BU390: 427 | BV390: 0.01 | BW390: 0.25 | BX390: 0.31 | BY390: 0.2 | BZ390: null | CA390: 0 | CB390: 0 | CC390: 0 | CD390: 18 | CE390: 0 | CF390: 0 | CG390: 0 | CH390: 0.57 | CI390: 40.22 | CJ390: 0 | CK390: 475.56 | CL390: 1923.76 | CM390: 202400 | CN390: 4 | CO390: 27619.1 | CP390: 5764.17 | CQ390: 0.83 | CR390: 1.29 | CS390: Região: NE | CT390: 0 | CU390: 0 | CV390: 60 | CW390: 60 | CX390: 60 | CY390: 181.3 | CZ390: 60 | DA390: 854 | DB390: TRUE | DC390: FALSE | DD390: Cargo: MODELO EQUIPE ATIVA ATUAL | DE390: 3 | DF390: 60 | DG390: 202400 | DH390: ff75a53c-9f95-4e11-8f48-f7e64280cdcb
...
